Workbook
Name OLE_LINK1: 'P&L Отчет'!#REF!
Name База_цена: Продажи!$L$2
Name Срез_Станция_ДО: #N/A
Name Срез_Станция_ОТ: #N/A
Name Срез_Тип_пассажира: #N/A
Name Срез_Тип_полки: #N/A

Sheet Dashboard
A1: «Аналитическая модель рейса: Москва — Ростов-на-Дону». (на примере расчёта одного плацкартного вагона)
A5: Выручка | D5: ='P&L Отчет'!C6 -> 72487.75 | AX5: {="Точка роста (Макс. спрос): участок " & INDEX(Справочник!$B$2:$B$31, MATCH(MAX(Аналитика!$B$57:$AD$57), Аналитика!$B$57:$AD$57, 0)) & " — " & INDEX(Справочник!$B$2:$B$31, MATCH(MAX(Аналитика!$B$57:$AD$57), Аналитика!$B$57:$AD$57, 0) + 1) & " (загрузка " & TEXT(MAX(Аналитика!$B$57:$AD$57)/54, "0%") & ")"} -> Точка роста (Макс. спрос): участок Мичуринск-Вор. — Грязи-Воронежские (загрузка 28%)
A6: Затраты | D6: ='P&L Отчет'!C15 -> 66900 | AI6: Рентабельность | AL6: ='P&L Отчет'!C22 -> 0.077085439
A7: Чистая прибыль | D7: ='P&L Отчет'!C19 -> 5587.75 | AI7: Загрузка (Load Factor) | AL7: ='P&L Отчет'!C23 -> 0.23371648 | AX7: {="Зона риска (Мин. спрос): участок " & INDEX(Справочник!$B$2:$B$31, MATCH(MIN(Аналитика!$B$57:$AD$57), Аналитика!$B$57:$AD$57, 0)) & " — " & INDEX(Справочник!$B$2:$B$31, MATCH(MIN(Аналитика!$B$57:$AD$57), Аналитика!$B$57:$AD$57, 0) + 1) & " (загрузка " & TEXT(MIN(Аналитика!$B$57:$AD$57)/54, "0%") & ")"} -> Зона риска (Мин. спрос): участок Шахтная — Каменоломни (загрузка 19%)

Sheet Продажи
A1: ID билета | B1: Место | C1: Станция ОТ | D1: Станция ДО | E1: Индекс ОТ | F1: Индекс ДО | G1: Тип пассажира | H1: Тип полки | I1: Базовая цена, руб | J1: Сумма скидки льготникам, руб | K1: Сумма скидки тип-места, руб2 | L1: Цена, ₽ | N1: Статус места | O1: Тип полки | P1: № места | Q1: Наличие полного купе | R1: Выбор станции маршрута | S1: Наименование станций | T1: № зоны
A2: =IF(ISBLANK(Sales[[#This Row],[Место]]),"",CONCATENATE("T-00"&ROW()-1)) -> T-001 | B2: 1 | C2: Москва (Казанский) | D2: Ростов-Главный | E2: =IFERROR(_xlfn.XLOOKUP(Sales[[#This Row],[Станция ОТ]],Справочник_станций_и_сборов[Станция (остановка)],Справочник_станций_и_сборов[ID]),"") -> 1 | F2: =IFERROR(_xlfn.XLOOKUP(Sales[[#This Row],[Станция ДО]],Справочник_станций_и_сборов[Станция (остановка)],Справочник_станций_и_сборов[ID]),"") -> 30 | G2: Полный | H2: =IF(ISBLANK(Sales[[#This Row],[Место]]),"",IF(Sales[[#This Row],[Место]]>36, IF(MOD(Sales[[#This Row],[Место]],2)=0, "Верхнее боковое место", "Нижнее боковое место"), IF(MOD(Sales[[#This Row],[Место]],2)=0, "Верхнее место", "Нижнее место"))) -> Нижнее место | I2: =IFERROR(((_xlfn.XLOOKUP(Sales[[#This Row],[Станция ДО]],Справочник_станций_и_сборов[Станция (остановка)],Справочник_станций_и_сборов[Расстояние от Мск (км)],)-_xlfn.XLOOKUP(Sales[[#This Row],[Станция ОТ]],Справочник_станций_и_сборов[Станция (остановка)],Справочник_станций_и_сборов[Расстояние от Мск (км)],))*Справочник!$Q$3+Справочник!$Q$2),"") -> 5105 | J2: =IFERROR(Sales[[#This Row],[Базовая цена, руб]] * _xlfn.XLOOKUP(Sales[[#This Row],[Тип пассажира]],Тип_пассажира[Наименование],Тип_пассажира[Цена]), "") -> 0 | K2: =IFERROR(Sales[[#This Row],[Базовая цена, руб]] * VALUE(_xlfn.XLOOKUP(Sales[[#This Row],[Тип полки]], Тариф_полок[Тип полки], Тариф_полок[Коэф-нт цены], 1)),"") -> 0 | L2: =IFERROR((Sales[[#This Row],[Базовая цена, руб]]-Sales[[#This Row],[Сумма скидки льготникам, руб]])-Sales[[#This Row],[Сумма скидки тип-места, руб2]],"") -> 5105 | N2: =IF(ISBLANK(P2),"","Свободно") -> Свободно | O2: =IF(ISBLANK(P2),"",IF(P2>36, IF(MOD(P2,2)=0, "Верхнее боковое место", "Нижнее боковое место"), IF(MOD(P2,2)=0, "Верхнее место", "Нижнее место"))) -> Нижнее место | P2: {=_xlfn._xlws.FILTER(Аналитика!A3:A56, Аналитика!AF3:AF56="Свободно", "Мест нет")} -> 15 | Q2: =IFERROR(VLOOKUP(P2,Аналитика!A3:AH56,34,0),"") -> Частично | S2: Москва (Казанский) | T2: =VALUE(_xlfn.XLOOKUP(S2,Справочник_станций_и_сборов[Станция (остановка)],Справочник_станций_и_сборов[ID])) -> 1
A3: =IF(ISBLANK(Sales[[#This Row],[Место]]),"",CONCATENATE("T-00"&ROW()-1)) -> T-002 | B3: 2 | C3: Москва (Казанский) | D3: Воронеж 1 | E3: =IFERROR(_xlfn.XLOOKUP(Sales[[#This Row],[Станция ОТ]],Справочник_станций_и_сборов[Станция (остановка)],Справочник_станций_и_сборов[ID]),"") -> 1 | F3: =IFERROR(_xlfn.XLOOKUP(Sales[[#This Row],[Станция ДО]],Справочник_станций_и_сборов[Станция (остановка)],Справочник_станций_и_сборов[ID]),"") -> 6 | G3: Полный | H3: =IF(ISBLANK(Sales[[#This Row],[Место]]),"",IF(Sales[[#This Row],[Место]]>36, IF(MOD(Sales[[#This Row],[Место]],2)=0, "Верхнее боковое место", "Нижнее боковое место"), IF(MOD(Sales[[#This Row],[Место]],2)=0, "Верхнее место", "Нижнее место"))) -> Верхнее место | I3: =IFERROR(((_xlfn.XLOOKUP(Sales[[#This Row],[Станция ДО]],Справочник_станций_и_сборов[Станция (остановка)],Справочник_станций_и_сборов[Расстояние от Мск (км)],)-_xlfn.XLOOKUP(Sales[[#This Row],[Станция ОТ]],Справочник_станций_и_сборов[Станция (остановка)],Справочник_станций_и_сборов[Расстояние от Мск (км)],))*Справочник!$Q$3+Справочник!$Q$2),"") -> 2861.5 | J3: =IFERROR(Sales[[#This Row],[Базовая цена, руб]] * _xlfn.XLOOKUP(Sales[[#This Row],[Тип пассажира]],Тип_пассажира[Наименование],Тип_пассажира[Цена]), "") -> 0 | K3: =IFERROR(Sales[[#This Row],[Базовая цена, руб]] * VALUE(_xlfn.XLOOKUP(Sales[[#This Row],[Тип полки]], Тариф_полок[Тип полки], Тариф_полок[Коэф-нт цены], 1)),"") -> 286.15 | L3: =IFERROR((Sales[[#This Row],[Базовая цена, руб]]-Sales[[#This Row],[Сумма скидки льготникам, руб]])-Sales[[#This Row],[Сумма скидки тип-места, руб2]],"") -> 2575.35 | N3: =IF(ISBLANK(P3),"","Свободно") -> Свободно | O3: =IF(ISBLANK(P3),"",IF(P3>36, IF(MOD(P3,2)=0, "Верхнее боковое место", "Нижнее боковое место"), IF(MOD(P3,2)=0, "Верхнее место", "Нижнее место"))) -> Верхнее место | P3: 16 | Q3: =IFERROR(VLOOKUP(P3,Аналитика!A4:AH57,34,0),"") -> Частично | S3: Рязань 2 | T3: =VALUE(_xlfn.XLOOKUP(S3,Справочник_станций_и_сборов[Станция (остановка)],Справочник_станций_и_сборов[ID])) -> 2
A4: =IF(ISBLANK(Sales[[#This Row],[Место]]),"",CONCATENATE("T-00"&ROW()-1)) -> T-003 | B4: 2 | C4: Воронеж 1 | D4: Ростов-Главный | E4: =IFERROR(_xlfn.XLOOKUP(Sales[[#This Row],[Станция ОТ]],Справочник_станций_и_сборов[Станция (остановка)],Справочник_станций_и_сборов[ID]),"") -> 6 | F4: =IFERROR(_xlfn.XLOOKUP(Sales[[#This Row],[Станция ДО]],Справочник_станций_и_сборов[Станция (остановка)],Справочник_станций_и_сборов[ID]),"") -> 30 | G4: Полный | H4: =IF(ISBLANK(Sales[[#This Row],[Место]]),"",IF(Sales[[#This Row],[Место]]>36, IF(MOD(Sales[[#This Row],[Место]],2)=0, "Верхнее боковое место", "Нижнее боковое место"), IF(MOD(Sales[[#This Row],[Место]],2)=0, "Верхнее место", "Нижнее место"))) -> Верхнее место | I4: =IFERROR(((_xlfn.XLOOKUP(Sales[[#This Row],[Станция ДО]],Справочник_станций_и_сборов[Станция (остановка)],Справочник_станций_и_сборов[Расстояние от Мск (км)],)-_xlfn.XLOOKUP(Sales[[#This Row],[Станция ОТ]],Справочник_станций_и_сборов[Станция (остановка)],Справочник_станций_и_сборов[Расстояние от Мск (км)],))*Справочник!$Q$3+Справочник!$Q$2),"") -> 3043.5 | J4: =IFERROR(Sales[[#This Row],[Базовая цена, руб]] * _xlfn.XLOOKUP(Sales[[#This Row],[Тип пассажира]],Тип_пассажира[Наименование],Тип_пассажира[Цена]), "") -> 0 | K4: =IFERROR(Sales[[#This Row],[Базовая цена, руб]] * VALUE(_xlfn.XLOOKUP(Sales[[#This Row],[Тип полки]], Тариф_полок[Тип полки], Тариф_полок[Коэф-нт цены], 1)),"") -> 304.35 | L4: =IFERROR((Sales[[#This Row],[Базовая цена, руб]]-Sales[[#This Row],[Сумма скидки льготникам, руб]])-Sales[[#This Row],[Сумма скидки тип-места, руб2]],"") -> 2739.15 | N4: =IF(ISBLANK(P4),"","Свободно") -> Свободно | O4: =IF(ISBLANK(P4),"",IF(P4>36, IF(MOD(P4,2)=0, "Верхнее боковое место", "Нижнее боковое место"), IF(MOD(P4,2)=0, "Верхнее место", "Нижнее место"))) -> Нижнее место | P4: 17 | Q4: =IFERROR(VLOOKUP(P4,Аналитика!A5:AH58,34,0),"") -> Частично | S4: Ряжск 1 | T4: =VALUE(_xlfn.XLOOKUP(S4,Справочник_станций_и_сборов[Станция (остановка)],Справочник_станций_и_сборов[ID])) -> 3
A5: =IF(ISBLANK(Sales[[#This Row],[Место]]),"",CONCATENATE("T-00"&ROW()-1)) -> T-004 | B5: 3 | C5: Москва (Казанский) | D5: Мичуринск-Вор. | E5: =IFERROR(_xlfn.XLOOKUP(Sales[[#This Row],[Станция ОТ]],Справочник_станций_и_сборов[Станция (остановка)],Справочник_станций_и_сборов[ID]),"") -> 1 | F5: =IFERROR(_xlfn.XLOOKUP(Sales[[#This Row],[Станция ДО]],Справочник_станций_и_сборов[Станция (остановка)],Справочник_станций_и_сборов[ID]),"") -> 4 | G5: Полный | H5: =IF(ISBLANK(Sales[[#This Row],[Место]]),"",IF(Sales[[#This Row],[Место]]>36, IF(MOD(Sales[[#This Row],[Место]],2)=0, "Верхнее боковое место", "Нижнее боковое место"), IF(MOD(Sales[[#This Row],[Место]],2)=0, "Верхнее место", "Нижнее место"))) -> Нижнее место | I5: =IFERROR(((_xlfn.XLOOKUP(Sales[[#This Row],[Станция ДО]],Справочник_станций_и_сборов[Станция (остановка)],Справочник_станций_и_сборов[Расстояние от Мск (км)],)-_xlfn.XLOOKUP(Sales[[#This Row],[Станция ОТ]],Справочник_станций_и_сборов[Станция (остановка)],Справочник_станций_и_сборов[Расстояние от Мск (км)],))*Справочник!$Q$3+Справочник!$Q$2),"") -> 2235 | J5: =IFERROR(Sales[[#This Row],[Базовая цена, руб]] * _xlfn.XLOOKUP(Sales[[#This Row],[Тип пассажира]],Тип_пассажира[Наименование],Тип_пассажира[Цена]), "") -> 0 | K5: =IFERROR(Sales[[#This Row],[Базовая цена, руб]] * VALUE(_xlfn.XLOOKUP(Sales[[#This Row],[Тип полки]], Тариф_полок[Тип полки], Тариф_полок[Коэф-нт цены], 1)),"") -> 0 | L5: =IFERROR((Sales[[#This Row],[Базовая цена, руб]]-Sales[[#This Row],[Сумма скидки льготникам, руб]])-Sales[[#This Row],[Сумма скидки тип-места, руб2]],"") -> 2235 | N5: =IF(ISBLANK(P5),"","Свободно") -> Свободно | O5: =IF(ISBLANK(P5),"",IF(P5>36, IF(MOD(P5,2)=0, "Верхнее боковое место", "Нижнее боковое место"), IF(MOD(P5,2)=0, "Верхнее место", "Нижнее место"))) -> Нижнее место | P5: 19 | Q5: =IFERROR(VLOOKUP(P5,Аналитика!A6:AH59,34,0),"") -> Частично | R5: Станция отправления | S5: Мичуринск-Вор. | T5: =VALUE(_xlfn.XLOOKUP(S5,Справочник_станций_и_сборов[Станция (остановка)],Справочник_станций_и_сборов[ID])) -> 4
A6: =IF(ISBLANK(Sales[[#This Row],[Место]]),"",CONCATENATE("T-00"&ROW()-1)) -> T-005 | B6: 3 | C6: Мичуринск-Вор. | D6: Лиски | E6: =IFERROR(_xlfn.XLOOKUP(Sales[[#This Row],[Станция ОТ]],Справочник_станций_и_сборов[Станция (остановка)],Справочник_станций_и_сборов[ID]),"") -> 4 | F6: =IFERROR(_xlfn.XLOOKUP(Sales[[#This Row],[Станция ДО]],Справочник_станций_и_сборов[Станция (остановка)],Справочник_станций_и_сборов[ID]),"") -> 7 | G6: Полный | H6: =IF(ISBLANK(Sales[[#This Row],[Место]]),"",IF(Sales[[#This Row],[Место]]>36, IF(MOD(Sales[[#This Row],[Место]],2)=0, "Верхнее боковое место", "Нижнее боковое место"), IF(MOD(Sales[[#This Row],[Место]],2)=0, "Верхнее место", "Нижнее место"))) -> Нижнее место | I6: =IFERROR(((_xlfn.XLOOKUP(Sales[[#This Row],[Станция ДО]],Справочник_станций_и_сборов[Станция (остановка)],Справочник_станций_и_сборов[Расстояние от Мск (км)],)-_xlfn.XLOOKUP(Sales[[#This Row],[Станция ОТ]],Справочник_станций_и_сборов[Станция (остановка)],Справочник_станций_и_сборов[Расстояние от Мск (км)],))*Справочник!$Q$3+Справочник!$Q$2),"") -> 1769.5 | J6: =IFERROR(Sales[[#This Row],[Базовая цена, руб]] * _xlfn.XLOOKUP(Sales[[#This Row],[Тип пассажира]],Тип_пассажира[Наименование],Тип_пассажира[Цена]), "") -> 0 | K6: =IFERROR(Sales[[#This Row],[Базовая цена, руб]] * VALUE(_xlfn.XLOOKUP(Sales[[#This Row],[Тип полки]], Тариф_полок[Тип полки], Тариф_полок[Коэф-нт цены], 1)),"") -> 0 | L6: =IFERROR((Sales[[#This Row],[Базовая цена, руб]]-Sales[[#This Row],[Сумма скидки льготникам, руб]])-Sales[[#This Row],[Сумма скидки тип-места, руб2]],"") -> 1769.5 | N6: =IF(ISBLANK(P6),"","Свободно") -> Свободно | O6: =IF(ISBLANK(P6),"",IF(P6>36, IF(MOD(P6,2)=0, "Верхнее боковое место", "Нижнее боковое место"), IF(MOD(P6,2)=0, "Верхнее место", "Нижнее место"))) -> Верхнее место | P6: 20 | Q6: =IFERROR(VLOOKUP(P6,Аналитика!A7:AH60,34,0),"") -> Частично | S6: Грязи-Воронежские | T6: =VALUE(_xlfn.XLOOKUP(S6,Справочник_станций_и_сборов[Станция (остановка)],Справочник_станций_и_сборов[ID])) -> 5
A7: =IF(ISBLANK(Sales[[#This Row],[Место]]),"",CONCATENATE("T-00"&ROW()-1)) -> T-006 | B7: 3 | C7: Россошь | D7: Ростов-Главный | E7: =IFERROR(_xlfn.XLOOKUP(Sales[[#This Row],[Станция ОТ]],Справочник_станций_и_сборов[Станция (остановка)],Справочник_станций_и_сборов[ID]),"") -> 12 | F7: =IFERROR(_xlfn.XLOOKUP(Sales[[#This Row],[Станция ДО]],Справочник_станций_и_сборов[Станция (остановка)],Справочник_станций_и_сборов[ID]),"") -> 30 | G7: Полный | H7: =IF(ISBLANK(Sales[[#This Row],[Место]]),"",IF(Sales[[#This Row],[Место]]>36, IF(MOD(Sales[[#This Row],[Место]],2)=0, "Верхнее боковое место", "Нижнее боковое место"), IF(MOD(Sales[[#This Row],[Место]],2)=0, "Верхнее место", "Нижнее место"))) -> Нижнее место | I7: =IFERROR(((_xlfn.XLOOKUP(Sales[[#This Row],[Станция ДО]],Справочник_станций_и_сборов[Станция (остановка)],Справочник_станций_и_сборов[Расстояние от Мск (км)],)-_xlfn.XLOOKUP(Sales[[#This Row],[Станция ОТ]],Справочник_станций_и_сборов[Станция (остановка)],Справочник_станций_и_сборов[Расстояние от Мск (км)],))*Справочник!$Q$3+Справочник!$Q$2),"") -> 2224.5 | J7: =IFERROR(Sales[[#This Row],[Базовая цена, руб]] * _xlfn.XLOOKUP(Sales[[#This Row],[Тип пассажира]],Тип_пассажира[Наименование],Тип_пассажира[Цена]), "") -> 0 | K7: =IFERROR(Sales[[#This Row],[Базовая цена, руб]] * VALUE(_xlfn.XLOOKUP(Sales[[#This Row],[Тип полки]], Тариф_полок[Тип полки], Тариф_полок[Коэф-нт цены], 1)),"") -> 0 | L7: =IFERROR((Sales[[#This Row],[Базовая цена, руб]]-Sales[[#This Row],[Сумма скидки льготникам, руб]])-Sales[[#This Row],[Сумма скидки тип-места, руб2]],"") -> 2224.5 | N7: =IF(ISBLANK(P7),"","Свободно") -> Свободно | O7: =IF(ISBLANK(P7),"",IF(P7>36, IF(MOD(P7,2)=0, "Верхнее боковое место", "Нижнее боковое место"), IF(MOD(P7,2)=0, "Верхнее место", "Нижнее место"))) -> Нижнее место | P7: 21 | Q7: =IFERROR(VLOOKUP(P7,Аналитика!A8:AH61,34,0),"") -> Целое купе/отсек | S7: Воронеж 1 | T7: =VALUE(_xlfn.XLOOKUP(S7,Справочник_станций_и_сборов[Станция (остановка)],Справочник_станций_и_сборов[ID])) -> 6
A8: =IF(ISBLANK(Sales[[#This Row],[Место]]),"",CONCATENATE("T-00"&ROW()-1)) -> T-007 | B8: 4 | C8: Рязань 2 | D8: Каменская | E8: =IFERROR(_xlfn.XLOOKUP(Sales[[#This Row],[Станция ОТ]],Справочник_станций_и_сборов[Станция (остановка)],Справочник_станций_и_сборов[ID]),"") -> 2 | F8: =IFERROR(_xlfn.XLOOKUP(Sales[[#This Row],[Станция ДО]],Справочник_станций_и_сборов[Станция (остановка)],Справочник_станций_и_сборов[ID]),"") -> 19 | G8: Полный | H8: =IF(ISBLANK(Sales[[#This Row],[Место]]),"",IF(Sales[[#This Row],[Место]]>36, IF(MOD(Sales[[#This Row],[Место]],2)=0, "Верхнее боковое место", "Нижнее боковое место"), IF(MOD(Sales[[#This Row],[Место]],2)=0, "Верхнее место", "Нижнее место"))) -> Верхнее место | I8: =IFERROR(((_xlfn.XLOOKUP(Sales[[#This Row],[Станция ДО]],Справочник_станций_и_сборов[Станция (остановка)],Справочник_станций_и_сборов[Расстояние от Мск (км)],)-_xlfn.XLOOKUP(Sales[[#This Row],[Станция ОТ]],Справочник_станций_и_сборов[Станция (остановка)],Справочник_станций_и_сборов[Расстояние от Мск (км)],))*Справочник!$Q$3+Справочник!$Q$2),"") -> 3834.5 | J8: =IFERROR(Sales[[#This Row],[Базовая цена, руб]] * _xlfn.XLOOKUP(Sales[[#This Row],[Тип пассажира]],Тип_пассажира[Наименование],Тип_пассажира[Цена]), "") -> 0 | K8: =IFERROR(Sales[[#This Row],[Базовая цена, руб]] * VALUE(_xlfn.XLOOKUP(Sales[[#This Row],[Тип полки]], Тариф_полок[Тип полки], Тариф_полок[Коэф-нт цены], 1)),"") -> 383.45 | L8: =IFERROR((Sales[[#This Row],[Базовая цена, руб]]-Sales[[#This Row],[Сумма скидки льготникам, руб]])-Sales[[#This Row],[Сумма скидки тип-места, руб2]],"") -> 3451.05 | N8: =IF(ISBLANK(P8),"","Свободно") -> Свободно | O8: =IF(ISBLANK(P8),"",IF(P8>36, IF(MOD(P8,2)=0, "Верхнее боковое место", "Нижнее боковое место"), IF(MOD(P8,2)=0, "Верхнее место", "Нижнее место"))) -> Верхнее место | P8: 22 | Q8: =IFERROR(VLOOKUP(P8,Аналитика!A9:AH62,34,0),"") -> Целое купе/отсек | S8: Лиски | T8: =VALUE(_xlfn.XLOOKUP(S8,Справочник_станций_и_сборов[Станция (остановка)],Справочник_станций_и_сборов[ID])) -> 7
A9: =IF(ISBLANK(Sales[[#This Row],[Место]]),"",CONCATENATE("T-00"&ROW()-1)) -> T-008 | B9: 18 | C9: Воронеж 1 | D9: Ростов-Главный | E9: =IFERROR(_xlfn.XLOOKUP(Sales[[#This Row],[Станция ОТ]],Справочник_станций_и_сборов[Станция (остановка)],Справочник_станций_и_сборов[ID]),"") -> 6 | F9: =IFERROR(_xlfn.XLOOKUP(Sales[[#This Row],[Станция ДО]],Справочник_станций_и_сборов[Станция (остановка)],Справочник_станций_и_сборов[ID]),"") -> 30 | G9: Полный | H9: =IF(ISBLANK(Sales[[#This Row],[Место]]),"",IF(Sales[[#This Row],[Место]]>36, IF(MOD(Sales[[#This Row],[Место]],2)=0, "Верхнее боковое место", "Нижнее боковое место"), IF(MOD(Sales[[#This Row],[Место]],2)=0, "Верхнее место", "Нижнее место"))) -> Верхнее место | I9: =IFERROR(((_xlfn.XLOOKUP(Sales[[#This Row],[Станция ДО]],Справочник_станций_и_сборов[Станция (остановка)],Справочник_станций_и_сборов[Расстояние от Мск (км)],)-_xlfn.XLOOKUP(Sales[[#This Row],[Станция ОТ]],Справочник_станций_и_сборов[Станция (остановка)],Справочник_станций_и_сборов[Расстояние от Мск (км)],))*Справочник!$Q$3+Справочник!$Q$2),"") -> 3043.5 | J9: =IFERROR(Sales[[#This Row],[Базовая цена, руб]] * _xlfn.XLOOKUP(Sales[[#This Row],[Тип пассажира]],Тип_пассажира[Наименование],Тип_пассажира[Цена]), "") -> 0 | K9: =IFERROR(Sales[[#This Row],[Базовая цена, руб]] * VALUE(_xlfn.XLOOKUP(Sales[[#This Row],[Тип полки]], Тариф_полок[Тип полки], Тариф_полок[Коэф-нт цены], 1)),"") -> 304.35 | L9: =IFERROR((Sales[[#This Row],[Базовая цена, руб]]-Sales[[#This Row],[Сумма скидки льготникам, руб]])-Sales[[#This Row],[Сумма скидки тип-места, руб2]],"") -> 2739.15 | N9: =IF(ISBLANK(P9),"","Свободно") -> Свободно | O9: =IF(ISBLANK(P9),"",IF(P9>36, IF(MOD(P9,2)=0, "Верхнее боковое место", "Нижнее боковое место"), IF(MOD(P9,2)=0, "Верхнее место", "Нижнее место"))) -> Нижнее место | P9: 23 | Q9: =IFERROR(VLOOKUP(P9,Аналитика!A10:AH63,34,0),"") -> Целое купе/отсек | S9: Пухово | T9: =VALUE(_xlfn.XLOOKUP(S9,Справочник_станций_и_сборов[Станция (остановка)],Справочник_станций_и_сборов[ID])) -> 8
A10: =IF(ISBLANK(Sales[[#This Row],[Место]]),"",CONCATENATE("T-00"&ROW()-1)) -> T-009 | B10: 14 | C10: Миллерово | D10: Шахтная | E10: =IFERROR(_xlfn.XLOOKUP(Sales[[#This Row],[Станция ОТ]],Справочник_станций_и_сборов[Станция (остановка)],Справочник_станций_и_сборов[ID]),"") -> 16 | F10: =IFERROR(_xlfn.XLOOKUP(Sales[[#This Row],[Станция ДО]],Справочник_станций_и_сборов[Станция (остановка)],Справочник_станций_и_сборов[ID]),"") -> 24 | G10: Полный | H10: =IF(ISBLANK(Sales[[#This Row],[Место]]),"",IF(Sales[[#This Row],[Место]]>36, IF(MOD(Sales[[#This Row],[Место]],2)=0, "Верхнее боковое место", "Нижнее боковое место"), IF(MOD(Sales[[#This Row],[Место]],2)=0, "Верхнее место", "Нижнее место"))) -> Верхнее место | I10: =IFERROR(((_xlfn.XLOOKUP(Sales[[#This Row],[Станция ДО]],Справочник_станций_и_сборов[Станция (остановка)],Справочник_станций_и_сборов[Расстояние от Мск (км)],)-_xlfn.XLOOKUP(Sales[[#This Row],[Станция ОТ]],Справочник_станций_и_сборов[Станция (остановка)],Справочник_станций_и_сборов[Расстояние от Мск (км)],))*Справочник!$Q$3+Справочник!$Q$2),"") -> 1363.5 | J10: =IFERROR(Sales[[#This Row],[Базовая цена, руб]] * _xlfn.XLOOKUP(Sales[[#This Row],[Тип пассажира]],Тип_пассажира[Наименование],Тип_пассажира[Цена]), "") -> 0 | K10: =IFERROR(Sales[[#This Row],[Базовая цена, руб]] * VALUE(_xlfn.XLOOKUP(Sales[[#This Row],[Тип полки]], Тариф_полок[Тип полки], Тариф_полок[Коэф-нт цены], 1)),"") -> 136.35 | L10: =IFERROR((Sales[[#This Row],[Базовая цена, руб]]-Sales[[#This Row],[Сумма скидки льготникам, руб]])-Sales[[#This Row],[Сумма скидки тип-места, руб2]],"") -> 1227.15 | N10: =IF(ISBLANK(P10),"","Свободно") -> Свободно | O10: =IF(ISBLANK(P10),"",IF(P10>36, IF(MOD(P10,2)=0, "Верхнее боковое место", "Нижнее боковое место"), IF(MOD(P10,2)=0, "Верхнее место", "Нижнее место"))) -> Верхнее место | P10: 24 | Q10: =IFERROR(VLOOKUP(P10,Аналитика!A11:AH64,34,0),"") -> Целое купе/отсек | S10: Евдаково | T10: =VALUE(_xlfn.XLOOKUP(S10,Справочник_станций_и_сборов[Станция (остановка)],Справочник_станций_и_сборов[ID])) -> 9
A11: =IF(ISBLANK(Sales[[#This Row],[Место]]),"",CONCATENATE("T-00"&ROW()-1)) -> T-0010 | B11: 39 | C11: Мичуринск-Вор. | D11: Сулин | E11: =IFERROR(_xlfn.XLOOKUP(Sales[[#This Row],[Станция ОТ]],Справочник_станций_и_сборов[Станция (остановка)],Справочник_станций_и_сборов[ID]),"") -> 4 | F11: =IFERROR(_xlfn.XLOOKUP(Sales[[#This Row],[Станция ДО]],Справочник_станций_и_сборов[Станция (остановка)],Справочник_станций_и_сборов[ID]),"") -> 23 | G11: Полный | H11: =IF(ISBLANK(Sales[[#This Row],[Место]]),"",IF(Sales[[#This Row],[Место]]>36, IF(MOD(Sales[[#This Row],[Место]],2)=0, "Верхнее боковое место", "Нижнее боковое место"), IF(MOD(Sales[[#This Row],[Место]],2)=0, "Верхнее место", "Нижнее место"))) -> Нижнее боковое место | I11: =IFERROR(((_xlfn.XLOOKUP(Sales[[#This Row],[Станция ДО]],Справочник_станций_и_сборов[Станция (остановка)],Справочник_станций_и_сборов[Расстояние от Мск (км)],)-_xlfn.XLOOKUP(Sales[[#This Row],[Станция ОТ]],Справочник_станций_и_сборов[Станция (остановка)],Справочник_станций_и_сборов[Расстояние от Мск (км)],))*Справочник!$Q$3+Справочник!$Q$2),"") -> 3313 | J11: =IFERROR(Sales[[#This Row],[Базовая цена, руб]] * _xlfn.XLOOKUP(Sales[[#This Row],[Тип пассажира]],Тип_пассажира[Наименование],Тип_пассажира[Цена]), "") -> 0 | K11: =IFERROR(Sales[[#This Row],[Базовая цена, руб]] * VALUE(_xlfn.XLOOKUP(Sales[[#This Row],[Тип полки]], Тариф_полок[Тип полки], Тариф_полок[Коэф-нт цены], 1)),"") -> 496.95 | L11: =IFERROR((Sales[[#This Row],[Базовая цена, руб]]-Sales[[#This Row],[Сумма скидки льготникам, руб]])-Sales[[#This Row],[Сумма скидки тип-места, руб2]],"") -> 2816.05 | N11: =IF(ISBLANK(P11),"","Свободно") -> Свободно | O11: =IF(ISBLANK(P11),"",IF(P11>36, IF(MOD(P11,2)=0, "Верхнее боковое место", "Нижнее боковое место"), IF(MOD(P11,2)=0, "Верхнее место", "Нижнее место"))) -> Нижнее место | P11: 25 | Q11: =IFERROR(VLOOKUP(P11,Аналитика!A12:AH65,34,0),"") -> Целое купе/отсек | S11: Сагуны | T11: =VALUE(_xlfn.XLOOKUP(S11,Справочник_станций_и_сборов[Станция (остановка)],Справочник_станций_и_сборов[ID])) -> 10
A12: =IF(ISBLANK(Sales[[#This Row],[Место]]),"",CONCATENATE("T-00"&ROW()-1)) -> T-0011 | B12: 33 | C12: Москва (Казанский) | D12: Грязи-Воронежские | E12: =IFERROR(_xlfn.XLOOKUP(Sales[[#This Row],[Станция ОТ]],Справочник_станций_и_сборов[Станция (остановка)],Справочник_станций_и_сборов[ID]),"") -> 1 | F12: =IFERROR(_xlfn.XLOOKUP(Sales[[#This Row],[Станция ДО]],Справочник_станций_и_сборов[Станция (остановка)],Справочник_станций_и_сборов[ID]),"") -> 5 | G12: Полный | H12: =IF(ISBLANK(Sales[[#This Row],[Место]]),"",IF(Sales[[#This Row],[Место]]>36, IF(MOD(Sales[[#This Row],[Место]],2)=0, "Верхнее боковое место", "Нижнее боковое место"), IF(MOD(Sales[[#This Row],[Место]],2)=0, "Верхнее место", "Нижнее место"))) -> Нижнее место | I12: =IFERROR(((_xlfn.XLOOKUP(Sales[[#This Row],[Станция ДО]],Справочник_станций_и_сборов[Станция (остановка)],Справочник_станций_и_сборов[Расстояние от Мск (км)],)-_xlfn.XLOOKUP(Sales[[#This Row],[Станция ОТ]],Справочник_станций_и_сборов[Станция (остановка)],Справочник_станций_и_сборов[Расстояние от Мск (км)],))*Справочник!$Q$3+Справочник!$Q$2),"") -> 2448.5 | J12: =IFERROR(Sales[[#This Row],[Базовая цена, руб]] * _xlfn.XLOOKUP(Sales[[#This Row],[Тип пассажира]],Тип_пассажира[Наименование],Тип_пассажира[Цена]), "") -> 0 | K12: =IFERROR(Sales[[#This Row],[Базовая цена, руб]] * VALUE(_xlfn.XLOOKUP(Sales[[#This Row],[Тип полки]], Тариф_полок[Тип полки], Тариф_полок[Коэф-нт цены], 1)),"") -> 0 | L12: =IFERROR((Sales[[#This Row],[Базовая цена, руб]]-Sales[[#This Row],[Сумма скидки льготникам, руб]])-Sales[[#This Row],[Сумма скидки тип-места, руб2]],"") -> 2448.5 | N12: =IF(ISBLANK(P12),"","Свободно") -> Свободно | O12: =IF(ISBLANK(P12),"",IF(P12>36, IF(MOD(P12,2)=0, "Верхнее боковое место", "Нижнее боковое место"), IF(MOD(P12,2)=0, "Верхнее место", "Нижнее место"))) -> Верхнее место | P12: 26 | Q12: =IFERROR(VLOOKUP(P12,Аналитика!A13:AH66,34,0),"") -> Целое купе/отсек | S12: Подгорное | T12: =VALUE(_xlfn.XLOOKUP(S12,Справочник_станций_и_сборов[Станция (остановка)],Справочник_станций_и_сборов[ID])) -> 11
A13: =IF(ISBLANK(Sales[[#This Row],[Место]]),"",CONCATENATE("T-00"&ROW()-1)) -> T-0012 | B13: 25 | C13: Хотунок | D13: Ростов-Главный | E13: =IFERROR(_xlfn.XLOOKUP(Sales[[#This Row],[Станция ОТ]],Справочник_станций_и_сборов[Станция (остановка)],Справочник_станций_и_сборов[ID]),"") -> 27 | F13: =IFERROR(_xlfn.XLOOKUP(Sales[[#This Row],[Станция ДО]],Справочник_станций_и_сборов[Станция (остановка)],Справочник_станций_и_сборов[ID]),"") -> 30 | G13: Полный | H13: =IF(ISBLANK(Sales[[#This Row],[Место]]),"",IF(Sales[[#This Row],[Место]]>36, IF(MOD(Sales[[#This Row],[Место]],2)=0, "Верхнее боковое место", "Нижнее боковое место"), IF(MOD(Sales[[#This Row],[Место]],2)=0, "Верхнее место", "Нижнее место"))) -> Нижнее место | I13: =IFERROR(((_xlfn.XLOOKUP(Sales[[#This Row],[Станция ДО]],Справочник_станций_и_сборов[Станция (остановка)],Справочник_станций_и_сборов[Расстояние от Мск (км)],)-_xlfn.XLOOKUP(Sales[[#This Row],[Станция ОТ]],Справочник_станций_и_сборов[Станция (остановка)],Справочник_станций_и_сборов[Расстояние от Мск (км)],))*Справочник!$Q$3+Справочник!$Q$2),"") -> 940 | J13: =IFERROR(Sales[[#This Row],[Базовая цена, руб]] * _xlfn.XLOOKUP(Sales[[#This Row],[Тип пассажира]],Тип_пассажира[Наименование],Тип_пассажира[Цена]), "") -> 0 | K13: =IFERROR(Sales[[#This Row],[Базовая цена, руб]] * VALUE(_xlfn.XLOOKUP(Sales[[#This Row],[Тип полки]], Тариф_полок[Тип полки], Тариф_полок[Коэф-нт цены], 1)),"") -> 0 | L13: =IFERROR((Sales[[#This Row],[Базовая цена, руб]]-Sales[[#This Row],[Сумма скидки льготникам, руб]])-Sales[[#This Row],[Сумма скидки тип-места, руб2]],"") -> 940 | N13: =IF(ISBLANK(P13),"","Свободно") -> Свободно | O13: =IF(ISBLANK(P13),"",IF(P13>36, IF(MOD(P13,2)=0, "Верхнее боковое место", "Нижнее боковое место"), IF(MOD(P13,2)=0, "Верхнее место", "Нижнее место"))) -> Нижнее место | P13: 27 | Q13: =IFERROR(VLOOKUP(P13,Аналитика!A14:AH67,34,0),"") -> Целое купе/отсек | S13: Россошь | T13: =VALUE(_xlfn.XLOOKUP(S13,Справочник_станций_и_сборов[Станция (остановка)],Справочник_станций_и_сборов[ID])) -> 12
A14: =IF(ISBLANK(Sales[[#This Row],[Место]]),"",CONCATENATE("T-00"&ROW()-1)) -> T-0013 | B14: 5 | C14: Мичуринск-Вор. | D14: Чертково | E14: =IFERROR(_xlfn.XLOOKUP(Sales[[#This Row],[Станция ОТ]],Справочник_станций_и_сборов[Станция (остановка)],Справочник_станций_и_сборов[ID]),"") -> 4 | F14: =IFERROR(_xlfn.XLOOKUP(Sales[[#This Row],[Станция ДО]],Справочник_станций_и_сборов[Станция (остановка)],Справочник_станций_и_сборов[ID]),"") -> 15 | G14: Полный | H14: =IF(ISBLANK(Sales[[#This Row],[Место]]),"",IF(Sales[[#This Row],[Место]]>36, IF(MOD(Sales[[#This Row],[Место]],2)=0, "Верхнее боковое место", "Нижнее боковое место"), IF(MOD(Sales[[#This Row],[Место]],2)=0, "Верхнее место", "Нижнее место"))) -> Нижнее место | I14: =IFERROR(((_xlfn.XLOOKUP(Sales[[#This Row],[Станция ДО]],Справочник_станций_и_сборов[Станция (остановка)],Справочник_станций_и_сборов[Расстояние от Мск (км)],)-_xlfn.XLOOKUP(Sales[[#This Row],[Станция ОТ]],Справочник_станций_и_сборов[Станция (остановка)],Справочник_станций_и_сборов[Расстояние от Мск (км)],))*Справочник!$Q$3+Справочник!$Q$2),"") -> 2620 | J14: =IFERROR(Sales[[#This Row],[Базовая цена, руб]] * _xlfn.XLOOKUP(Sales[[#This Row],[Тип пассажира]],Тип_пассажира[Наименование],Тип_пассажира[Цена]), "") -> 0 | K14: =IFERROR(Sales[[#This Row],[Базовая цена, руб]] * VALUE(_xlfn.XLOOKUP(Sales[[#This Row],[Тип полки]], Тариф_полок[Тип полки], Тариф_полок[Коэф-нт цены], 1)),"") -> 0 | L14: =IFERROR((Sales[[#This Row],[Базовая цена, руб]]-Sales[[#This Row],[Сумма скидки льготникам, руб]])-Sales[[#This Row],[Сумма скидки тип-места, руб2]],"") -> 2620 | N14: =IF(ISBLANK(P14),"","Свободно") -> Свободно | O14: =IF(ISBLANK(P14),"",IF(P14>36, IF(MOD(P14,2)=0, "Верхнее боковое место", "Нижнее боковое место"), IF(MOD(P14,2)=0, "Верхнее место", "Нижнее место"))) -> Верхнее место | P14: 28 | Q14: =IFERROR(VLOOKUP(P14,Аналитика!A15:AH68,34,0),"") -> Целое купе/отсек | S14: Райновская | T14: =VALUE(_xlfn.XLOOKUP(S14,Справочник_станций_и_сборов[Станция (остановка)],Справочник_станций_и_сборов[ID])) -> 13
A15: =IF(ISBLANK(Sales[[#This Row],[Место]]),"",CONCATENATE("T-00"&ROW()-1)) -> T-0014 | B15: 5 | C15: Чертково | D15: Ростов-Главный | E15: =IFERROR(_xlfn.XLOOKUP(Sales[[#This Row],[Станция ОТ]],Справочник_станций_и_сборов[Станция (остановка)],Справочник_станций_и_сборов[ID]),"") -> 15 | F15: =IFERROR(_xlfn.XLOOKUP(Sales[[#This Row],[Станция ДО]],Справочник_станций_и_сборов[Станция (остановка)],Справочник_станций_и_сборов[ID]),"") -> 30 | G15: Полный | H15: =IF(ISBLANK(Sales[[#This Row],[Место]]),"",IF(Sales[[#This Row],[Место]]>36, IF(MOD(Sales[[#This Row],[Место]],2)=0, "Верхнее боковое место", "Нижнее боковое место"), IF(MOD(Sales[[#This Row],[Место]],2)=0, "Верхнее место", "Нижнее место"))) -> Нижнее место | I15: =IFERROR(((_xlfn.XLOOKUP(Sales[[#This Row],[Станция ДО]],Справочник_станций_и_сборов[Станция (остановка)],Справочник_станций_и_сборов[Расстояние от Мск (км)],)-_xlfn.XLOOKUP(Sales[[#This Row],[Станция ОТ]],Справочник_станций_и_сборов[Станция (остановка)],Справочник_станций_и_сборов[Расстояние от Мск (км)],))*Справочник!$Q$3+Справочник!$Q$2),"") -> 1850 | J15: =IFERROR(Sales[[#This Row],[Базовая цена, руб]] * _xlfn.XLOOKUP(Sales[[#This Row],[Тип пассажира]],Тип_пассажира[Наименование],Тип_пассажира[Цена]), "") -> 0 | K15: =IFERROR(Sales[[#This Row],[Базовая цена, руб]] * VALUE(_xlfn.XLOOKUP(Sales[[#This Row],[Тип полки]], Тариф_полок[Тип полки], Тариф_полок[Коэф-нт цены], 1)),"") -> 0 | L15: =IFERROR((Sales[[#This Row],[Базовая цена, руб]]-Sales[[#This Row],[Сумма скидки льготникам, руб]])-Sales[[#This Row],[Сумма скидки тип-места, руб2]],"") -> 1850 | N15: =IF(ISBLANK(P15),"","Свободно") -> Свободно | O15: =IF(ISBLANK(P15),"",IF(P15>36, IF(MOD(P15,2)=0, "Верхнее боковое место", "Нижнее боковое место"), IF(MOD(P15,2)=0, "Верхнее место", "Нижнее место"))) -> Нижнее место | P15: 29 | Q15: =IFERROR(VLOOKUP(P15,Аналитика!A16:AH69,34,0),"") -> Частично | S15: Кантемировка | T15: =VALUE(_xlfn.XLOOKUP(S15,Справочник_станций_и_сборов[Станция (остановка)],Справочник_станций_и_сборов[ID])) -> 14
A16: =IF(ISBLANK(Sales[[#This Row],[Место]]),"",CONCATENATE("T-00"&ROW()-1)) -> T-0015 | B16: 4 | C16: Каменская | D16: Ростов-Главный | E16: =IFERROR(_xlfn.XLOOKUP(Sales[[#This Row],[Станция ОТ]],Справочник_станций_и_сборов[Станция (остановка)],Справочник_станций_и_сборов[ID]),"") -> 19 | F16: =IFERROR(_xlfn.XLOOKUP(Sales[[#This Row],[Станция ДО]],Справочник_станций_и_сборов[Станция (остановка)],Справочник_станций_и_сборов[ID]),"") -> 30 | G16: Полный | H16: =IF(ISBLANK(Sales[[#This Row],[Место]]),"",IF(Sales[[#This Row],[Место]]>36, IF(MOD(Sales[[#This Row],[Место]],2)=0, "Верхнее боковое место", "Нижнее боковое место"), IF(MOD(Sales[[#This Row],[Место]],2)=0, "Верхнее место", "Нижнее место"))) -> Верхнее место | I16: =IFERROR(((_xlfn.XLOOKUP(Sales[[#This Row],[Станция ДО]],Справочник_станций_и_сборов[Станция (остановка)],Справочник_станций_и_сборов[Расстояние от Мск (км)],)-_xlfn.XLOOKUP(Sales[[#This Row],[Станция ОТ]],Справочник_станций_и_сборов[Станция (остановка)],Справочник_станций_и_сборов[Расстояние от Мск (км)],))*Справочник!$Q$3+Справочник!$Q$2),"") -> 1377.5 | J16: =IFERROR(Sales[[#This Row],[Базовая цена, руб]] * _xlfn.XLOOKUP(Sales[[#This Row],[Тип пассажира]],Тип_пассажира[Наименование],Тип_пассажира[Цена]), "") -> 0 | K16: =IFERROR(Sales[[#This Row],[Базовая цена, руб]] * VALUE(_xlfn.XLOOKUP(Sales[[#This Row],[Тип полки]], Тариф_полок[Тип полки], Тариф_полок[Коэф-нт цены], 1)),"") -> 137.75 | L16: =IFERROR((Sales[[#This Row],[Базовая цена, руб]]-Sales[[#This Row],[Сумма скидки льготникам, руб]])-Sales[[#This Row],[Сумма скидки тип-места, руб2]],"") -> 1239.75 | N16: =IF(ISBLANK(P16),"","Свободно") -> Свободно | O16: =IF(ISBLANK(P16),"",IF(P16>36, IF(MOD(P16,2)=0, "Верхнее боковое место", "Нижнее боковое место"), IF(MOD(P16,2)=0, "Верхнее место", "Нижнее место"))) -> Верхнее место | P16: 30 | Q16: =IFERROR(VLOOKUP(P16,Аналитика!A17:AH70,34,0),"") -> Частично | R16: Станция прибытия | S16: Чертково | T16: =VALUE(_xlfn.XLOOKUP(S16,Справочник_станций_и_сборов[Станция (остановка)],Справочник_станций_и_сборов[ID])) -> 15
A17: =IF(ISBLANK(Sales[[#This Row],[Место]]),"",CONCATENATE("T-00"&ROW()-1)) -> T-0016 | B17: 6 | C17: Москва (Казанский) | D17: Воронеж 1 | E17: =IFERROR(_xlfn.XLOOKUP(Sales[[#This Row],[Станция ОТ]],Справочник_станций_и_сборов[Станция (остановка)],Справочник_станций_и_сборов[ID]),"") -> 1 | F17: =IFERROR(_xlfn.XLOOKUP(Sales[[#This Row],[Станция ДО]],Справочник_станций_и_сборов[Станция (остановка)],Справочник_станций_и_сборов[ID]),"") -> 6 | G17: Полный | H17: =IF(ISBLANK(Sales[[#This Row],[Место]]),"",IF(Sales[[#This Row],[Место]]>36, IF(MOD(Sales[[#This Row],[Место]],2)=0, "Верхнее боковое место", "Нижнее боковое место"), IF(MOD(Sales[[#This Row],[Место]],2)=0, "Верхнее место", "Нижнее место"))) -> Верхнее место | I17: =IFERROR(((_xlfn.XLOOKUP(Sales[[#This Row],[Станция ДО]],Справочник_станций_и_сборов[Станция (остановка)],Справочник_станций_и_сборов[Расстояние от Мск (км)],)-_xlfn.XLOOKUP(Sales[[#This Row],[Станция ОТ]],Справочник_станций_и_сборов[Станция (остановка)],Справочник_станций_и_сборов[Расстояние от Мск (км)],))*Справочник!$Q$3+Справочник!$Q$2),"") -> 2861.5 | J17: =IFERROR(Sales[[#This Row],[Базовая цена, руб]] * _xlfn.XLOOKUP(Sales[[#This Row],[Тип пассажира]],Тип_пассажира[Наименование],Тип_пассажира[Цена]), "") -> 0 | K17: =IFERROR(Sales[[#This Row],[Базовая цена, руб]] * VALUE(_xlfn.XLOOKUP(Sales[[#This Row],[Тип полки]], Тариф_полок[Тип полки], Тариф_полок[Коэф-нт цены], 1)),"") -> 286.15 | L17: =IFERROR((Sales[[#This Row],[Базовая цена, руб]]-Sales[[#This Row],[Сумма скидки льготникам, руб]])-Sales[[#This Row],[Сумма скидки тип-места, руб2]],"") -> 2575.35 | N17: =IF(ISBLANK(P17),"","Свободно") -> Свободно | O17: =IF(ISBLANK(P17),"",IF(P17>36, IF(MOD(P17,2)=0, "Верхнее боковое место", "Нижнее боковое место"), IF(MOD(P17,2)=0, "Верхнее место", "Нижнее место"))) -> Нижнее место | P17: 31 | Q17: =IFERROR(VLOOKUP(P17,Аналитика!A18:AH71,34,0),"") -> Частично | S17: Миллерово | T17: =VALUE(_xlfn.XLOOKUP(S17,Справочник_станций_и_сборов[Станция (остановка)],Справочник_станций_и_сборов[ID])) -> 16
A18: =IF(ISBLANK(Sales[[#This Row],[Место]]),"",CONCATENATE("T-00"&ROW()-1)) -> T-0017 | B18: 7 | C18: Москва (Казанский) | D18: Миллерово | E18: =IFERROR(_xlfn.XLOOKUP(Sales[[#This Row],[Станция ОТ]],Справочник_станций_и_сборов[Станция (остановка)],Справочник_станций_и_сборов[ID]),"") -> 1 | F18: =IFERROR(_xlfn.XLOOKUP(Sales[[#This Row],[Станция ДО]],Справочник_станций_и_сборов[Станция (остановка)],Справочник_станций_и_сборов[ID]),"") -> 16 | G18: Полный | H18: =IF(ISBLANK(Sales[[#This Row],[Место]]),"",IF(Sales[[#This Row],[Место]]>36, IF(MOD(Sales[[#This Row],[Место]],2)=0, "Верхнее боковое место", "Нижнее боковое место"), IF(MOD(Sales[[#This Row],[Место]],2)=0, "Верхнее место", "Нижнее место"))) -> Нижнее место | I18: =IFERROR(((_xlfn.XLOOKUP(Sales[[#This Row],[Станция ДО]],Справочник_станций_и_сборов[Станция (остановка)],Справочник_станций_и_сборов[Расстояние от Мск (км)],)-_xlfn.XLOOKUP(Sales[[#This Row],[Станция ОТ]],Справочник_станций_и_сборов[Станция (остановка)],Справочник_станций_и_сборов[Расстояние от Мск (км)],))*Справочник!$Q$3+Справочник!$Q$2),"") -> 4286 | J18: =IFERROR(Sales[[#This Row],[Базовая цена, руб]] * _xlfn.XLOOKUP(Sales[[#This Row],[Тип пассажира]],Тип_пассажира[Наименование],Тип_пассажира[Цена]), "") -> 0 | K18: =IFERROR(Sales[[#This Row],[Базовая цена, руб]] * VALUE(_xlfn.XLOOKUP(Sales[[#This Row],[Тип полки]], Тариф_полок[Тип полки], Тариф_полок[Коэф-нт цены], 1)),"") -> 0 | L18: =IFERROR((Sales[[#This Row],[Базовая цена, руб]]-Sales[[#This Row],[Сумма скидки льготникам, руб]])-Sales[[#This Row],[Сумма скидки тип-места, руб2]],"") -> 4286 | N18: =IF(ISBLANK(P18),"","Свободно") -> Свободно | O18: =IF(ISBLANK(P18),"",IF(P18>36, IF(MOD(P18,2)=0, "Верхнее боковое место", "Нижнее боковое место"), IF(MOD(P18,2)=0, "Верхнее место", "Нижнее место"))) -> Верхнее место | P18: 32 | Q18: =IFERROR(VLOOKUP(P18,Аналитика!A19:AH72,34,0),"") -> Частично | S18: Тарасовка | T18: =VALUE(_xlfn.XLOOKUP(S18,Справочник_станций_и_сборов[Станция (остановка)],Справочник_станций_и_сборов[ID])) -> 17
A19: =IF(ISBLANK(Sales[[#This Row],[Место]]),"",CONCATENATE("T-00"&ROW()-1)) -> T-0018 | B19: 8 | C19: Москва (Казанский) | D19: Лиски | E19: =IFERROR(_xlfn.XLOOKUP(Sales[[#This Row],[Станция ОТ]],Справочник_станций_и_сборов[Станция (остановка)],Справочник_станций_и_сборов[ID]),"") -> 1 | F19: =IFERROR(_xlfn.XLOOKUP(Sales[[#This Row],[Станция ДО]],Справочник_станций_и_сборов[Станция (остановка)],Справочник_станций_и_сборов[ID]),"") -> 7 | G19: Полный | H19: =IF(ISBLANK(Sales[[#This Row],[Место]]),"",IF(Sales[[#This Row],[Место]]>36, IF(MOD(Sales[[#This Row],[Место]],2)=0, "Верхнее боковое место", "Нижнее боковое место"), IF(MOD(Sales[[#This Row],[Место]],2)=0, "Верхнее место", "Нижнее место"))) -> Верхнее место | I19: =IFERROR(((_xlfn.XLOOKUP(Sales[[#This Row],[Станция ДО]],Справочник_станций_и_сборов[Станция (остановка)],Справочник_станций_и_сборов[Расстояние от Мск (км)],)-_xlfn.XLOOKUP(Sales[[#This Row],[Станция ОТ]],Справочник_станций_и_сборов[Станция (остановка)],Справочник_станций_и_сборов[Расстояние от Мск (км)],))*Справочник!$Q$3+Справочник!$Q$2),"") -> 3204.5 | J19: =IFERROR(Sales[[#This Row],[Базовая цена, руб]] * _xlfn.XLOOKUP(Sales[[#This Row],[Тип пассажира]],Тип_пассажира[Наименование],Тип_пассажира[Цена]), "") -> 0 | K19: =IFERROR(Sales[[#This Row],[Базовая цена, руб]] * VALUE(_xlfn.XLOOKUP(Sales[[#This Row],[Тип полки]], Тариф_полок[Тип полки], Тариф_полок[Коэф-нт цены], 1)),"") -> 320.45 | L19: =IFERROR((Sales[[#This Row],[Базовая цена, руб]]-Sales[[#This Row],[Сумма скидки льготникам, руб]])-Sales[[#This Row],[Сумма скидки тип-места, руб2]],"") -> 2884.05 | N19: =IF(ISBLANK(P19),"","Свободно") -> Свободно | O19: =IF(ISBLANK(P19),"",IF(P19>36, IF(MOD(P19,2)=0, "Верхнее боковое место", "Нижнее боковое место"), IF(MOD(P19,2)=0, "Верхнее место", "Нижнее место"))) -> Верхнее место | P19: 34 | Q19: =IFERROR(VLOOKUP(P19,Аналитика!A20:AH73,34,0),"") -> Частично | S19: Глубокая | T19: =VALUE(_xlfn.XLOOKUP(S19,Справочник_станций_и_сборов[Станция (остановка)],Справочник_станций_и_сборов[ID])) -> 18
A20: =IF(ISBLANK(Sales[[#This Row],[Место]]),"",CONCATENATE("T-00"&ROW()-1)) -> T-0019 | B20: 9 | C20: Москва (Казанский) | D20: Воронеж 1 | E20: =IFERROR(_xlfn.XLOOKUP(Sales[[#This Row],[Станция ОТ]],Справочник_станций_и_сборов[Станция (остановка)],Справочник_станций_и_сборов[ID]),"") -> 1 | F20: =IFERROR(_xlfn.XLOOKUP(Sales[[#This Row],[Станция ДО]],Справочник_станций_и_сборов[Станция (остановка)],Справочник_станций_и_сборов[ID]),"") -> 6 | G20: Полный | H20: =IF(ISBLANK(Sales[[#This Row],[Место]]),"",IF(Sales[[#This Row],[Место]]>36, IF(MOD(Sales[[#This Row],[Место]],2)=0, "Верхнее боковое место", "Нижнее боковое место"), IF(MOD(Sales[[#This Row],[Место]],2)=0, "Верхнее место", "Нижнее место"))) -> Нижнее место | I20: =IFERROR(((_xlfn.XLOOKUP(Sales[[#This Row],[Станция ДО]],Справочник_станций_и_сборов[Станция (остановка)],Справочник_станций_и_сборов[Расстояние от Мск (км)],)-_xlfn.XLOOKUP(Sales[[#This Row],[Станция ОТ]],Справочник_станций_и_сборов[Станция (остановка)],Справочник_станций_и_сборов[Расстояние от Мск (км)],))*Справочник!$Q$3+Справочник!$Q$2),"") -> 2861.5 | J20: =IFERROR(Sales[[#This Row],[Базовая цена, руб]] * _xlfn.XLOOKUP(Sales[[#This Row],[Тип пассажира]],Тип_пассажира[Наименование],Тип_пассажира[Цена]), "") -> 0 | K20: =IFERROR(Sales[[#This Row],[Базовая цена, руб]] * VALUE(_xlfn.XLOOKUP(Sales[[#This Row],[Тип полки]], Тариф_полок[Тип полки], Тариф_полок[Коэф-нт цены], 1)),"") -> 0 | L20: =IFERROR((Sales[[#This Row],[Базовая цена, руб]]-Sales[[#This Row],[Сумма скидки льготникам, руб]])-Sales[[#This Row],[Сумма скидки тип-места, руб2]],"") -> 2861.5 | N20: =IF(ISBLANK(P20),"","Свободно") -> Свободно | O20: =IF(ISBLANK(P20),"",IF(P20>36, IF(MOD(P20,2)=0, "Верхнее боковое место", "Нижнее боковое место"), IF(MOD(P20,2)=0, "Верхнее место", "Нижнее место"))) -> Нижнее место | P20: 35 | Q20: =IFERROR(VLOOKUP(P20,Аналитика!A21:AH74,34,0),"") -> Частично | S20: Каменская | T20: =VALUE(_xlfn.XLOOKUP(S20,Справочник_станций_и_сборов[Станция (остановка)],Справочник_станций_и_сборов[ID])) -> 19
A21: =IF(ISBLANK(Sales[[#This Row],[Место]]),"",CONCATENATE("T-00"&ROW()-1)) -> T-0020 | B21: 10 | C21: Москва (Казанский) | D21: Ростов-Главный | E21: =IFERROR(_xlfn.XLOOKUP(Sales[[#This Row],[Станция ОТ]],Справочник_станций_и_сборов[Станция (остановка)],Справочник_станций_и_сборов[ID]),"") -> 1 | F21: =IFERROR(_xlfn.XLOOKUP(Sales[[#This Row],[Станция ДО]],Справочник_станций_и_сборов[Станция (остановка)],Справочник_станций_и_сборов[ID]),"") -> 30 | G21: Полный | H21: =IF(ISBLANK(Sales[[#This Row],[Место]]),"",IF(Sales[[#This Row],[Место]]>36, IF(MOD(Sales[[#This Row],[Место]],2)=0, "Верхнее боковое место", "Нижнее боковое место"), IF(MOD(Sales[[#This Row],[Место]],2)=0, "Верхнее место", "Нижнее место"))) -> Верхнее место | I21: =IFERROR(((_xlfn.XLOOKUP(Sales[[#This Row],[Станция ДО]],Справочник_станций_и_сборов[Станция (остановка)],Справочник_станций_и_сборов[Расстояние от Мск (км)],)-_xlfn.XLOOKUP(Sales[[#This Row],[Станция ОТ]],Справочник_станций_и_сборов[Станция (остановка)],Справочник_станций_и_сборов[Расстояние от Мск (км)],))*Справочник!$Q$3+Справочник!$Q$2),"") -> 5105 | J21: =IFERROR(Sales[[#This Row],[Базовая цена, руб]] * _xlfn.XLOOKUP(Sales[[#This Row],[Тип пассажира]],Тип_пассажира[Наименование],Тип_пассажира[Цена]), "") -> 0 | K21: =IFERROR(Sales[[#This Row],[Базовая цена, руб]] * VALUE(_xlfn.XLOOKUP(Sales[[#This Row],[Тип полки]], Тариф_полок[Тип полки], Тариф_полок[Коэф-нт цены], 1)),"") -> 510.5 | L21: =IFERROR((Sales[[#This Row],[Базовая цена, руб]]-Sales[[#This Row],[Сумма скидки льготникам, руб]])-Sales[[#This Row],[Сумма скидки тип-места, руб2]],"") -> 4594.5 | N21: =IF(ISBLANK(P21),"","Свободно") -> Свободно | O21: =IF(ISBLANK(P21),"",IF(P21>36, IF(MOD(P21,2)=0, "Верхнее боковое место", "Нижнее боковое место"), IF(MOD(P21,2)=0, "Верхнее место", "Нижнее место"))) -> Верхнее место | P21: 36 | Q21: =IFERROR(VLOOKUP(P21,Аналитика!A22:AH75,34,0),"") -> Частично | S21: Лихая | T21: =VALUE(_xlfn.XLOOKUP(S21,Справочник_станций_и_сборов[Станция (остановка)],Справочник_станций_и_сборов[ID])) -> 20
A22: =IF(ISBLANK(Sales[[#This Row],[Место]]),"",CONCATENATE("T-00"&ROW()-1)) -> T-0021 | B22: 6 | C22: Воронеж 1 | D22: Глубокая | E22: =IFERROR(_xlfn.XLOOKUP(Sales[[#This Row],[Станция ОТ]],Справочник_станций_и_сборов[Станция (остановка)],Справочник_станций_и_сборов[ID]),"") -> 6 | F22: =IFERROR(_xlfn.XLOOKUP(Sales[[#This Row],[Станция ДО]],Справочник_станций_и_сборов[Станция (остановка)],Справочник_станций_и_сборов[ID]),"") -> 18 | G22: Полный | H22: =IF(ISBLANK(Sales[[#This Row],[Место]]),"",IF(Sales[[#This Row],[Место]]>36, IF(MOD(Sales[[#This Row],[Место]],2)=0, "Верхнее боковое место", "Нижнее боковое место"), IF(MOD(Sales[[#This Row],[Место]],2)=0, "Верхнее место", "Нижнее место"))) -> Верхнее место | I22: =IFERROR(((_xlfn.XLOOKUP(Sales[[#This Row],[Станция ДО]],Справочник_станций_и_сборов[Станция (остановка)],Справочник_станций_и_сборов[Расстояние от Мск (км)],)-_xlfn.XLOOKUP(Sales[[#This Row],[Станция ОТ]],Справочник_станций_и_сборов[Станция (остановка)],Справочник_станций_и_сборов[Расстояние от Мск (км)],))*Справочник!$Q$3+Справочник!$Q$2),"") -> 2385.5 | J22: =IFERROR(Sales[[#This Row],[Базовая цена, руб]] * _xlfn.XLOOKUP(Sales[[#This Row],[Тип пассажира]],Тип_пассажира[Наименование],Тип_пассажира[Цена]), "") -> 0 | K22: =IFERROR(Sales[[#This Row],[Базовая цена, руб]] * VALUE(_xlfn.XLOOKUP(Sales[[#This Row],[Тип полки]], Тариф_полок[Тип полки], Тариф_полок[Коэф-нт цены], 1)),"") -> 238.55 | L22: =IFERROR((Sales[[#This Row],[Базовая цена, руб]]-Sales[[#This Row],[Сумма скидки льготникам, руб]])-Sales[[#This Row],[Сумма скидки тип-места, руб2]],"") -> 2146.95 | N22: =IF(ISBLANK(P22),"","Свободно") -> Свободно | O22: =IF(ISBLANK(P22),"",IF(P22>36, IF(MOD(P22,2)=0, "Верхнее боковое место", "Нижнее боковое место"), IF(MOD(P22,2)=0, "Верхнее место", "Нижнее место"))) -> Нижнее боковое место | P22: 37 | Q22: =IFERROR(VLOOKUP(P22,Аналитика!A23:AH76,34,0),"") -> Частично | S22: Замчалово | T22: =VALUE(_xlfn.XLOOKUP(S22,Справочник_станций_и_сборов[Станция (остановка)],Справочник_станций_и_сборов[ID])) -> 21
A23: =IF(ISBLANK(Sales[[#This Row],[Место]]),"",CONCATENATE("T-00"&ROW()-1)) -> T-0022 | B23: 11 | C23: Москва (Казанский) | D23: Ростов-Главный | E23: =IFERROR(_xlfn.XLOOKUP(Sales[[#This Row],[Станция ОТ]],Справочник_станций_и_сборов[Станция (остановка)],Справочник_станций_и_сборов[ID]),"") -> 1 | F23: =IFERROR(_xlfn.XLOOKUP(Sales[[#This Row],[Станция ДО]],Справочник_станций_и_сборов[Станция (остановка)],Справочник_станций_и_сборов[ID]),"") -> 30 | G23: Дети (до 10 лет): | H23: =IF(ISBLANK(Sales[[#This Row],[Место]]),"",IF(Sales[[#This Row],[Место]]>36, IF(MOD(Sales[[#This Row],[Место]],2)=0, "Верхнее боковое место", "Нижнее боковое место"), IF(MOD(Sales[[#This Row],[Место]],2)=0, "Верхнее место", "Нижнее место"))) -> Нижнее место | I23: =IFERROR(((_xlfn.XLOOKUP(Sales[[#This Row],[Станция ДО]],Справочник_станций_и_сборов[Станция (остановка)],Справочник_станций_и_сборов[Расстояние от Мск (км)],)-_xlfn.XLOOKUP(Sales[[#This Row],[Станция ОТ]],Справочник_станций_и_сборов[Станция (остановка)],Справочник_станций_и_сборов[Расстояние от Мск (км)],))*Справочник!$Q$3+Справочник!$Q$2),"") -> 5105 | J23: =IFERROR(Sales[[#This Row],[Базовая цена, руб]] * _xlfn.XLOOKUP(Sales[[#This Row],[Тип пассажира]],Тип_пассажира[Наименование],Тип_пассажира[Цена]), "") -> 1786.75 | K23: =IFERROR(Sales[[#This Row],[Базовая цена, руб]] * VALUE(_xlfn.XLOOKUP(Sales[[#This Row],[Тип полки]], Тариф_полок[Тип полки], Тариф_полок[Коэф-нт цены], 1)),"") -> 0 | L23: =IFERROR((Sales[[#This Row],[Базовая цена, руб]]-Sales[[#This Row],[Сумма скидки льготникам, руб]])-Sales[[#This Row],[Сумма скидки тип-места, руб2]],"") -> 3318.25 | N23: =IF(ISBLANK(P23),"","Свободно") -> Свободно | O23: =IF(ISBLANK(P23),"",IF(P23>36, IF(MOD(P23,2)=0, "Верхнее боковое место", "Нижнее боковое место"), IF(MOD(P23,2)=0, "Верхнее место", "Нижнее место"))) -> Верхнее боковое место | P23: 38 | Q23: =IFERROR(VLOOKUP(P23,Аналитика!A24:AH77,34,0),"") -> Частично | S23: Зверево | T23: =VALUE(_xlfn.XLOOKUP(S23,Справочник_станций_и_сборов[Станция (остановка)],Справочник_станций_и_сборов[ID])) -> 22
A24: =IF(ISBLANK(Sales[[#This Row],[Место]]),"",CONCATENATE("T-00"&ROW()-1)) -> T-0023 | B24: 12 | C24: Москва (Казанский) | D24: Ростов-Главный | E24: =IFERROR(_xlfn.XLOOKUP(Sales[[#This Row],[Станция ОТ]],Справочник_станций_и_сборов[Станция (остановка)],Справочник_станций_и_сборов[ID]),"") -> 1 | F24: =IFERROR(_xlfn.XLOOKUP(Sales[[#This Row],[Станция ДО]],Справочник_станций_и_сборов[Станция (остановка)],Справочник_станций_и_сборов[ID]),"") -> 30 | G24: Школьники/Студенты: | H24: =IF(ISBLANK(Sales[[#This Row],[Место]]),"",IF(Sales[[#This Row],[Место]]>36, IF(MOD(Sales[[#This Row],[Место]],2)=0, "Верхнее боковое место", "Нижнее боковое место"), IF(MOD(Sales[[#This Row],[Место]],2)=0, "Верхнее место", "Нижнее место"))) -> Верхнее место | I24: =IFERROR(((_xlfn.XLOOKUP(Sales[[#This Row],[Станция ДО]],Справочник_станций_и_сборов[Станция (остановка)],Справочник_станций_и_сборов[Расстояние от Мск (км)],)-_xlfn.XLOOKUP(Sales[[#This Row],[Станция ОТ]],Справочник_станций_и_сборов[Станция (остановка)],Справочник_станций_и_сборов[Расстояние от Мск (км)],))*Справочник!$Q$3+Справочник!$Q$2),"") -> 5105 | J24: =IFERROR(Sales[[#This Row],[Базовая цена, руб]] * _xlfn.XLOOKUP(Sales[[#This Row],[Тип пассажира]],Тип_пассажира[Наименование],Тип_пассажира[Цена]), "") -> 2552.5 | K24: =IFERROR(Sales[[#This Row],[Базовая цена, руб]] * VALUE(_xlfn.XLOOKUP(Sales[[#This Row],[Тип полки]], Тариф_полок[Тип полки], Тариф_полок[Коэф-нт цены], 1)),"") -> 510.5 | L24: =IFERROR((Sales[[#This Row],[Базовая цена, руб]]-Sales[[#This Row],[Сумма скидки льготникам, руб]])-Sales[[#This Row],[Сумма скидки тип-места, руб2]],"") -> 2042 | N24: =IF(ISBLANK(P24),"","Свободно") -> Свободно | O24: =IF(ISBLANK(P24),"",IF(P24>36, IF(MOD(P24,2)=0, "Верхнее боковое место", "Нижнее боковое место"), IF(MOD(P24,2)=0, "Верхнее место", "Нижнее место"))) -> Верхнее боковое место | P24: 40 | Q24: =IFERROR(VLOOKUP(P24,Аналитика!A25:AH78,34,0),"") -> Частично | S24: Сулин | T24: =VALUE(_xlfn.XLOOKUP(S24,Справочник_станций_и_сборов[Станция (остановка)],Справочник_станций_и_сборов[ID])) -> 23
A25: =IF(ISBLANK(Sales[[#This Row],[Место]]),"",CONCATENATE("T-00"&ROW()-1)) -> T-0024 | B25: 0 | C25: Москва (Казанский) | D25: Ростов-Главный | E25: =IFERROR(_xlfn.XLOOKUP(Sales[[#This Row],[Станция ОТ]],Справочник_станций_и_сборов[Станция (остановка)],Справочник_станций_и_сборов[ID]),"") -> 1 | F25: =IFERROR(_xlfn.XLOOKUP(Sales[[#This Row],[Станция ДО]],Справочник_станций_и_сборов[Станция (остановка)],Справочник_станций_и_сборов[ID]),"") -> 30 | G25: Младенцы (до 5 лет): | H25: =IF(ISBLANK(Sales[[#This Row],[Место]]),"",IF(Sales[[#This Row],[Место]]>36, IF(MOD(Sales[[#This Row],[Место]],2)=0, "Верхнее боковое место", "Нижнее боковое место"), IF(MOD(Sales[[#This Row],[Место]],2)=0, "Верхнее место", "Нижнее место"))) -> Верхнее место | I25: =IFERROR(((_xlfn.XLOOKUP(Sales[[#This Row],[Станция ДО]],Справочник_станций_и_сборов[Станция (остановка)],Справочник_станций_и_сборов[Расстояние от Мск (км)],)-_xlfn.XLOOKUP(Sales[[#This Row],[Станция ОТ]],Справочник_станций_и_сборов[Станция (остановка)],Справочник_станций_и_сборов[Расстояние от Мск (км)],))*Справочник!$Q$3+Справочник!$Q$2),"") -> 5105 | J25: =IFERROR(Sales[[#This Row],[Базовая цена, руб]] * _xlfn.XLOOKUP(Sales[[#This Row],[Тип пассажира]],Тип_пассажира[Наименование],Тип_пассажира[Цена]), "") -> 5105 | K25: =IFERROR(Sales[[#This Row],[Базовая цена, руб]] * VALUE(_xlfn.XLOOKUP(Sales[[#This Row],[Тип полки]], Тариф_полок[Тип полки], Тариф_полок[Коэф-нт цены], 1)),"") -> 510.5 | L25: =IFERROR((Sales[[#This Row],[Базовая цена, руб]]-Sales[[#This Row],[Сумма скидки льготникам, руб]])-Sales[[#This Row],[Сумма скидки тип-места, руб2]],"") -> -510.5 | N25: =IF(ISBLANK(P25),"","Свободно") -> Свободно | O25: =IF(ISBLANK(P25),"",IF(P25>36, IF(MOD(P25,2)=0, "Верхнее боковое место", "Нижнее боковое место"), IF(MOD(P25,2)=0, "Верхнее место", "Нижнее место"))) -> Нижнее боковое место | P25: 41 | Q25: =IFERROR(VLOOKUP(P25,Аналитика!A26:AH79,34,0),"") -> Целое купе/отсек | S25: Шахтная | T25: =VALUE(_xlfn.XLOOKUP(S25,Справочник_станций_и_сборов[Станция (остановка)],Справочник_станций_и_сборов[ID])) -> 24
A26: =IF(ISBLANK(Sales[[#This Row],[Место]]),"",CONCATENATE("T-00"&ROW()-1)) -> T-0025 | B26: 3 | C26: Лиски | D26: Россошь | E26: =IFERROR(_xlfn.XLOOKUP(Sales[[#This Row],[Станция ОТ]],Справочник_станций_и_сборов[Станция (остановка)],Справочник_станций_и_сборов[ID]),"") -> 7 | F26: =IFERROR(_xlfn.XLOOKUP(Sales[[#This Row],[Станция ДО]],Справочник_станций_и_сборов[Станция (остановка)],Справочник_станций_и_сборов[ID]),"") -> 12 | G26: Полный | H26: =IF(ISBLANK(Sales[[#This Row],[Место]]),"",IF(Sales[[#This Row],[Место]]>36, IF(MOD(Sales[[#This Row],[Место]],2)=0, "Верхнее боковое место", "Нижнее боковое место"), IF(MOD(Sales[[#This Row],[Место]],2)=0, "Верхнее место", "Нижнее место"))) -> Нижнее место | I26: =IFERROR(((_xlfn.XLOOKUP(Sales[[#This Row],[Станция ДО]],Справочник_станций_и_сборов[Станция (остановка)],Справочник_станций_и_сборов[Расстояние от Мск (км)],)-_xlfn.XLOOKUP(Sales[[#This Row],[Станция ОТ]],Справочник_станций_и_сборов[Станция (остановка)],Справочник_станций_и_сборов[Расстояние от Мск (км)],))*Справочник!$Q$3+Справочник!$Q$2),"") -> 1276 | J26: =IFERROR(Sales[[#This Row],[Базовая цена, руб]] * _xlfn.XLOOKUP(Sales[[#This Row],[Тип пассажира]],Тип_пассажира[Наименование],Тип_пассажира[Цена]), "") -> 0 | K26: =IFERROR(Sales[[#This Row],[Базовая цена, руб]] * VALUE(_xlfn.XLOOKUP(Sales[[#This Row],[Тип полки]], Тариф_полок[Тип полки], Тариф_полок[Коэф-нт цены], 1)),"") -> 0 | L26: =IFERROR((Sales[[#This Row],[Базовая цена, руб]]-Sales[[#This Row],[Сумма скидки льготникам, руб]])-Sales[[#This Row],[Сумма скидки тип-места, руб2]],"") -> 1276 | N26: =IF(ISBLANK(P26),"","Свободно") -> Свободно | O26: =IF(ISBLANK(P26),"",IF(P26>36, IF(MOD(P26,2)=0, "Верхнее боковое место", "Нижнее боковое место"), IF(MOD(P26,2)=0, "Верхнее место", "Нижнее место"))) -> Верхнее боковое место | P26: 42 | Q26: =IFERROR(VLOOKUP(P26,Аналитика!A27:AH80,34,0),"") -> Целое купе/отсек | S26: Каменоломни | T26: =VALUE(_xlfn.XLOOKUP(S26,Справочник_станций_и_сборов[Станция (остановка)],Справочник_станций_и_сборов[ID])) -> 25
A27: =IF(ISBLANK(Sales[[#This Row],[Место]]),"",CONCATENATE("T-00"&ROW()-1)) -> T-0026 | B27: 13 | C27: Грязи-Воронежские | D27: Новочеркасск | E27: =IFERROR(_xlfn.XLOOKUP(Sales[[#This Row],[Станция ОТ]],Справочник_станций_и_сборов[Станция (остановка)],Справочник_станций_и_сборов[ID]),"") -> 5 | F27: =IFERROR(_xlfn.XLOOKUP(Sales[[#This Row],[Станция ДО]],Справочник_станций_и_сборов[Станция (остановка)],Справочник_станций_и_сборов[ID]),"") -> 28 | G27: Полный | H27: =IF(ISBLANK(Sales[[#This Row],[Место]]),"",IF(Sales[[#This Row],[Место]]>36, IF(MOD(Sales[[#This Row],[Место]],2)=0, "Верхнее боковое место", "Нижнее боковое место"), IF(MOD(Sales[[#This Row],[Место]],2)=0, "Верхнее место", "Нижнее место"))) -> Нижнее место | I27: =IFERROR(((_xlfn.XLOOKUP(Sales[[#This Row],[Станция ДО]],Справочник_станций_и_сборов[Станция (остановка)],Справочник_станций_и_сборов[Расстояние от Мск (км)],)-_xlfn.XLOOKUP(Sales[[#This Row],[Станция ОТ]],Справочник_станций_и_сборов[Станция (остановка)],Справочник_станций_и_сборов[Расстояние от Мск (км)],))*Справочник!$Q$3+Справочник!$Q$2),"") -> 3334 | J27: =IFERROR(Sales[[#This Row],[Базовая цена, руб]] * _xlfn.XLOOKUP(Sales[[#This Row],[Тип пассажира]],Тип_пассажира[Наименование],Тип_пассажира[Цена]), "") -> 0 | K27: =IFERROR(Sales[[#This Row],[Базовая цена, руб]] * VALUE(_xlfn.XLOOKUP(Sales[[#This Row],[Тип полки]], Тариф_полок[Тип полки], Тариф_полок[Коэф-нт цены], 1)),"") -> 0 | L27: =IFERROR((Sales[[#This Row],[Базовая цена, руб]]-Sales[[#This Row],[Сумма скидки льготникам, руб]])-Sales[[#This Row],[Сумма скидки тип-места, руб2]],"") -> 3334 | N27: =IF(ISBLANK(P27),"","Свободно") -> Свободно | O27: =IF(ISBLANK(P27),"",IF(P27>36, IF(MOD(P27,2)=0, "Верхнее боковое место", "Нижнее боковое место"), IF(MOD(P27,2)=0, "Верхнее место", "Нижнее место"))) -> Нижнее боковое место | P27: 43 | Q27: =IFERROR(VLOOKUP(P27,Аналитика!A28:AH81,34,0),"") -> Целое купе/отсек | S27: Персиановка | T27: =VALUE(_xlfn.XLOOKUP(S27,Справочник_станций_и_сборов[Станция (остановка)],Справочник_станций_и_сборов[ID])) -> 26
A28: =IF(ISBLANK(Sales[[#This Row],[Место]]),"",CONCATENATE("T-00"&ROW()-1)) -> T-0027 | B28: 14 | C28: Москва (Казанский) | D28: Чертково | E28: =IFERROR(_xlfn.XLOOKUP(Sales[[#This Row],[Станция ОТ]],Справочник_станций_и_сборов[Станция (остановка)],Справочник_станций_и_сборов[ID]),"") -> 1 | F28: =IFERROR(_xlfn.XLOOKUP(Sales[[#This Row],[Станция ДО]],Справочник_станций_и_сборов[Станция (остановка)],Справочник_станций_и_сборов[ID]),"") -> 15 | G28: Полный | H28: =IF(ISBLANK(Sales[[#This Row],[Место]]),"",IF(Sales[[#This Row],[Место]]>36, IF(MOD(Sales[[#This Row],[Место]],2)=0, "Верхнее боковое место", "Нижнее боковое место"), IF(MOD(Sales[[#This Row],[Место]],2)=0, "Верхнее место", "Нижнее место"))) -> Верхнее место | I28: =IFERROR(((_xlfn.XLOOKUP(Sales[[#This Row],[Станция ДО]],Справочник_станций_и_сборов[Станция (остановка)],Справочник_станций_и_сборов[Расстояние от Мск (км)],)-_xlfn.XLOOKUP(Sales[[#This Row],[Станция ОТ]],Справочник_станций_и_сборов[Станция (остановка)],Справочник_станций_и_сборов[Расстояние от Мск (км)],))*Справочник!$Q$3+Справочник!$Q$2),"") -> 4055 | J28: =IFERROR(Sales[[#This Row],[Базовая цена, руб]] * _xlfn.XLOOKUP(Sales[[#This Row],[Тип пассажира]],Тип_пассажира[Наименование],Тип_пассажира[Цена]), "") -> 0 | K28: =IFERROR(Sales[[#This Row],[Базовая цена, руб]] * VALUE(_xlfn.XLOOKUP(Sales[[#This Row],[Тип полки]], Тариф_полок[Тип полки], Тариф_полок[Коэф-нт цены], 1)),"") -> 405.5 | L28: =IFERROR((Sales[[#This Row],[Базовая цена, руб]]-Sales[[#This Row],[Сумма скидки льготникам, руб]])-Sales[[#This Row],[Сумма скидки тип-места, руб2]],"") -> 3649.5 | N28: =IF(ISBLANK(P28),"","Свободно") -> Свободно | O28: =IF(ISBLANK(P28),"",IF(P28>36, IF(MOD(P28,2)=0, "Верхнее боковое место", "Нижнее боковое место"), IF(MOD(P28,2)=0, "Верхнее место", "Нижнее место"))) -> Верхнее боковое место | P28: 44 | Q28: =IFERROR(VLOOKUP(P28,Аналитика!A29:AH82,34,0),"") -> Целое купе/отсек | S28: Хотунок | T28: =VALUE(_xlfn.XLOOKUP(S28,Справочник_станций_и_сборов[Станция (остановка)],Справочник_станций_и_сборов[ID])) -> 27
A29: =IF(ISBLANK(Sales[[#This Row],[Место]]),"",CONCATENATE("T-00"&ROW()-1)) | E29: =IFERROR(_xlfn.XLOOKUP(Sales[[#This Row],[Станция ОТ]],Справочник_станций_и_сборов[Станция (остановка)],Справочник_станций_и_сборов[ID]),"") | F29: =IFERROR(_xlfn.XLOOKUP(Sales[[#This Row],[Станция ДО]],Справочник_станций_и_сборов[Станция (остановка)],Справочник_станций_и_сборов[ID]),"") | H29: =IF(ISBLANK(Sales[[#This Row],[Место]]),"",IF(Sales[[#This Row],[Место]]>36, IF(MOD(Sales[[#This Row],[Место]],2)=0, "Верхнее боковое место", "Нижнее боковое место"), IF(MOD(Sales[[#This Row],[Место]],2)=0, "Верхнее место", "Нижнее место"))) | I29: =IFERROR(((_xlfn.XLOOKUP(Sales[[#This Row],[Станция ДО]],Справочник_станций_и_сборов[Станция (остановка)],Справочник_станций_и_сборов[Расстояние от Мск (км)],)-_xlfn.XLOOKUP(Sales[[#This Row],[Станция ОТ]],Справочник_станций_и_сборов[Станция (остановка)],Справочник_станций_и_сборов[Расстояние от Мск (км)],))*Справочник!$Q$3+Справочник!$Q$2),"") | J29: =IFERROR(Sales[[#This Row],[Базовая цена, руб]] * _xlfn.XLOOKUP(Sales[[#This Row],[Тип пассажира]],Тип_пассажира[Наименование],Тип_пассажира[Цена]), "") | K29: =IFERROR(Sales[[#This Row],[Базовая цена, руб]] * VALUE(_xlfn.XLOOKUP(Sales[[#This Row],[Тип полки]], Тариф_полок[Тип полки], Тариф_полок[Коэф-нт цены], 1)),"") | L29: =IFERROR((Sales[[#This Row],[Базовая цена, руб]]-Sales[[#This Row],[Сумма скидки льготникам, руб]])-Sales[[#This Row],[Сумма скидки тип-места, руб2]],"") | N29: =IF(ISBLANK(P29),"","Свободно") -> Свободно | O29: =IF(ISBLANK(P29),"",IF(P29>36, IF(MOD(P29,2)=0, "Верхнее боковое место", "Нижнее боковое место"), IF(MOD(P29,2)=0, "Верхнее место", "Нижнее место"))) -> Нижнее боковое место | P29: 45 | Q29: =IFERROR(VLOOKUP(P29,Аналитика!A30:AH83,34,0),"") -> Частично | S29: Новочеркасск | T29: =VALUE(_xlfn.XLOOKUP(S29,Справочник_станций_и_сборов[Станция (остановка)],Справочник_станций_и_сборов[ID])) -> 28
A30: =IF(ISBLANK(Sales[[#This Row],[Место]]),"",CONCATENATE("T-00"&ROW()-1)) | E30: =IFERROR(_xlfn.XLOOKUP(Sales[[#This Row],[Станция ОТ]],Справочник_станций_и_сборов[Станция (остановка)],Справочник_станций_и_сборов[ID]),"") | F30: =IFERROR(_xlfn.XLOOKUP(Sales[[#This Row],[Станция ДО]],Справочник_станций_и_сборов[Станция (остановка)],Справочник_станций_и_сборов[ID]),"") | H30: =IF(ISBLANK(Sales[[#This Row],[Место]]),"",IF(Sales[[#This Row],[Место]]>36, IF(MOD(Sales[[#This Row],[Место]],2)=0, "Верхнее боковое место", "Нижнее боковое место"), IF(MOD(Sales[[#This Row],[Место]],2)=0, "Верхнее место", "Нижнее место"))) | I30: =IFERROR(((_xlfn.XLOOKUP(Sales[[#This Row],[Станция ДО]],Справочник_станций_и_сборов[Станция (остановка)],Справочник_станций_и_сборов[Расстояние от Мск (км)],)-_xlfn.XLOOKUP(Sales[[#This Row],[Станция ОТ]],Справочник_станций_и_сборов[Станция (остановка)],Справочник_станций_и_сборов[Расстояние от Мск (км)],))*Справочник!$Q$3+Справочник!$Q$2),"") | J30: =IFERROR(Sales[[#This Row],[Базовая цена, руб]] * _xlfn.XLOOKUP(Sales[[#This Row],[Тип пассажира]],Тип_пассажира[Наименование],Тип_пассажира[Цена]), "") | K30: =IFERROR(Sales[[#This Row],[Базовая цена, руб]] * VALUE(_xlfn.XLOOKUP(Sales[[#This Row],[Тип полки]], Тариф_полок[Тип полки], Тариф_полок[Коэф-нт цены], 1)),"") | L30: =IFERROR((Sales[[#This Row],[Базовая цена, руб]]-Sales[[#This Row],[Сумма скидки льготникам, руб]])-Sales[[#This Row],[Сумма скидки тип-места, руб2]],"") | N30: =IF(ISBLANK(P30),"","Свободно") -> Свободно | O30: =IF(ISBLANK(P30),"",IF(P30>36, IF(MOD(P30,2)=0, "Верхнее боковое место", "Нижнее боковое место"), IF(MOD(P30,2)=0, "Верхнее место", "Нижнее место"))) -> Верхнее боковое место | P30: 46 | Q30: =IFERROR(VLOOKUP(P30,Аналитика!A31:AH84,34,0),"") -> Частично | S30: Александровка | T30: =VALUE(_xlfn.XLOOKUP(S30,Справочник_станций_и_сборов[Станция (остановка)],Справочник_станций_и_сборов[ID])) -> 29
A31: =IF(ISBLANK(Sales[[#This Row],[Место]]),"",CONCATENATE("T-00"&ROW()-1)) | E31: =IFERROR(_xlfn.XLOOKUP(Sales[[#This Row],[Станция ОТ]],Справочник_станций_и_сборов[Станция (остановка)],Справочник_станций_и_сборов[ID]),"") | F31: =IFERROR(_xlfn.XLOOKUP(Sales[[#This Row],[Станция ДО]],Справочник_станций_и_сборов[Станция (остановка)],Справочник_станций_и_сборов[ID]),"") | H31: =IF(ISBLANK(Sales[[#This Row],[Место]]),"",IF(Sales[[#This Row],[Место]]>36, IF(MOD(Sales[[#This Row],[Место]],2)=0, "Верхнее боковое место", "Нижнее боковое место"), IF(MOD(Sales[[#This Row],[Место]],2)=0, "Верхнее место", "Нижнее место"))) | I31: =IFERROR(((_xlfn.XLOOKUP(Sales[[#This Row],[Станция ДО]],Справочник_станций_и_сборов[Станция (остановка)],Справочник_станций_и_сборов[Расстояние от Мск (км)],)-_xlfn.XLOOKUP(Sales[[#This Row],[Станция ОТ]],Справочник_станций_и_сборов[Станция (остановка)],Справочник_станций_и_сборов[Расстояние от Мск (км)],))*Справочник!$Q$3+Справочник!$Q$2),"") | J31: =IFERROR(Sales[[#This Row],[Базовая цена, руб]] * _xlfn.XLOOKUP(Sales[[#This Row],[Тип пассажира]],Тип_пассажира[Наименование],Тип_пассажира[Цена]), "") | K31: =IFERROR(Sales[[#This Row],[Базовая цена, руб]] * VALUE(_xlfn.XLOOKUP(Sales[[#This Row],[Тип полки]], Тариф_полок[Тип полки], Тариф_полок[Коэф-нт цены], 1)),"") | L31: =IFERROR((Sales[[#This Row],[Базовая цена, руб]]-Sales[[#This Row],[Сумма скидки льготникам, руб]])-Sales[[#This Row],[Сумма скидки тип-места, руб2]],"") | N31: =IF(ISBLANK(P31),"","Свободно") -> Свободно | O31: =IF(ISBLANK(P31),"",IF(P31>36, IF(MOD(P31,2)=0, "Верхнее боковое место", "Нижнее боковое место"), IF(MOD(P31,2)=0, "Верхнее место", "Нижнее место"))) -> Нижнее боковое место | P31: 47 | Q31: =IFERROR(VLOOKUP(P31,Аналитика!A32:AH85,34,0),"") -> Частично | S31: Ростов-Главный | T31: =VALUE(_xlfn.XLOOKUP(S31,Справочник_станций_и_сборов[Станция (остановка)],Справочник_станций_и_сборов[ID])) -> 30
A32: =IF(ISBLANK(Sales[[#This Row],[Место]]),"",CONCATENATE("T-00"&ROW()-1)) | E32: =IFERROR(_xlfn.XLOOKUP(Sales[[#This Row],[Станция ОТ]],Справочник_станций_и_сборов[Станция (остановка)],Справочник_станций_и_сборов[ID]),"") | F32: =IFERROR(_xlfn.XLOOKUP(Sales[[#This Row],[Станция ДО]],Справочник_станций_и_сборов[Станция (остановка)],Справочник_станций_и_сборов[ID]),"") | H32: =IF(ISBLANK(Sales[[#This Row],[Место]]),"",IF(Sales[[#This Row],[Место]]>36, IF(MOD(Sales[[#This Row],[Место]],2)=0, "Верхнее боковое место", "Нижнее боковое место"), IF(MOD(Sales[[#This Row],[Место]],2)=0, "Верхнее место", "Нижнее место"))) | I32: =IFERROR(((_xlfn.XLOOKUP(Sales[[#This Row],[Станция ДО]],Справочник_станций_и_сборов[Станция (остановка)],Справочник_станций_и_сборов[Расстояние от Мск (км)],)-_xlfn.XLOOKUP(Sales[[#This Row],[Станция ОТ]],Справочник_станций_и_сборов[Станция (остановка)],Справочник_станций_и_сборов[Расстояние от Мск (км)],))*Справочник!$Q$3+Справочник!$Q$2),"") | J32: =IFERROR(Sales[[#This Row],[Базовая цена, руб]] * _xlfn.XLOOKUP(Sales[[#This Row],[Тип пассажира]],Тип_пассажира[Наименование],Тип_пассажира[Цена]), "") | K32: =IFERROR(Sales[[#This Row],[Базовая цена, руб]] * VALUE(_xlfn.XLOOKUP(Sales[[#This Row],[Тип полки]], Тариф_полок[Тип полки], Тариф_полок[Коэф-нт цены], 1)),"") | L32: =IFERROR((Sales[[#This Row],[Базовая цена, руб]]-Sales[[#This Row],[Сумма скидки льготникам, руб]])-Sales[[#This Row],[Сумма скидки тип-места, руб2]],"") | N32: =IF(ISBLANK(P32),"","Свободно") -> Свободно | O32: =IF(ISBLANK(P32),"",IF(P32>36, IF(MOD(P32,2)=0, "Верхнее боковое место", "Нижнее боковое место"), IF(MOD(P32,2)=0, "Верхнее место", "Нижнее место"))) -> Верхнее боковое место | P32: 48 | Q32: =IFERROR(VLOOKUP(P32,Аналитика!A33:AH86,34,0),"") -> Частично
A33: =IF(ISBLANK(Sales[[#This Row],[Место]]),"",CONCATENATE("T-00"&ROW()-1)) | E33: =IFERROR(_xlfn.XLOOKUP(Sales[[#This Row],[Станция ОТ]],Справочник_станций_и_сборов[Станция (остановка)],Справочник_станций_и_сборов[ID]),"") | F33: =IFERROR(_xlfn.XLOOKUP(Sales[[#This Row],[Станция ДО]],Справочник_станций_и_сборов[Станция (остановка)],Справочник_станций_и_сборов[ID]),"") | H33: =IF(ISBLANK(Sales[[#This Row],[Место]]),"",IF(Sales[[#This Row],[Место]]>36, IF(MOD(Sales[[#This Row],[Место]],2)=0, "Верхнее боковое место", "Нижнее боковое место"), IF(MOD(Sales[[#This Row],[Место]],2)=0, "Верхнее место", "Нижнее место"))) | I33: =IFERROR(((_xlfn.XLOOKUP(Sales[[#This Row],[Станция ДО]],Справочник_станций_и_сборов[Станция (остановка)],Справочник_станций_и_сборов[Расстояние от Мск (км)],)-_xlfn.XLOOKUP(Sales[[#This Row],[Станция ОТ]],Справочник_станций_и_сборов[Станция (остановка)],Справочник_станций_и_сборов[Расстояние от Мск (км)],))*Справочник!$Q$3+Справочник!$Q$2),"") | J33: =IFERROR(Sales[[#This Row],[Базовая цена, руб]] * _xlfn.XLOOKUP(Sales[[#This Row],[Тип пассажира]],Тип_пассажира[Наименование],Тип_пассажира[Цена]), "") | K33: =IFERROR(Sales[[#This Row],[Базовая цена, руб]] * VALUE(_xlfn.XLOOKUP(Sales[[#This Row],[Тип полки]], Тариф_полок[Тип полки], Тариф_полок[Коэф-нт цены], 1)),"") | L33: =IFERROR((Sales[[#This Row],[Базовая цена, руб]]-Sales[[#This Row],[Сумма скидки льготникам, руб]])-Sales[[#This Row],[Сумма скидки тип-места, руб2]],"") | N33: =IF(ISBLANK(P33),"","Свободно") -> Свободно | O33: =IF(ISBLANK(P33),"",IF(P33>36, IF(MOD(P33,2)=0, "Верхнее боковое место", "Нижнее боковое место"), IF(MOD(P33,2)=0, "Верхнее место", "Нижнее место"))) -> Нижнее боковое место | P33: 49 | Q33: =IFERROR(VLOOKUP(P33,Аналитика!A34:AH87,34,0),"") -> Частично
A34: =IF(ISBLANK(Sales[[#This Row],[Место]]),"",CONCATENATE("T-00"&ROW()-1)) | E34: =IFERROR(_xlfn.XLOOKUP(Sales[[#This Row],[Станция ОТ]],Справочник_станций_и_сборов[Станция (остановка)],Справочник_станций_и_сборов[ID]),"") | F34: =IFERROR(_xlfn.XLOOKUP(Sales[[#This Row],[Станция ДО]],Справочник_станций_и_сборов[Станция (остановка)],Справочник_станций_и_сборов[ID]),"") | H34: =IF(ISBLANK(Sales[[#This Row],[Место]]),"",IF(Sales[[#This Row],[Место]]>36, IF(MOD(Sales[[#This Row],[Место]],2)=0, "Верхнее боковое место", "Нижнее боковое место"), IF(MOD(Sales[[#This Row],[Место]],2)=0, "Верхнее место", "Нижнее место"))) | I34: =IFERROR(((_xlfn.XLOOKUP(Sales[[#This Row],[Станция ДО]],Справочник_станций_и_сборов[Станция (остановка)],Справочник_станций_и_сборов[Расстояние от Мск (км)],)-_xlfn.XLOOKUP(Sales[[#This Row],[Станция ОТ]],Справочник_станций_и_сборов[Станция (остановка)],Справочник_станций_и_сборов[Расстояние от Мск (км)],))*Справочник!$Q$3+Справочник!$Q$2),"") | J34: =IFERROR(Sales[[#This Row],[Базовая цена, руб]] * _xlfn.XLOOKUP(Sales[[#This Row],[Тип пассажира]],Тип_пассажира[Наименование],Тип_пассажира[Цена]), "") | K34: =IFERROR(Sales[[#This Row],[Базовая цена, руб]] * VALUE(_xlfn.XLOOKUP(Sales[[#This Row],[Тип полки]], Тариф_полок[Тип полки], Тариф_полок[Коэф-нт цены], 1)),"") | L34: =IFERROR((Sales[[#This Row],[Базовая цена, руб]]-Sales[[#This Row],[Сумма скидки льготникам, руб]])-Sales[[#This Row],[Сумма скидки тип-места, руб2]],"") | N34: =IF(ISBLANK(P34),"","Свободно") -> Свободно | O34: =IF(ISBLANK(P34),"",IF(P34>36, IF(MOD(P34,2)=0, "Верхнее боковое место", "Нижнее боковое место"), IF(MOD(P34,2)=0, "Верхнее место", "Нижнее место"))) -> Верхнее боковое место | P34: 50 | Q34: =IFERROR(VLOOKUP(P34,Аналитика!A35:AH88,34,0),"") -> Частично
A35: =IF(ISBLANK(Sales[[#This Row],[Место]]),"",CONCATENATE("T-00"&ROW()-1)) | E35: =IFERROR(_xlfn.XLOOKUP(Sales[[#This Row],[Станция ОТ]],Справочник_станций_и_сборов[Станция (остановка)],Справочник_станций_и_сборов[ID]),"") | F35: =IFERROR(_xlfn.XLOOKUP(Sales[[#This Row],[Станция ДО]],Справочник_станций_и_сборов[Станция (остановка)],Справочник_станций_и_сборов[ID]),"") | H35: =IF(ISBLANK(Sales[[#This Row],[Место]]),"",IF(Sales[[#This Row],[Место]]>36, IF(MOD(Sales[[#This Row],[Место]],2)=0, "Верхнее боковое место", "Нижнее боковое место"), IF(MOD(Sales[[#This Row],[Место]],2)=0, "Верхнее место", "Нижнее место"))) | I35: =IFERROR(((_xlfn.XLOOKUP(Sales[[#This Row],[Станция ДО]],Справочник_станций_и_сборов[Станция (остановка)],Справочник_станций_и_сборов[Расстояние от Мск (км)],)-_xlfn.XLOOKUP(Sales[[#This Row],[Станция ОТ]],Справочник_станций_и_сборов[Станция (остановка)],Справочник_станций_и_сборов[Расстояние от Мск (км)],))*Справочник!$Q$3+Справочник!$Q$2),"") | J35: =IFERROR(Sales[[#This Row],[Базовая цена, руб]] * _xlfn.XLOOKUP(Sales[[#This Row],[Тип пассажира]],Тип_пассажира[Наименование],Тип_пассажира[Цена]), "") | K35: =IFERROR(Sales[[#This Row],[Базовая цена, руб]] * VALUE(_xlfn.XLOOKUP(Sales[[#This Row],[Тип полки]], Тариф_полок[Тип полки], Тариф_полок[Коэф-нт цены], 1)),"") | L35: =IFERROR((Sales[[#This Row],[Базовая цена, руб]]-Sales[[#This Row],[Сумма скидки льготникам, руб]])-Sales[[#This Row],[Сумма скидки тип-места, руб2]],"") | N35: =IF(ISBLANK(P35),"","Свободно") -> Свободно | O35: =IF(ISBLANK(P35),"",IF(P35>36, IF(MOD(P35,2)=0, "Верхнее боковое место", "Нижнее боковое место"), IF(MOD(P35,2)=0, "Верхнее место", "Нижнее место"))) -> Нижнее боковое место | P35: 51 | Q35: =IFERROR(VLOOKUP(P35,Аналитика!A36:AH89,34,0),"") -> Частично
A36: =IF(ISBLANK(Sales[[#This Row],[Место]]),"",CONCATENATE("T-00"&ROW()-1)) | E36: =IFERROR(_xlfn.XLOOKUP(Sales[[#This Row],[Станция ОТ]],Справочник_станций_и_сборов[Станция (остановка)],Справочник_станций_и_сборов[ID]),"") | F36: =IFERROR(_xlfn.XLOOKUP(Sales[[#This Row],[Станция ДО]],Справочник_станций_и_сборов[Станция (остановка)],Справочник_станций_и_сборов[ID]),"") | H36: =IF(ISBLANK(Sales[[#This Row],[Место]]),"",IF(Sales[[#This Row],[Место]]>36, IF(MOD(Sales[[#This Row],[Место]],2)=0, "Верхнее боковое место", "Нижнее боковое место"), IF(MOD(Sales[[#This Row],[Место]],2)=0, "Верхнее место", "Нижнее место"))) | I36: =IFERROR(((_xlfn.XLOOKUP(Sales[[#This Row],[Станция ДО]],Справочник_станций_и_сборов[Станция (остановка)],Справочник_станций_и_сборов[Расстояние от Мск (км)],)-_xlfn.XLOOKUP(Sales[[#This Row],[Станция ОТ]],Справочник_станций_и_сборов[Станция (остановка)],Справочник_станций_и_сборов[Расстояние от Мск (км)],))*Справочник!$Q$3+Справочник!$Q$2),"") | J36: =IFERROR(Sales[[#This Row],[Базовая цена, руб]] * _xlfn.XLOOKUP(Sales[[#This Row],[Тип пассажира]],Тип_пассажира[Наименование],Тип_пассажира[Цена]), "") | K36: =IFERROR(Sales[[#This Row],[Базовая цена, руб]] * VALUE(_xlfn.XLOOKUP(Sales[[#This Row],[Тип полки]], Тариф_полок[Тип полки], Тариф_полок[Коэф-нт цены], 1)),"") | L36: =IFERROR((Sales[[#This Row],[Базовая цена, руб]]-Sales[[#This Row],[Сумма скидки льготникам, руб]])-Sales[[#This Row],[Сумма скидки тип-места, руб2]],"") | N36: =IF(ISBLANK(P36),"","Свободно") -> Свободно | O36: =IF(ISBLANK(P36),"",IF(P36>36, IF(MOD(P36,2)=0, "Верхнее боковое место", "Нижнее боковое место"), IF(MOD(P36,2)=0, "Верхнее место", "Нижнее место"))) -> Верхнее боковое место | P36: 52 | Q36: =IFERROR(VLOOKUP(P36,Аналитика!A37:AH90,34,0),"") -> Частично
A37: =IF(ISBLANK(Sales[[#This Row],[Место]]),"",CONCATENATE("T-00"&ROW()-1)) | E37: =IFERROR(_xlfn.XLOOKUP(Sales[[#This Row],[Станция ОТ]],Справочник_станций_и_сборов[Станция (остановка)],Справочник_станций_и_сборов[ID]),"") | F37: =IFERROR(_xlfn.XLOOKUP(Sales[[#This Row],[Станция ДО]],Справочник_станций_и_сборов[Станция (остановка)],Справочник_станций_и_сборов[ID]),"") | H37: =IF(ISBLANK(Sales[[#This Row],[Место]]),"",IF(Sales[[#This Row],[Место]]>36, IF(MOD(Sales[[#This Row],[Место]],2)=0, "Верхнее боковое место", "Нижнее боковое место"), IF(MOD(Sales[[#This Row],[Место]],2)=0, "Верхнее место", "Нижнее место"))) | I37: =IFERROR(((_xlfn.XLOOKUP(Sales[[#This Row],[Станция ДО]],Справочник_станций_и_сборов[Станция (остановка)],Справочник_станций_и_сборов[Расстояние от Мск (км)],)-_xlfn.XLOOKUP(Sales[[#This Row],[Станция ОТ]],Справочник_станций_и_сборов[Станция (остановка)],Справочник_станций_и_сборов[Расстояние от Мск (км)],))*Справочник!$Q$3+Справочник!$Q$2),"") | J37: =IFERROR(Sales[[#This Row],[Базовая цена, руб]] * _xlfn.XLOOKUP(Sales[[#This Row],[Тип пассажира]],Тип_пассажира[Наименование],Тип_пассажира[Цена]), "") | K37: =IFERROR(Sales[[#This Row],[Базовая цена, руб]] * VALUE(_xlfn.XLOOKUP(Sales[[#This Row],[Тип полки]], Тариф_полок[Тип полки], Тариф_полок[Коэф-нт цены], 1)),"") | L37: =IFERROR((Sales[[#This Row],[Базовая цена, руб]]-Sales[[#This Row],[Сумма скидки льготникам, руб]])-Sales[[#This Row],[Сумма скидки тип-места, руб2]],"") | N37: =IF(ISBLANK(P37),"","Свободно") -> Свободно | O37: =IF(ISBLANK(P37),"",IF(P37>36, IF(MOD(P37,2)=0, "Верхнее боковое место", "Нижнее боковое место"), IF(MOD(P37,2)=0, "Верхнее место", "Нижнее место"))) -> Нижнее боковое место | P37: 53 | Q37: =IFERROR(VLOOKUP(P37,Аналитика!A38:AH91,34,0),"") -> Частично
A38: =IF(ISBLANK(Sales[[#This Row],[Место]]),"",CONCATENATE("T-00"&ROW()-1)) | E38: =IFERROR(_xlfn.XLOOKUP(Sales[[#This Row],[Станция ОТ]],Справочник_станций_и_сборов[Станция (остановка)],Справочник_станций_и_сборов[ID]),"") | F38: =IFERROR(_xlfn.XLOOKUP(Sales[[#This Row],[Станция ДО]],Справочник_станций_и_сборов[Станция (остановка)],Справочник_станций_и_сборов[ID]),"") | H38: =IF(ISBLANK(Sales[[#This Row],[Место]]),"",IF(Sales[[#This Row],[Место]]>36, IF(MOD(Sales[[#This Row],[Место]],2)=0, "Верхнее боковое место", "Нижнее боковое место"), IF(MOD(Sales[[#This Row],[Место]],2)=0, "Верхнее место", "Нижнее место"))) | I38: =IFERROR(((_xlfn.XLOOKUP(Sales[[#This Row],[Станция ДО]],Справочник_станций_и_сборов[Станция (остановка)],Справочник_станций_и_сборов[Расстояние от Мск (км)],)-_xlfn.XLOOKUP(Sales[[#This Row],[Станция ОТ]],Справочник_станций_и_сборов[Станция (остановка)],Справочник_станций_и_сборов[Расстояние от Мск (км)],))*Справочник!$Q$3+Справочник!$Q$2),"") | J38: =IFERROR(Sales[[#This Row],[Базовая цена, руб]] * _xlfn.XLOOKUP(Sales[[#This Row],[Тип пассажира]],Тип_пассажира[Наименование],Тип_пассажира[Цена]), "") | K38: =IFERROR(Sales[[#This Row],[Базовая цена, руб]] * VALUE(_xlfn.XLOOKUP(Sales[[#This Row],[Тип полки]], Тариф_полок[Тип полки], Тариф_полок[Коэф-нт цены], 1)),"") | L38: =IFERROR((Sales[[#This Row],[Базовая цена, руб]]-Sales[[#This Row],[Сумма скидки льготникам, руб]])-Sales[[#This Row],[Сумма скидки тип-места, руб2]],"") | N38: =IF(ISBLANK(P38),"","Свободно") -> Свободно | O38: =IF(ISBLANK(P38),"",IF(P38>36, IF(MOD(P38,2)=0, "Верхнее боковое место", "Нижнее боковое место"), IF(MOD(P38,2)=0, "Верхнее место", "Нижнее место"))) -> Верхнее боковое место | P38: 54 | Q38: =IFERROR(VLOOKUP(P38,Аналитика!A39:AH92,34,0),"") -> Частично
A39: =IF(ISBLANK(Sales[[#This Row],[Место]]),"",CONCATENATE("T-00"&ROW()-1)) | E39: =IFERROR(_xlfn.XLOOKUP(Sales[[#This Row],[Станция ОТ]],Справочник_станций_и_сборов[Станция (остановка)],Справочник_станций_и_сборов[ID]),"") | F39: =IFERROR(_xlfn.XLOOKUP(Sales[[#This Row],[Станция ДО]],Справочник_станций_и_сборов[Станция (остановка)],Справочник_станций_и_сборов[ID]),"") | H39: =IF(ISBLANK(Sales[[#This Row],[Место]]),"",IF(Sales[[#This Row],[Место]]>36, IF(MOD(Sales[[#This Row],[Место]],2)=0, "Верхнее боковое место", "Нижнее боковое место"), IF(MOD(Sales[[#This Row],[Место]],2)=0, "Верхнее место", "Нижнее место"))) | I39: =IFERROR(((_xlfn.XLOOKUP(Sales[[#This Row],[Станция ДО]],Справочник_станций_и_сборов[Станция (остановка)],Справочник_станций_и_сборов[Расстояние от Мск (км)],)-_xlfn.XLOOKUP(Sales[[#This Row],[Станция ОТ]],Справочник_станций_и_сборов[Станция (остановка)],Справочник_станций_и_сборов[Расстояние от Мск (км)],))*Справочник!$Q$3+Справочник!$Q$2),"") | J39: =IFERROR(Sales[[#This Row],[Базовая цена, руб]] * _xlfn.XLOOKUP(Sales[[#This Row],[Тип пассажира]],Тип_пассажира[Наименование],Тип_пассажира[Цена]), "") | K39: =IFERROR(Sales[[#This Row],[Базовая цена, руб]] * VALUE(_xlfn.XLOOKUP(Sales[[#This Row],[Тип полки]], Тариф_полок[Тип полки], Тариф_полок[Коэф-нт цены], 1)),"") | L39: =IFERROR((Sales[[#This Row],[Базовая цена, руб]]-Sales[[#This Row],[Сумма скидки льготникам, руб]])-Sales[[#This Row],[Сумма скидки тип-места, руб2]],"") | N39: =IF(ISBLANK(P39),"","Свободно") | O39: =IF(ISBLANK(P39),"",IF(P39>36, IF(MOD(P39,2)=0, "Верхнее боковое место", "Нижнее боковое место"), IF(MOD(P39,2)=0, "Верхнее место", "Нижнее место"))) | Q39: =IFERROR(VLOOKUP(P39,Аналитика!A40:AH93,34,0),"")
A40: =IF(ISBLANK(Sales[[#This Row],[Место]]),"",CONCATENATE("T-00"&ROW()-1)) | E40: =IFERROR(_xlfn.XLOOKUP(Sales[[#This Row],[Станция ОТ]],Справочник_станций_и_сборов[Станция (остановка)],Справочник_станций_и_сборов[ID]),"") | F40: =IFERROR(_xlfn.XLOOKUP(Sales[[#This Row],[Станция ДО]],Справочник_станций_и_сборов[Станция (остановка)],Справочник_станций_и_сборов[ID]),"") | H40: =IF(ISBLANK(Sales[[#This Row],[Место]]),"",IF(Sales[[#This Row],[Место]]>36, IF(MOD(Sales[[#This Row],[Место]],2)=0, "Верхнее боковое место", "Нижнее боковое место"), IF(MOD(Sales[[#This Row],[Место]],2)=0, "Верхнее место", "Нижнее место"))) | I40: =IFERROR(((_xlfn.XLOOKUP(Sales[[#This Row],[Станция ДО]],Справочник_станций_и_сборов[Станция (остановка)],Справочник_станций_и_сборов[Расстояние от Мск (км)],)-_xlfn.XLOOKUP(Sales[[#This Row],[Станция ОТ]],Справочник_станций_и_сборов[Станция (остановка)],Справочник_станций_и_сборов[Расстояние от Мск (км)],))*Справочник!$Q$3+Справочник!$Q$2),"") | J40: =IFERROR(Sales[[#This Row],[Базовая цена, руб]] * _xlfn.XLOOKUP(Sales[[#This Row],[Тип пассажира]],Тип_пассажира[Наименование],Тип_пассажира[Цена]), "") | K40: =IFERROR(Sales[[#This Row],[Базовая цена, руб]] * VALUE(_xlfn.XLOOKUP(Sales[[#This Row],[Тип полки]], Тариф_полок[Тип полки], Тариф_полок[Коэф-нт цены], 1)),"") | L40: =IFERROR((Sales[[#This Row],[Базовая цена, руб]]-Sales[[#This Row],[Сумма скидки льготникам, руб]])-Sales[[#This Row],[Сумма скидки тип-места, руб2]],"") | N40: =IF(ISBLANK(P40),"","Свободно") | O40: =IF(ISBLANK(P40),"",IF(P40>36, IF(MOD(P40,2)=0, "Верхнее боковое место", "Нижнее боковое место"), IF(MOD(P40,2)=0, "Верхнее место", "Нижнее место"))) | Q40: =IFERROR(VLOOKUP(P40,Аналитика!A41:AH94,34,0),"")
A41: =IF(ISBLANK(Sales[[#This Row],[Место]]),"",CONCATENATE("T-00"&ROW()-1)) | E41: =IFERROR(_xlfn.XLOOKUP(Sales[[#This Row],[Станция ОТ]],Справочник_станций_и_сборов[Станция (остановка)],Справочник_станций_и_сборов[ID]),"") | F41: =IFERROR(_xlfn.XLOOKUP(Sales[[#This Row],[Станция ДО]],Справочник_станций_и_сборов[Станция (остановка)],Справочник_станций_и_сборов[ID]),"") | H41: =IF(ISBLANK(Sales[[#This Row],[Место]]),"",IF(Sales[[#This Row],[Место]]>36, IF(MOD(Sales[[#This Row],[Место]],2)=0, "Верхнее боковое место", "Нижнее боковое место"), IF(MOD(Sales[[#This Row],[Место]],2)=0, "Верхнее место", "Нижнее место"))) | I41: =IFERROR(((_xlfn.XLOOKUP(Sales[[#This Row],[Станция ДО]],Справочник_станций_и_сборов[Станция (остановка)],Справочник_станций_и_сборов[Расстояние от Мск (км)],)-_xlfn.XLOOKUP(Sales[[#This Row],[Станция ОТ]],Справочник_станций_и_сборов[Станция (остановка)],Справочник_станций_и_сборов[Расстояние от Мск (км)],))*Справочник!$Q$3+Справочник!$Q$2),"") | J41: =IFERROR(Sales[[#This Row],[Базовая цена, руб]] * _xlfn.XLOOKUP(Sales[[#This Row],[Тип пассажира]],Тип_пассажира[Наименование],Тип_пассажира[Цена]), "") | K41: =IFERROR(Sales[[#This Row],[Базовая цена, руб]] * VALUE(_xlfn.XLOOKUP(Sales[[#This Row],[Тип полки]], Тариф_полок[Тип полки], Тариф_полок[Коэф-нт цены], 1)),"") | L41: =IFERROR((Sales[[#This Row],[Базовая цена, руб]]-Sales[[#This Row],[Сумма скидки льготникам, руб]])-Sales[[#This Row],[Сумма скидки тип-места, руб2]],"") | N41: =IF(ISBLANK(P41),"","Свободно") | O41: =IF(ISBLANK(P41),"",IF(P41>36, IF(MOD(P41,2)=0, "Верхнее боковое место", "Нижнее боковое место"), IF(MOD(P41,2)=0, "Верхнее место", "Нижнее место"))) | Q41: =IFERROR(VLOOKUP(P41,Аналитика!A42:AH95,34,0),"")
A42: =IF(ISBLANK(Sales[[#This Row],[Место]]),"",CONCATENATE("T-00"&ROW()-1)) | E42: =IFERROR(_xlfn.XLOOKUP(Sales[[#This Row],[Станция ОТ]],Справочник_станций_и_сборов[Станция (остановка)],Справочник_станций_и_сборов[ID]),"") | F42: =IFERROR(_xlfn.XLOOKUP(Sales[[#This Row],[Станция ДО]],Справочник_станций_и_сборов[Станция (остановка)],Справочник_станций_и_сборов[ID]),"") | H42: =IF(ISBLANK(Sales[[#This Row],[Место]]),"",IF(Sales[[#This Row],[Место]]>36, IF(MOD(Sales[[#This Row],[Место]],2)=0, "Верхнее боковое место", "Нижнее боковое место"), IF(MOD(Sales[[#This Row],[Место]],2)=0, "Верхнее место", "Нижнее место"))) | I42: =IFERROR(((_xlfn.XLOOKUP(Sales[[#This Row],[Станция ДО]],Справочник_станций_и_сборов[Станция (остановка)],Справочник_станций_и_сборов[Расстояние от Мск (км)],)-_xlfn.XLOOKUP(Sales[[#This Row],[Станция ОТ]],Справочник_станций_и_сборов[Станция (остановка)],Справочник_станций_и_сборов[Расстояние от Мск (км)],))*Справочник!$Q$3+Справочник!$Q$2),"") | J42: =IFERROR(Sales[[#This Row],[Базовая цена, руб]] * _xlfn.XLOOKUP(Sales[[#This Row],[Тип пассажира]],Тип_пассажира[Наименование],Тип_пассажира[Цена]), "") | K42: =IFERROR(Sales[[#This Row],[Базовая цена, руб]] * VALUE(_xlfn.XLOOKUP(Sales[[#This Row],[Тип полки]], Тариф_полок[Тип полки], Тариф_полок[Коэф-нт цены], 1)),"") | L42: =IFERROR((Sales[[#This Row],[Базовая цена, руб]]-Sales[[#This Row],[Сумма скидки льготникам, руб]])-Sales[[#This Row],[Сумма скидки тип-места, руб2]],"") | N42: =IF(ISBLANK(P42),"","Свободно") | O42: =IF(ISBLANK(P42),"",IF(P42>36, IF(MOD(P42,2)=0, "Верхнее боковое место", "Нижнее боковое место"), IF(MOD(P42,2)=0, "Верхнее место", "Нижнее место"))) | Q42: =IFERROR(VLOOKUP(P42,Аналитика!A43:AH96,34,0),"")
A43: =IF(ISBLANK(Sales[[#This Row],[Место]]),"",CONCATENATE("T-00"&ROW()-1)) | E43: =IFERROR(_xlfn.XLOOKUP(Sales[[#This Row],[Станция ОТ]],Справочник_станций_и_сборов[Станция (остановка)],Справочник_станций_и_сборов[ID]),"") | F43: =IFERROR(_xlfn.XLOOKUP(Sales[[#This Row],[Станция ДО]],Справочник_станций_и_сборов[Станция (остановка)],Справочник_станций_и_сборов[ID]),"") | H43: =IF(ISBLANK(Sales[[#This Row],[Место]]),"",IF(Sales[[#This Row],[Место]]>36, IF(MOD(Sales[[#This Row],[Место]],2)=0, "Верхнее боковое место", "Нижнее боковое место"), IF(MOD(Sales[[#This Row],[Место]],2)=0, "Верхнее место", "Нижнее место"))) | I43: =IFERROR(((_xlfn.XLOOKUP(Sales[[#This Row],[Станция ДО]],Справочник_станций_и_сборов[Станция (остановка)],Справочник_станций_и_сборов[Расстояние от Мск (км)],)-_xlfn.XLOOKUP(Sales[[#This Row],[Станция ОТ]],Справочник_станций_и_сборов[Станция (остановка)],Справочник_станций_и_сборов[Расстояние от Мск (км)],))*Справочник!$Q$3+Справочник!$Q$2),"") | J43: =IFERROR(Sales[[#This Row],[Базовая цена, руб]] * _xlfn.XLOOKUP(Sales[[#This Row],[Тип пассажира]],Тип_пассажира[Наименование],Тип_пассажира[Цена]), "") | K43: =IFERROR(Sales[[#This Row],[Базовая цена, руб]] * VALUE(_xlfn.XLOOKUP(Sales[[#This Row],[Тип полки]], Тариф_полок[Тип полки], Тариф_полок[Коэф-нт цены], 1)),"") | L43: =IFERROR((Sales[[#This Row],[Базовая цена, руб]]-Sales[[#This Row],[Сумма скидки льготникам, руб]])-Sales[[#This Row],[Сумма скидки тип-места, руб2]],"") | N43: =IF(ISBLANK(P43),"","Свободно") | O43: =IF(ISBLANK(P43),"",IF(P43>36, IF(MOD(P43,2)=0, "Верхнее боковое место", "Нижнее боковое место"), IF(MOD(P43,2)=0, "Верхнее место", "Нижнее место"))) | Q43: =IFERROR(VLOOKUP(P43,Аналитика!A44:AH97,34,0),"")
A44: =IF(ISBLANK(Sales[[#This Row],[Место]]),"",CONCATENATE("T-00"&ROW()-1)) | E44: =IFERROR(_xlfn.XLOOKUP(Sales[[#This Row],[Станция ОТ]],Справочник_станций_и_сборов[Станция (остановка)],Справочник_станций_и_сборов[ID]),"") | F44: =IFERROR(_xlfn.XLOOKUP(Sales[[#This Row],[Станция ДО]],Справочник_станций_и_сборов[Станция (остановка)],Справочник_станций_и_сборов[ID]),"") | H44: =IF(ISBLANK(Sales[[#This Row],[Место]]),"",IF(Sales[[#This Row],[Место]]>36, IF(MOD(Sales[[#This Row],[Место]],2)=0, "Верхнее боковое место", "Нижнее боковое место"), IF(MOD(Sales[[#This Row],[Место]],2)=0, "Верхнее место", "Нижнее место"))) | I44: =IFERROR(((_xlfn.XLOOKUP(Sales[[#This Row],[Станция ДО]],Справочник_станций_и_сборов[Станция (остановка)],Справочник_станций_и_сборов[Расстояние от Мск (км)],)-_xlfn.XLOOKUP(Sales[[#This Row],[Станция ОТ]],Справочник_станций_и_сборов[Станция (остановка)],Справочник_станций_и_сборов[Расстояние от Мск (км)],))*Справочник!$Q$3+Справочник!$Q$2),"") | J44: =IFERROR(Sales[[#This Row],[Базовая цена, руб]] * _xlfn.XLOOKUP(Sales[[#This Row],[Тип пассажира]],Тип_пассажира[Наименование],Тип_пассажира[Цена]), "") | K44: =IFERROR(Sales[[#This Row],[Базовая цена, руб]] * VALUE(_xlfn.XLOOKUP(Sales[[#This Row],[Тип полки]], Тариф_полок[Тип полки], Тариф_полок[Коэф-нт цены], 1)),"") | L44: =IFERROR((Sales[[#This Row],[Базовая цена, руб]]-Sales[[#This Row],[Сумма скидки льготникам, руб]])-Sales[[#This Row],[Сумма скидки тип-места, руб2]],"")
A45: =IF(ISBLANK(Sales[[#This Row],[Место]]),"",CONCATENATE("T-00"&ROW()-1)) | E45: =IFERROR(_xlfn.XLOOKUP(Sales[[#This Row],[Станция ОТ]],Справочник_станций_и_сборов[Станция (остановка)],Справочник_станций_и_сборов[ID]),"") | F45: =IFERROR(_xlfn.XLOOKUP(Sales[[#This Row],[Станция ДО]],Справочник_станций_и_сборов[Станция (остановка)],Справочник_станций_и_сборов[ID]),"") | H45: =IF(ISBLANK(Sales[[#This Row],[Место]]),"",IF(Sales[[#This Row],[Место]]>36, IF(MOD(Sales[[#This Row],[Место]],2)=0, "Верхнее боковое место", "Нижнее боковое место"), IF(MOD(Sales[[#This Row],[Место]],2)=0, "Верхнее место", "Нижнее место"))) | I45: =IFERROR(((_xlfn.XLOOKUP(Sales[[#This Row],[Станция ДО]],Справочник_станций_и_сборов[Станция (остановка)],Справочник_станций_и_сборов[Расстояние от Мск (км)],)-_xlfn.XLOOKUP(Sales[[#This Row],[Станция ОТ]],Справочник_станций_и_сборов[Станция (остановка)],Справочник_станций_и_сборов[Расстояние от Мск (км)],))*Справочник!$Q$3+Справочник!$Q$2),"") | J45: =IFERROR(Sales[[#This Row],[Базовая цена, руб]] * _xlfn.XLOOKUP(Sales[[#This Row],[Тип пассажира]],Тип_пассажира[Наименование],Тип_пассажира[Цена]), "") | K45: =IFERROR(Sales[[#This Row],[Базовая цена, руб]] * VALUE(_xlfn.XLOOKUP(Sales[[#This Row],[Тип полки]], Тариф_полок[Тип полки], Тариф_полок[Коэф-нт цены], 1)),"") | L45: =IFERROR((Sales[[#This Row],[Базовая цена, руб]]-Sales[[#This Row],[Сумма скидки льготникам, руб]])-Sales[[#This Row],[Сумма скидки тип-места, руб2]],"")
A46: =IF(ISBLANK(Sales[[#This Row],[Место]]),"",CONCATENATE("T-00"&ROW()-1)) | E46: =IFERROR(_xlfn.XLOOKUP(Sales[[#This Row],[Станция ОТ]],Справочник_станций_и_сборов[Станция (остановка)],Справочник_станций_и_сборов[ID]),"") | F46: =IFERROR(_xlfn.XLOOKUP(Sales[[#This Row],[Станция ДО]],Справочник_станций_и_сборов[Станция (остановка)],Справочник_станций_и_сборов[ID]),"") | H46: =IF(ISBLANK(Sales[[#This Row],[Место]]),"",IF(Sales[[#This Row],[Место]]>36, IF(MOD(Sales[[#This Row],[Место]],2)=0, "Верхнее боковое место", "Нижнее боковое место"), IF(MOD(Sales[[#This Row],[Место]],2)=0, "Верхнее место", "Нижнее место"))) | I46: =IFERROR(((_xlfn.XLOOKUP(Sales[[#This Row],[Станция ДО]],Справочник_станций_и_сборов[Станция (остановка)],Справочник_станций_и_сборов[Расстояние от Мск (км)],)-_xlfn.XLOOKUP(Sales[[#This Row],[Станция ОТ]],Справочник_станций_и_сборов[Станция (остановка)],Справочник_станций_и_сборов[Расстояние от Мск (км)],))*Справочник!$Q$3+Справочник!$Q$2),"") | J46: =IFERROR(Sales[[#This Row],[Базовая цена, руб]] * _xlfn.XLOOKUP(Sales[[#This Row],[Тип пассажира]],Тип_пассажира[Наименование],Тип_пассажира[Цена]), "") | K46: =IFERROR(Sales[[#This Row],[Базовая цена, руб]] * VALUE(_xlfn.XLOOKUP(Sales[[#This Row],[Тип полки]], Тариф_полок[Тип полки], Тариф_полок[Коэф-нт цены], 1)),"") | L46: =IFERROR((Sales[[#This Row],[Базовая цена, руб]]-Sales[[#This Row],[Сумма скидки льготникам, руб]])-Sales[[#This Row],[Сумма скидки тип-места, руб2]],"")
A47: =IF(ISBLANK(Sales[[#This Row],[Место]]),"",CONCATENATE("T-00"&ROW()-1)) | E47: =IFERROR(_xlfn.XLOOKUP(Sales[[#This Row],[Станция ОТ]],Справочник_станций_и_сборов[Станция (остановка)],Справочник_станций_и_сборов[ID]),"") | F47: =IFERROR(_xlfn.XLOOKUP(Sales[[#This Row],[Станция ДО]],Справочник_станций_и_сборов[Станция (остановка)],Справочник_станций_и_сборов[ID]),"") | H47: =IF(ISBLANK(Sales[[#This Row],[Место]]),"",IF(Sales[[#This Row],[Место]]>36, IF(MOD(Sales[[#This Row],[Место]],2)=0, "Верхнее боковое место", "Нижнее боковое место"), IF(MOD(Sales[[#This Row],[Место]],2)=0, "Верхнее место", "Нижнее место"))) | I47: =IFERROR(((_xlfn.XLOOKUP(Sales[[#This Row],[Станция ДО]],Справочник_станций_и_сборов[Станция (остановка)],Справочник_станций_и_сборов[Расстояние от Мск (км)],)-_xlfn.XLOOKUP(Sales[[#This Row],[Станция ОТ]],Справочник_станций_и_сборов[Станция (остановка)],Справочник_станций_и_сборов[Расстояние от Мск (км)],))*Справочник!$Q$3+Справочник!$Q$2),"") | J47: =IFERROR(Sales[[#This Row],[Базовая цена, руб]] * _xlfn.XLOOKUP(Sales[[#This Row],[Тип пассажира]],Тип_пассажира[Наименование],Тип_пассажира[Цена]), "") | K47: =IFERROR(Sales[[#This Row],[Базовая цена, руб]] * VALUE(_xlfn.XLOOKUP(Sales[[#This Row],[Тип полки]], Тариф_полок[Тип полки], Тариф_полок[Коэф-нт цены], 1)),"") | L47: =IFERROR((Sales[[#This Row],[Базовая цена, руб]]-Sales[[#This Row],[Сумма скидки льготникам, руб]])-Sales[[#This Row],[Сумма скидки тип-места, руб2]],"")
A48: =IF(ISBLANK(Sales[[#This Row],[Место]]),"",CONCATENATE("T-00"&ROW()-1)) | E48: =IFERROR(_xlfn.XLOOKUP(Sales[[#This Row],[Станция ОТ]],Справочник_станций_и_сборов[Станция (остановка)],Справочник_станций_и_сборов[ID]),"") | F48: =IFERROR(_xlfn.XLOOKUP(Sales[[#This Row],[Станция ДО]],Справочник_станций_и_сборов[Станция (остановка)],Справочник_станций_и_сборов[ID]),"") | H48: =IF(ISBLANK(Sales[[#This Row],[Место]]),"",IF(Sales[[#This Row],[Место]]>36, IF(MOD(Sales[[#This Row],[Место]],2)=0, "Верхнее боковое место", "Нижнее боковое место"), IF(MOD(Sales[[#This Row],[Место]],2)=0, "Верхнее место", "Нижнее место"))) | I48: =IFERROR(((_xlfn.XLOOKUP(Sales[[#This Row],[Станция ДО]],Справочник_станций_и_сборов[Станция (остановка)],Справочник_станций_и_сборов[Расстояние от Мск (км)],)-_xlfn.XLOOKUP(Sales[[#This Row],[Станция ОТ]],Справочник_станций_и_сборов[Станция (остановка)],Справочник_станций_и_сборов[Расстояние от Мск (км)],))*Справочник!$Q$3+Справочник!$Q$2),"") | J48: =IFERROR(Sales[[#This Row],[Базовая цена, руб]] * _xlfn.XLOOKUP(Sales[[#This Row],[Тип пассажира]],Тип_пассажира[Наименование],Тип_пассажира[Цена]), "") | K48: =IFERROR(Sales[[#This Row],[Базовая цена, руб]] * VALUE(_xlfn.XLOOKUP(Sales[[#This Row],[Тип полки]], Тариф_полок[Тип полки], Тариф_полок[Коэф-нт цены], 1)),"") | L48: =IFERROR((Sales[[#This Row],[Базовая цена, руб]]-Sales[[#This Row],[Сумма скидки льготникам, руб]])-Sales[[#This Row],[Сумма скидки тип-места, руб2]],"")
A49: =IF(ISBLANK(Sales[[#This Row],[Место]]),"",CONCATENATE("T-00"&ROW()-1)) | E49: =IFERROR(_xlfn.XLOOKUP(Sales[[#This Row],[Станция ОТ]],Справочник_станций_и_сборов[Станция (остановка)],Справочник_станций_и_сборов[ID]),"") | F49: =IFERROR(_xlfn.XLOOKUP(Sales[[#This Row],[Станция ДО]],Справочник_станций_и_сборов[Станция (остановка)],Справочник_станций_и_сборов[ID]),"") | H49: =IF(ISBLANK(Sales[[#This Row],[Место]]),"",IF(Sales[[#This Row],[Место]]>36, IF(MOD(Sales[[#This Row],[Место]],2)=0, "Верхнее боковое место", "Нижнее боковое место"), IF(MOD(Sales[[#This Row],[Место]],2)=0, "Верхнее место", "Нижнее место"))) | I49: =IFERROR(((_xlfn.XLOOKUP(Sales[[#This Row],[Станция ДО]],Справочник_станций_и_сборов[Станция (остановка)],Справочник_станций_и_сборов[Расстояние от Мск (км)],)-_xlfn.XLOOKUP(Sales[[#This Row],[Станция ОТ]],Справочник_станций_и_сборов[Станция (остановка)],Справочник_станций_и_сборов[Расстояние от Мск (км)],))*Справочник!$Q$3+Справочник!$Q$2),"") | J49: =IFERROR(Sales[[#This Row],[Базовая цена, руб]] * _xlfn.XLOOKUP(Sales[[#This Row],[Тип пассажира]],Тип_пассажира[Наименование],Тип_пассажира[Цена]), "") | K49: =IFERROR(Sales[[#This Row],[Базовая цена, руб]] * VALUE(_xlfn.XLOOKUP(Sales[[#This Row],[Тип полки]], Тариф_полок[Тип полки], Тариф_полок[Коэф-нт цены], 1)),"") | L49: =IFERROR((Sales[[#This Row],[Базовая цена, руб]]-Sales[[#This Row],[Сумма скидки льготникам, руб]])-Sales[[#This Row],[Сумма скидки тип-места, руб2]],"")
A50: =IF(ISBLANK(Sales[[#This Row],[Место]]),"",CONCATENATE("T-00"&ROW()-1)) | E50: =IFERROR(_xlfn.XLOOKUP(Sales[[#This Row],[Станция ОТ]],Справочник_станций_и_сборов[Станция (остановка)],Справочник_станций_и_сборов[ID]),"") | F50: =IFERROR(_xlfn.XLOOKUP(Sales[[#This Row],[Станция ДО]],Справочник_станций_и_сборов[Станция (остановка)],Справочник_станций_и_сборов[ID]),"") | H50: =IF(ISBLANK(Sales[[#This Row],[Место]]),"",IF(Sales[[#This Row],[Место]]>36, IF(MOD(Sales[[#This Row],[Место]],2)=0, "Верхнее боковое место", "Нижнее боковое место"), IF(MOD(Sales[[#This Row],[Место]],2)=0, "Верхнее место", "Нижнее место"))) | I50: =IFERROR(((_xlfn.XLOOKUP(Sales[[#This Row],[Станция ДО]],Справочник_станций_и_сборов[Станция (остановка)],Справочник_станций_и_сборов[Расстояние от Мск (км)],)-_xlfn.XLOOKUP(Sales[[#This Row],[Станция ОТ]],Справочник_станций_и_сборов[Станция (остановка)],Справочник_станций_и_сборов[Расстояние от Мск (км)],))*Справочник!$Q$3+Справочник!$Q$2),"") | J50: =IFERROR(Sales[[#This Row],[Базовая цена, руб]] * _xlfn.XLOOKUP(Sales[[#This Row],[Тип пассажира]],Тип_пассажира[Наименование],Тип_пассажира[Цена]), "") | K50: =IFERROR(Sales[[#This Row],[Базовая цена, руб]] * VALUE(_xlfn.XLOOKUP(Sales[[#This Row],[Тип полки]], Тариф_полок[Тип полки], Тариф_полок[Коэф-нт цены], 1)),"") | L50: =IFERROR((Sales[[#This Row],[Базовая цена, руб]]-Sales[[#This Row],[Сумма скидки льготникам, руб]])-Sales[[#This Row],[Сумма скидки тип-места, руб2]],"")
A51: =IF(ISBLANK(Sales[[#This Row],[Место]]),"",CONCATENATE("T-00"&ROW()-1)) | E51: =IFERROR(_xlfn.XLOOKUP(Sales[[#This Row],[Станция ОТ]],Справочник_станций_и_сборов[Станция (остановка)],Справочник_станций_и_сборов[ID]),"") | F51: =IFERROR(_xlfn.XLOOKUP(Sales[[#This Row],[Станция ДО]],Справочник_станций_и_сборов[Станция (остановка)],Справочник_станций_и_сборов[ID]),"") | H51: =IF(ISBLANK(Sales[[#This Row],[Место]]),"",IF(Sales[[#This Row],[Место]]>36, IF(MOD(Sales[[#This Row],[Место]],2)=0, "Верхнее боковое место", "Нижнее боковое место"), IF(MOD(Sales[[#This Row],[Место]],2)=0, "Верхнее место", "Нижнее место"))) | I51: =IFERROR(((_xlfn.XLOOKUP(Sales[[#This Row],[Станция ДО]],Справочник_станций_и_сборов[Станция (остановка)],Справочник_станций_и_сборов[Расстояние от Мск (км)],)-_xlfn.XLOOKUP(Sales[[#This Row],[Станция ОТ]],Справочник_станций_и_сборов[Станция (остановка)],Справочник_станций_и_сборов[Расстояние от Мск (км)],))*Справочник!$Q$3+Справочник!$Q$2),"") | J51: =IFERROR(Sales[[#This Row],[Базовая цена, руб]] * _xlfn.XLOOKUP(Sales[[#This Row],[Тип пассажира]],Тип_пассажира[Наименование],Тип_пассажира[Цена]), "") | K51: =IFERROR(Sales[[#This Row],[Базовая цена, руб]] * VALUE(_xlfn.XLOOKUP(Sales[[#This Row],[Тип полки]], Тариф_полок[Тип полки], Тариф_полок[Коэф-нт цены], 1)),"") | L51: =IFERROR((Sales[[#This Row],[Базовая цена, руб]]-Sales[[#This Row],[Сумма скидки льготникам, руб]])-Sales[[#This Row],[Сумма скидки тип-места, руб2]],"")
A52: =IF(ISBLANK(Sales[[#This Row],[Место]]),"",CONCATENATE("T-00"&ROW()-1)) | E52: =IFERROR(_xlfn.XLOOKUP(Sales[[#This Row],[Станция ОТ]],Справочник_станций_и_сборов[Станция (остановка)],Справочник_станций_и_сборов[ID]),"") | F52: =IFERROR(_xlfn.XLOOKUP(Sales[[#This Row],[Станция ДО]],Справочник_станций_и_сборов[Станция (остановка)],Справочник_станций_и_сборов[ID]),"") | H52: =IF(ISBLANK(Sales[[#This Row],[Место]]),"",IF(Sales[[#This Row],[Место]]>36, IF(MOD(Sales[[#This Row],[Место]],2)=0, "Верхнее боковое место", "Нижнее боковое место"), IF(MOD(Sales[[#This Row],[Место]],2)=0, "Верхнее место", "Нижнее место"))) | I52: =IFERROR(((_xlfn.XLOOKUP(Sales[[#This Row],[Станция ДО]],Справочник_станций_и_сборов[Станция (остановка)],Справочник_станций_и_сборов[Расстояние от Мск (км)],)-_xlfn.XLOOKUP(Sales[[#This Row],[Станция ОТ]],Справочник_станций_и_сборов[Станция (остановка)],Справочник_станций_и_сборов[Расстояние от Мск (км)],))*Справочник!$Q$3+Справочник!$Q$2),"") | J52: =IFERROR(Sales[[#This Row],[Базовая цена, руб]] * _xlfn.XLOOKUP(Sales[[#This Row],[Тип пассажира]],Тип_пассажира[Наименование],Тип_пассажира[Цена]), "") | K52: =IFERROR(Sales[[#This Row],[Базовая цена, руб]] * VALUE(_xlfn.XLOOKUP(Sales[[#This Row],[Тип полки]], Тариф_полок[Тип полки], Тариф_полок[Коэф-нт цены], 1)),"") | L52: =IFERROR((Sales[[#This Row],[Базовая цена, руб]]-Sales[[#This Row],[Сумма скидки льготникам, руб]])-Sales[[#This Row],[Сумма скидки тип-места, руб2]],"")
A53: =IF(ISBLANK(Sales[[#This Row],[Место]]),"",CONCATENATE("T-00"&ROW()-1)) | E53: =IFERROR(_xlfn.XLOOKUP(Sales[[#This Row],[Станция ОТ]],Справочник_станций_и_сборов[Станция (остановка)],Справочник_станций_и_сборов[ID]),"") | F53: =IFERROR(_xlfn.XLOOKUP(Sales[[#This Row],[Станция ДО]],Справочник_станций_и_сборов[Станция (остановка)],Справочник_станций_и_сборов[ID]),"") | H53: =IF(ISBLANK(Sales[[#This Row],[Место]]),"",IF(Sales[[#This Row],[Место]]>36, IF(MOD(Sales[[#This Row],[Место]],2)=0, "Верхнее боковое место", "Нижнее боковое место"), IF(MOD(Sales[[#This Row],[Место]],2)=0, "Верхнее место", "Нижнее место"))) | I53: =IFERROR(((_xlfn.XLOOKUP(Sales[[#This Row],[Станция ДО]],Справочник_станций_и_сборов[Станция (остановка)],Справочник_станций_и_сборов[Расстояние от Мск (км)],)-_xlfn.XLOOKUP(Sales[[#This Row],[Станция ОТ]],Справочник_станций_и_сборов[Станция (остановка)],Справочник_станций_и_сборов[Расстояние от Мск (км)],))*Справочник!$Q$3+Справочник!$Q$2),"") | J53: =IFERROR(Sales[[#This Row],[Базовая цена, руб]] * _xlfn.XLOOKUP(Sales[[#This Row],[Тип пассажира]],Тип_пассажира[Наименование],Тип_пассажира[Цена]), "") | K53: =IFERROR(Sales[[#This Row],[Базовая цена, руб]] * VALUE(_xlfn.XLOOKUP(Sales[[#This Row],[Тип полки]], Тариф_полок[Тип полки], Тариф_полок[Коэф-нт цены], 1)),"") | L53: =IFERROR((Sales[[#This Row],[Базовая цена, руб]]-Sales[[#This Row],[Сумма скидки льготникам, руб]])-Sales[[#This Row],[Сумма скидки тип-места, руб2]],"")
A54: =IF(ISBLANK(Sales[[#This Row],[Место]]),"",CONCATENATE("T-00"&ROW()-1)) | E54: =IFERROR(_xlfn.XLOOKUP(Sales[[#This Row],[Станция ОТ]],Справочник_станций_и_сборов[Станция (остановка)],Справочник_станций_и_сборов[ID]),"") | F54: =IFERROR(_xlfn.XLOOKUP(Sales[[#This Row],[Станция ДО]],Справочник_станций_и_сборов[Станция (остановка)],Справочник_станций_и_сборов[ID]),"") | H54: =IF(ISBLANK(Sales[[#This Row],[Место]]),"",IF(Sales[[#This Row],[Место]]>36, IF(MOD(Sales[[#This Row],[Место]],2)=0, "Верхнее боковое место", "Нижнее боковое место"), IF(MOD(Sales[[#This Row],[Место]],2)=0, "Верхнее место", "Нижнее место"))) | I54: =IFERROR(((_xlfn.XLOOKUP(Sales[[#This Row],[Станция ДО]],Справочник_станций_и_сборов[Станция (остановка)],Справочник_станций_и_сборов[Расстояние от Мск (км)],)-_xlfn.XLOOKUP(Sales[[#This Row],[Станция ОТ]],Справочник_станций_и_сборов[Станция (остановка)],Справочник_станций_и_сборов[Расстояние от Мск (км)],))*Справочник!$Q$3+Справочник!$Q$2),"") | J54: =IFERROR(Sales[[#This Row],[Базовая цена, руб]] * _xlfn.XLOOKUP(Sales[[#This Row],[Тип пассажира]],Тип_пассажира[Наименование],Тип_пассажира[Цена]), "") | K54: =IFERROR(Sales[[#This Row],[Базовая цена, руб]] * VALUE(_xlfn.XLOOKUP(Sales[[#This Row],[Тип полки]], Тариф_полок[Тип полки], Тариф_полок[Коэф-нт цены], 1)),"") | L54: =IFERROR((Sales[[#This Row],[Базовая цена, руб]]-Sales[[#This Row],[Сумма скидки льготникам, руб]])-Sales[[#This Row],[Сумма скидки тип-места, руб2]],"")
A55: =IF(ISBLANK(Sales[[#This Row],[Место]]),"",CONCATENATE("T-00"&ROW()-1)) | E55: =IFERROR(_xlfn.XLOOKUP(Sales[[#This Row],[Станция ОТ]],Справочник_станций_и_сборов[Станция (остановка)],Справочник_станций_и_сборов[ID]),"") | F55: =IFERROR(_xlfn.XLOOKUP(Sales[[#This Row],[Станция ДО]],Справочник_станций_и_сборов[Станция (остановка)],Справочник_станций_и_сборов[ID]),"") | H55: =IF(ISBLANK(Sales[[#This Row],[Место]]),"",IF(Sales[[#This Row],[Место]]>36, IF(MOD(Sales[[#This Row],[Место]],2)=0, "Верхнее боковое место", "Нижнее боковое место"), IF(MOD(Sales[[#This Row],[Место]],2)=0, "Верхнее место", "Нижнее место"))) | I55: =IFERROR(((_xlfn.XLOOKUP(Sales[[#This Row],[Станция ДО]],Справочник_станций_и_сборов[Станция (остановка)],Справочник_станций_и_сборов[Расстояние от Мск (км)],)-_xlfn.XLOOKUP(Sales[[#This Row],[Станция ОТ]],Справочник_станций_и_сборов[Станция (остановка)],Справочник_станций_и_сборов[Расстояние от Мск (км)],))*Справочник!$Q$3+Справочник!$Q$2),"") | J55: =IFERROR(Sales[[#This Row],[Базовая цена, руб]] * _xlfn.XLOOKUP(Sales[[#This Row],[Тип пассажира]],Тип_пассажира[Наименование],Тип_пассажира[Цена]), "") | K55: =IFERROR(Sales[[#This Row],[Базовая цена, руб]] * VALUE(_xlfn.XLOOKUP(Sales[[#This Row],[Тип полки]], Тариф_полок[Тип полки], Тариф_полок[Коэф-нт цены], 1)),"") | L55: =IFERROR((Sales[[#This Row],[Базовая цена, руб]]-Sales[[#This Row],[Сумма скидки льготникам, руб]])-Sales[[#This Row],[Сумма скидки тип-места, руб2]],"")
... A57: =IF(ISBLANK(Sales[[#This Row],[Место]]),"",CONCATENATE("T-00"&ROW()-1)) | E57: =IFERROR(_xlfn.XLOOKUP(Sales[[#This Row],[Станция ОТ]],Справочник_станций_и_сборов[Станция (остановка)],Справочник_станций_и_сборов[ID]),"") | F57: =IFERROR(_xlfn.XLOOKUP(Sales[[#This Row],[Станция ДО]],Справочник_станций_и_сборов[Станция (остановка)],Справочник_станций_и_сборов[ID]),"") | H57: =IF(ISBLANK(Sales[[#This Row],[Место]]),"",IF(Sales[[#This Row],[Место]]>36, IF(MOD(Sales[[#This Row],[Место]],2)=0, "Верхнее боковое место", "Нижнее боковое место"), IF(MOD(Sales[[#This Row],[Место]],2)=0, "Верхнее место", "Нижнее место"))) | I57: =IFERROR(((_xlfn.XLOOKUP(Sales[[#This Row],[Станция ДО]],Справочник_станций_и_сборов[Станция (остановка)],Справочник_станций_и_сборов[Расстояние от Мск (км)],)-_xlfn.XLOOKUP(Sales[[#This Row],[Станция ОТ]],Справочник_станций_и_сборов[Станция (остановка)],Справочник_станций_и_сборов[Расстояние от Мск (км)],))*Справочник!$Q$3+Справочник!$Q$2),"") | J57: =IFERROR(Sales[[#This Row],[Базовая цена, руб]] * _xlfn.XLOOKUP(Sales[[#This Row],[Тип пассажира]],Тип_пассажира[Наименование],Тип_пассажира[Цена]), "") | K57: =IFERROR(Sales[[#This Row],[Базовая цена, руб]] * VALUE(_xlfn.XLOOKUP(Sales[[#This Row],[Тип полки]], Тариф_полок[Тип полки], Тариф_полок[Коэф-нт цены], 1)),"") | L57: =IFERROR((Sales[[#This Row],[Базовая цена, руб]]-Sales[[#This Row],[Сумма скидки льготникам, руб]])-Sales[[#This Row],[Сумма скидки тип-места, руб2]],"")
A58: Итог | B58: =SUBTOTAL(103,Sales[Место]) -> 27 | L58: =SUBTOTAL(109,Sales[Цена, ₽]) -> 68437.75

Sheet Аналитика
B1: Москва (Казанский) | C1: Рязань 2 | D1: Ряжск 1 | E1: Мичуринск-Вор. | F1: Грязи-Воронежские | G1: Воронеж 1 | H1: Лиски | I1: Пухово | J1: Евдаково | K1: Сагуны | L1: Подгорное | M1: Россошь | N1: Райновская | O1: Кантемировка | P1: Чертково | Q1: Миллерово | R1: Тарасовка | S1: Глубокая | T1: Каменская | U1: Лихая | V1: Замчалово | W1: Зверево | X1: Сулин | Y1: Шахтная | Z1: Каменоломни | AA1: Персиановка | AB1: Хотунок | AC1: Новочеркасск | AD1: Александровка | AE1: Ростов-Главный | AF1: Свободны места | AG1: {=_xlfn.TEXTJOIN(", ", TRUE, IF(AF3:AF56="Свободно", A2:A55, ""))} -> 14, 15, 16, 18, 19, 20, 21, 22, 23, 24, 25, 26, 27, 28, 29, 30, 31, 33, 34, 35, 36, 37, 39, 40, 41, 42, 43, 44, 45, 46, 47, 48, 49, 50, 51, 52, 53
B2: 1 | C2: 2 | D2: 3 | E2: 4 | F2: 5 | G2: 6 | H2: 7 | I2: 8 | J2: 9 | K2: 10 | L2: 11 | M2: 12 | N2: 13 | O2: 14 | P2: 15 | Q2: 16 | R2: 17 | S2: 18 | T2: 19 | U2: 20 | V2: 21 | W2: 22 | X2: 23 | Y2: 24 | Z2: 25 | AA2: 26 | AB2: 27 | AC2: 28 | AD2: 29 | AG2: ID купе
A3: 1 | B3: =COUNTIFS(Продажи!$B$2:$B$1002, $A3, Продажи!$E$2:$E$1002, "<=" & B$2, Продажи!$F$2:$F$1002, ">" & B$2) -> 1 | C3: =COUNTIFS(Продажи!$B$2:$B$1002, $A3, Продажи!$E$2:$E$1002, "<=" & C$2, Продажи!$F$2:$F$1002, ">" & C$2) -> 1 | D3: =COUNTIFS(Продажи!$B$2:$B$1002, $A3, Продажи!$E$2:$E$1002, "<=" & D$2, Продажи!$F$2:$F$1002, ">" & D$2) -> 1 | E3: =COUNTIFS(Продажи!$B$2:$B$1002, $A3, Продажи!$E$2:$E$1002, "<=" & E$2, Продажи!$F$2:$F$1002, ">" & E$2) -> 1 | F3: =COUNTIFS(Продажи!$B$2:$B$1002, $A3, Продажи!$E$2:$E$1002, "<=" & F$2, Продажи!$F$2:$F$1002, ">" & F$2) -> 1 | G3: =COUNTIFS(Продажи!$B$2:$B$1002, $A3, Продажи!$E$2:$E$1002, "<=" & G$2, Продажи!$F$2:$F$1002, ">" & G$2) -> 1 | H3: =COUNTIFS(Продажи!$B$2:$B$1002, $A3, Продажи!$E$2:$E$1002, "<=" & H$2, Продажи!$F$2:$F$1002, ">" & H$2) -> 1 | I3: =COUNTIFS(Продажи!$B$2:$B$1002, $A3, Продажи!$E$2:$E$1002, "<=" & I$2, Продажи!$F$2:$F$1002, ">" & I$2) -> 1 | ... AD3: =COUNTIFS(Продажи!$B$2:$B$1002, $A3, Продажи!$E$2:$E$1002, "<=" & AD$2, Продажи!$F$2:$F$1002, ">" & AD$2) -> 1 | AE3: =SUM(B3:AD3) -> 29 | AF3: =IF(SUM(OFFSET($B3, 0, VLOOKUP("Станция отправления",Продажи!$R$2:$T$31,3,0)-1, 1, VLOOKUP("Станция прибытия",Продажи!$R$2:$T$31,3,0)-VLOOKUP("Станция отправления",Продажи!$R$2:$T$31,3,0)))=0, "Свободно", "Мест нет") -> Мест нет | AG3: =VLOOKUP(A3,ID_купе[],2,0) -> 1 | AH3: =IF(AF3="Мест нет", "Занято", IF(COUNTIFS($AG$3:$AG$56, AG3, $AF$3:$AF$56, "Свободно") = COUNTIF($AG$3:$AG$56, AG3), "Целое купе/отсек", "Частично")) -> Занято
A4: 2 | B4: =COUNTIFS(Продажи!$B$2:$B$1002, $A4, Продажи!$E$2:$E$1002, "<=" & B$2, Продажи!$F$2:$F$1002, ">" & B$2) -> 1 | C4: =COUNTIFS(Продажи!$B$2:$B$1002, $A4, Продажи!$E$2:$E$1002, "<=" & C$2, Продажи!$F$2:$F$1002, ">" & C$2) -> 1 | D4: =COUNTIFS(Продажи!$B$2:$B$1002, $A4, Продажи!$E$2:$E$1002, "<=" & D$2, Продажи!$F$2:$F$1002, ">" & D$2) -> 1 | E4: =COUNTIFS(Продажи!$B$2:$B$1002, $A4, Продажи!$E$2:$E$1002, "<=" & E$2, Продажи!$F$2:$F$1002, ">" & E$2) -> 1 | F4: =COUNTIFS(Продажи!$B$2:$B$1002, $A4, Продажи!$E$2:$E$1002, "<=" & F$2, Продажи!$F$2:$F$1002, ">" & F$2) -> 1 | G4: =COUNTIFS(Продажи!$B$2:$B$1002, $A4, Продажи!$E$2:$E$1002, "<=" & G$2, Продажи!$F$2:$F$1002, ">" & G$2) -> 1 | H4: =COUNTIFS(Продажи!$B$2:$B$1002, $A4, Продажи!$E$2:$E$1002, "<=" & H$2, Продажи!$F$2:$F$1002, ">" & H$2) -> 1 | I4: =COUNTIFS(Продажи!$B$2:$B$1002, $A4, Продажи!$E$2:$E$1002, "<=" & I$2, Продажи!$F$2:$F$1002, ">" & I$2) -> 1 | ... AD4: =COUNTIFS(Продажи!$B$2:$B$1002, $A4, Продажи!$E$2:$E$1002, "<=" & AD$2, Продажи!$F$2:$F$1002, ">" & AD$2) -> 1 | AE4: =SUM(B4:AD4) -> 29 | AF4: =IF(SUM(OFFSET($B4, 0, VLOOKUP("Станция отправления",Продажи!$R$2:$T$31,3,0)-1, 1, VLOOKUP("Станция прибытия",Продажи!$R$2:$T$31,3,0)-VLOOKUP("Станция отправления",Продажи!$R$2:$T$31,3,0)))=0, "Свободно", "Мест нет") -> Мест нет | AG4: =VLOOKUP(A4,ID_купе[],2,0) -> 1 | AH4: =IF(AF4="Мест нет", "Занято", IF(COUNTIFS($AG$3:$AG$56, AG4, $AF$3:$AF$56, "Свободно") = COUNTIF($AG$3:$AG$56, AG4), "Целое купе/отсек", "Частично")) -> Занято
A5: 3 | B5: =COUNTIFS(Продажи!$B$2:$B$1002, $A5, Продажи!$E$2:$E$1002, "<=" & B$2, Продажи!$F$2:$F$1002, ">" & B$2) -> 1 | C5: =COUNTIFS(Продажи!$B$2:$B$1002, $A5, Продажи!$E$2:$E$1002, "<=" & C$2, Продажи!$F$2:$F$1002, ">" & C$2) -> 1 | D5: =COUNTIFS(Продажи!$B$2:$B$1002, $A5, Продажи!$E$2:$E$1002, "<=" & D$2, Продажи!$F$2:$F$1002, ">" & D$2) -> 1 | E5: =COUNTIFS(Продажи!$B$2:$B$1002, $A5, Продажи!$E$2:$E$1002, "<=" & E$2, Продажи!$F$2:$F$1002, ">" & E$2) -> 1 | F5: =COUNTIFS(Продажи!$B$2:$B$1002, $A5, Продажи!$E$2:$E$1002, "<=" & F$2, Продажи!$F$2:$F$1002, ">" & F$2) -> 1 | G5: =COUNTIFS(Продажи!$B$2:$B$1002, $A5, Продажи!$E$2:$E$1002, "<=" & G$2, Продажи!$F$2:$F$1002, ">" & G$2) -> 1 | H5: =COUNTIFS(Продажи!$B$2:$B$1002, $A5, Продажи!$E$2:$E$1002, "<=" & H$2, Продажи!$F$2:$F$1002, ">" & H$2) -> 1 | I5: =COUNTIFS(Продажи!$B$2:$B$1002, $A5, Продажи!$E$2:$E$1002, "<=" & I$2, Продажи!$F$2:$F$1002, ">" & I$2) -> 1 | ... AD5: =COUNTIFS(Продажи!$B$2:$B$1002, $A5, Продажи!$E$2:$E$1002, "<=" & AD$2, Продажи!$F$2:$F$1002, ">" & AD$2) -> 1 | AE5: =SUM(B5:AD5) -> 29 | AF5: =IF(SUM(OFFSET($B5, 0, VLOOKUP("Станция отправления",Продажи!$R$2:$T$31,3,0)-1, 1, VLOOKUP("Станция прибытия",Продажи!$R$2:$T$31,3,0)-VLOOKUP("Станция отправления",Продажи!$R$2:$T$31,3,0)))=0, "Свободно", "Мест нет") -> Мест нет | AG5: =VLOOKUP(A5,ID_купе[],2,0) -> 1 | AH5: =IF(AF5="Мест нет", "Занято", IF(COUNTIFS($AG$3:$AG$56, AG5, $AF$3:$AF$56, "Свободно") = COUNTIF($AG$3:$AG$56, AG5), "Целое купе/отсек", "Частично")) -> Занято
A6: 4 | B6: =COUNTIFS(Продажи!$B$2:$B$1002, $A6, Продажи!$E$2:$E$1002, "<=" & B$2, Продажи!$F$2:$F$1002, ">" & B$2) -> 0 | C6: =COUNTIFS(Продажи!$B$2:$B$1002, $A6, Продажи!$E$2:$E$1002, "<=" & C$2, Продажи!$F$2:$F$1002, ">" & C$2) -> 1 | D6: =COUNTIFS(Продажи!$B$2:$B$1002, $A6, Продажи!$E$2:$E$1002, "<=" & D$2, Продажи!$F$2:$F$1002, ">" & D$2) -> 1 | E6: =COUNTIFS(Продажи!$B$2:$B$1002, $A6, Продажи!$E$2:$E$1002, "<=" & E$2, Продажи!$F$2:$F$1002, ">" & E$2) -> 1 | F6: =COUNTIFS(Продажи!$B$2:$B$1002, $A6, Продажи!$E$2:$E$1002, "<=" & F$2, Продажи!$F$2:$F$1002, ">" & F$2) -> 1 | G6: =COUNTIFS(Продажи!$B$2:$B$1002, $A6, Продажи!$E$2:$E$1002, "<=" & G$2, Продажи!$F$2:$F$1002, ">" & G$2) -> 1 | H6: =COUNTIFS(Продажи!$B$2:$B$1002, $A6, Продажи!$E$2:$E$1002, "<=" & H$2, Продажи!$F$2:$F$1002, ">" & H$2) -> 1 | I6: =COUNTIFS(Продажи!$B$2:$B$1002, $A6, Продажи!$E$2:$E$1002, "<=" & I$2, Продажи!$F$2:$F$1002, ">" & I$2) -> 1 | ... AD6: =COUNTIFS(Продажи!$B$2:$B$1002, $A6, Продажи!$E$2:$E$1002, "<=" & AD$2, Продажи!$F$2:$F$1002, ">" & AD$2) -> 1 | AE6: =SUM(B6:AD6) -> 28 | AF6: =IF(SUM(OFFSET($B6, 0, VLOOKUP("Станция отправления",Продажи!$R$2:$T$31,3,0)-1, 1, VLOOKUP("Станция прибытия",Продажи!$R$2:$T$31,3,0)-VLOOKUP("Станция отправления",Продажи!$R$2:$T$31,3,0)))=0, "Свободно", "Мест нет") -> Мест нет | AG6: =VLOOKUP(A6,ID_купе[],2,0) -> 1 | AH6: =IF(AF6="Мест нет", "Занято", IF(COUNTIFS($AG$3:$AG$56, AG6, $AF$3:$AF$56, "Свободно") = COUNTIF($AG$3:$AG$56, AG6), "Целое купе/отсек", "Частично")) -> Занято
A7: 5 | B7: =COUNTIFS(Продажи!$B$2:$B$1002, $A7, Продажи!$E$2:$E$1002, "<=" & B$2, Продажи!$F$2:$F$1002, ">" & B$2) -> 0 | C7: =COUNTIFS(Продажи!$B$2:$B$1002, $A7, Продажи!$E$2:$E$1002, "<=" & C$2, Продажи!$F$2:$F$1002, ">" & C$2) -> 0 | D7: =COUNTIFS(Продажи!$B$2:$B$1002, $A7, Продажи!$E$2:$E$1002, "<=" & D$2, Продажи!$F$2:$F$1002, ">" & D$2) -> 0 | E7: =COUNTIFS(Продажи!$B$2:$B$1002, $A7, Продажи!$E$2:$E$1002, "<=" & E$2, Продажи!$F$2:$F$1002, ">" & E$2) -> 1 | F7: =COUNTIFS(Продажи!$B$2:$B$1002, $A7, Продажи!$E$2:$E$1002, "<=" & F$2, Продажи!$F$2:$F$1002, ">" & F$2) -> 1 | G7: =COUNTIFS(Продажи!$B$2:$B$1002, $A7, Продажи!$E$2:$E$1002, "<=" & G$2, Продажи!$F$2:$F$1002, ">" & G$2) -> 1 | H7: =COUNTIFS(Продажи!$B$2:$B$1002, $A7, Продажи!$E$2:$E$1002, "<=" & H$2, Продажи!$F$2:$F$1002, ">" & H$2) -> 1 | I7: =COUNTIFS(Продажи!$B$2:$B$1002, $A7, Продажи!$E$2:$E$1002, "<=" & I$2, Продажи!$F$2:$F$1002, ">" & I$2) -> 1 | ... AD7: =COUNTIFS(Продажи!$B$2:$B$1002, $A7, Продажи!$E$2:$E$1002, "<=" & AD$2, Продажи!$F$2:$F$1002, ">" & AD$2) -> 1 | AE7: =SUM(B7:AD7) -> 26 | AF7: =IF(SUM(OFFSET($B7, 0, VLOOKUP("Станция отправления",Продажи!$R$2:$T$31,3,0)-1, 1, VLOOKUP("Станция прибытия",Продажи!$R$2:$T$31,3,0)-VLOOKUP("Станция отправления",Продажи!$R$2:$T$31,3,0)))=0, "Свободно", "Мест нет") -> Мест нет | AG7: =VLOOKUP(A7,ID_купе[],2,0) -> 2 | AH7: =IF(AF7="Мест нет", "Занято", IF(COUNTIFS($AG$3:$AG$56, AG7, $AF$3:$AF$56, "Свободно") = COUNTIF($AG$3:$AG$56, AG7), "Целое купе/отсек", "Частично")) -> Занято
A8: 6 | B8: =COUNTIFS(Продажи!$B$2:$B$1002, $A8, Продажи!$E$2:$E$1002, "<=" & B$2, Продажи!$F$2:$F$1002, ">" & B$2) -> 1 | C8: =COUNTIFS(Продажи!$B$2:$B$1002, $A8, Продажи!$E$2:$E$1002, "<=" & C$2, Продажи!$F$2:$F$1002, ">" & C$2) -> 1 | D8: =COUNTIFS(Продажи!$B$2:$B$1002, $A8, Продажи!$E$2:$E$1002, "<=" & D$2, Продажи!$F$2:$F$1002, ">" & D$2) -> 1 | E8: =COUNTIFS(Продажи!$B$2:$B$1002, $A8, Продажи!$E$2:$E$1002, "<=" & E$2, Продажи!$F$2:$F$1002, ">" & E$2) -> 1 | F8: =COUNTIFS(Продажи!$B$2:$B$1002, $A8, Продажи!$E$2:$E$1002, "<=" & F$2, Продажи!$F$2:$F$1002, ">" & F$2) -> 1 | G8: =COUNTIFS(Продажи!$B$2:$B$1002, $A8, Продажи!$E$2:$E$1002, "<=" & G$2, Продажи!$F$2:$F$1002, ">" & G$2) -> 1 | H8: =COUNTIFS(Продажи!$B$2:$B$1002, $A8, Продажи!$E$2:$E$1002, "<=" & H$2, Продажи!$F$2:$F$1002, ">" & H$2) -> 1 | I8: =COUNTIFS(Продажи!$B$2:$B$1002, $A8, Продажи!$E$2:$E$1002, "<=" & I$2, Продажи!$F$2:$F$1002, ">" & I$2) -> 1 | ... AD8: =COUNTIFS(Продажи!$B$2:$B$1002, $A8, Продажи!$E$2:$E$1002, "<=" & AD$2, Продажи!$F$2:$F$1002, ">" & AD$2) -> 0 | AE8: =SUM(B8:AD8) -> 17 | AF8: =IF(SUM(OFFSET($B8, 0, VLOOKUP("Станция отправления",Продажи!$R$2:$T$31,3,0)-1, 1, VLOOKUP("Станция прибытия",Продажи!$R$2:$T$31,3,0)-VLOOKUP("Станция отправления",Продажи!$R$2:$T$31,3,0)))=0, "Свободно", "Мест нет") -> Мест нет | AG8: =VLOOKUP(A8,ID_купе[],2,0) -> 2 | AH8: =IF(AF8="Мест нет", "Занято", IF(COUNTIFS($AG$3:$AG$56, AG8, $AF$3:$AF$56, "Свободно") = COUNTIF($AG$3:$AG$56, AG8), "Целое купе/отсек", "Частично")) -> Занято
A9: 7 | B9: =COUNTIFS(Продажи!$B$2:$B$1002, $A9, Продажи!$E$2:$E$1002, "<=" & B$2, Продажи!$F$2:$F$1002, ">" & B$2) -> 1 | C9: =COUNTIFS(Продажи!$B$2:$B$1002, $A9, Продажи!$E$2:$E$1002, "<=" & C$2, Продажи!$F$2:$F$1002, ">" & C$2) -> 1 | D9: =COUNTIFS(Продажи!$B$2:$B$1002, $A9, Продажи!$E$2:$E$1002, "<=" & D$2, Продажи!$F$2:$F$1002, ">" & D$2) -> 1 | E9: =COUNTIFS(Продажи!$B$2:$B$1002, $A9, Продажи!$E$2:$E$1002, "<=" & E$2, Продажи!$F$2:$F$1002, ">" & E$2) -> 1 | F9: =COUNTIFS(Продажи!$B$2:$B$1002, $A9, Продажи!$E$2:$E$1002, "<=" & F$2, Продажи!$F$2:$F$1002, ">" & F$2) -> 1 | G9: =COUNTIFS(Продажи!$B$2:$B$1002, $A9, Продажи!$E$2:$E$1002, "<=" & G$2, Продажи!$F$2:$F$1002, ">" & G$2) -> 1 | H9: =COUNTIFS(Продажи!$B$2:$B$1002, $A9, Продажи!$E$2:$E$1002, "<=" & H$2, Продажи!$F$2:$F$1002, ">" & H$2) -> 1 | I9: =COUNTIFS(Продажи!$B$2:$B$1002, $A9, Продажи!$E$2:$E$1002, "<=" & I$2, Продажи!$F$2:$F$1002, ">" & I$2) -> 1 | ... AD9: =COUNTIFS(Продажи!$B$2:$B$1002, $A9, Продажи!$E$2:$E$1002, "<=" & AD$2, Продажи!$F$2:$F$1002, ">" & AD$2) -> 0 | AE9: =SUM(B9:AD9) -> 15 | AF9: =IF(SUM(OFFSET($B9, 0, VLOOKUP("Станция отправления",Продажи!$R$2:$T$31,3,0)-1, 1, VLOOKUP("Станция прибытия",Продажи!$R$2:$T$31,3,0)-VLOOKUP("Станция отправления",Продажи!$R$2:$T$31,3,0)))=0, "Свободно", "Мест нет") -> Мест нет | AG9: =VLOOKUP(A9,ID_купе[],2,0) -> 2 | AH9: =IF(AF9="Мест нет", "Занято", IF(COUNTIFS($AG$3:$AG$56, AG9, $AF$3:$AF$56, "Свободно") = COUNTIF($AG$3:$AG$56, AG9), "Целое купе/отсек", "Частично")) -> Занято
A10: 8 | B10: =COUNTIFS(Продажи!$B$2:$B$1002, $A10, Продажи!$E$2:$E$1002, "<=" & B$2, Продажи!$F$2:$F$1002, ">" & B$2) -> 1 | C10: =COUNTIFS(Продажи!$B$2:$B$1002, $A10, Продажи!$E$2:$E$1002, "<=" & C$2, Продажи!$F$2:$F$1002, ">" & C$2) -> 1 | D10: =COUNTIFS(Продажи!$B$2:$B$1002, $A10, Продажи!$E$2:$E$1002, "<=" & D$2, Продажи!$F$2:$F$1002, ">" & D$2) -> 1 | E10: =COUNTIFS(Продажи!$B$2:$B$1002, $A10, Продажи!$E$2:$E$1002, "<=" & E$2, Продажи!$F$2:$F$1002, ">" & E$2) -> 1 | F10: =COUNTIFS(Продажи!$B$2:$B$1002, $A10, Продажи!$E$2:$E$1002, "<=" & F$2, Продажи!$F$2:$F$1002, ">" & F$2) -> 1 | G10: =COUNTIFS(Продажи!$B$2:$B$1002, $A10, Продажи!$E$2:$E$1002, "<=" & G$2, Продажи!$F$2:$F$1002, ">" & G$2) -> 1 | H10: =COUNTIFS(Продажи!$B$2:$B$1002, $A10, Продажи!$E$2:$E$1002, "<=" & H$2, Продажи!$F$2:$F$1002, ">" & H$2) -> 0 | I10: =COUNTIFS(Продажи!$B$2:$B$1002, $A10, Продажи!$E$2:$E$1002, "<=" & I$2, Продажи!$F$2:$F$1002, ">" & I$2) -> 0 | ... AD10: =COUNTIFS(Продажи!$B$2:$B$1002, $A10, Продажи!$E$2:$E$1002, "<=" & AD$2, Продажи!$F$2:$F$1002, ">" & AD$2) -> 0 | AE10: =SUM(B10:AD10) -> 6 | AF10: =IF(SUM(OFFSET($B10, 0, VLOOKUP("Станция отправления",Продажи!$R$2:$T$31,3,0)-1, 1, VLOOKUP("Станция прибытия",Продажи!$R$2:$T$31,3,0)-VLOOKUP("Станция отправления",Продажи!$R$2:$T$31,3,0)))=0, "Свободно", "Мест нет") -> Мест нет | AG10: =VLOOKUP(A10,ID_купе[],2,0) -> 2 | AH10: =IF(AF10="Мест нет", "Занято", IF(COUNTIFS($AG$3:$AG$56, AG10, $AF$3:$AF$56, "Свободно") = COUNTIF($AG$3:$AG$56, AG10), "Целое купе/отсек", "Частично")) -> Занято
A11: 9 | B11: =COUNTIFS(Продажи!$B$2:$B$1002, $A11, Продажи!$E$2:$E$1002, "<=" & B$2, Продажи!$F$2:$F$1002, ">" & B$2) -> 1 | C11: =COUNTIFS(Продажи!$B$2:$B$1002, $A11, Продажи!$E$2:$E$1002, "<=" & C$2, Продажи!$F$2:$F$1002, ">" & C$2) -> 1 | D11: =COUNTIFS(Продажи!$B$2:$B$1002, $A11, Продажи!$E$2:$E$1002, "<=" & D$2, Продажи!$F$2:$F$1002, ">" & D$2) -> 1 | E11: =COUNTIFS(Продажи!$B$2:$B$1002, $A11, Продажи!$E$2:$E$1002, "<=" & E$2, Продажи!$F$2:$F$1002, ">" & E$2) -> 1 | F11: =COUNTIFS(Продажи!$B$2:$B$1002, $A11, Продажи!$E$2:$E$1002, "<=" & F$2, Продажи!$F$2:$F$1002, ">" & F$2) -> 1 | G11: =COUNTIFS(Продажи!$B$2:$B$1002, $A11, Продажи!$E$2:$E$1002, "<=" & G$2, Продажи!$F$2:$F$1002, ">" & G$2) -> 0 | H11: =COUNTIFS(Продажи!$B$2:$B$1002, $A11, Продажи!$E$2:$E$1002, "<=" & H$2, Продажи!$F$2:$F$1002, ">" & H$2) -> 0 | I11: =COUNTIFS(Продажи!$B$2:$B$1002, $A11, Продажи!$E$2:$E$1002, "<=" & I$2, Продажи!$F$2:$F$1002, ">" & I$2) -> 0 | ... AD11: =COUNTIFS(Продажи!$B$2:$B$1002, $A11, Продажи!$E$2:$E$1002, "<=" & AD$2, Продажи!$F$2:$F$1002, ">" & AD$2) -> 0 | AE11: =SUM(B11:AD11) -> 5 | AF11: =IF(SUM(OFFSET($B11, 0, VLOOKUP("Станция отправления",Продажи!$R$2:$T$31,3,0)-1, 1, VLOOKUP("Станция прибытия",Продажи!$R$2:$T$31,3,0)-VLOOKUP("Станция отправления",Продажи!$R$2:$T$31,3,0)))=0, "Свободно", "Мест нет") -> Мест нет | AG11: =VLOOKUP(A11,ID_купе[],2,0) -> 3 | AH11: =IF(AF11="Мест нет", "Занято", IF(COUNTIFS($AG$3:$AG$56, AG11, $AF$3:$AF$56, "Свободно") = COUNTIF($AG$3:$AG$56, AG11), "Целое купе/отсек", "Частично")) -> Занято
A12: 10 | B12: =COUNTIFS(Продажи!$B$2:$B$1002, $A12, Продажи!$E$2:$E$1002, "<=" & B$2, Продажи!$F$2:$F$1002, ">" & B$2) -> 1 | C12: =COUNTIFS(Продажи!$B$2:$B$1002, $A12, Продажи!$E$2:$E$1002, "<=" & C$2, Продажи!$F$2:$F$1002, ">" & C$2) -> 1 | D12: =COUNTIFS(Продажи!$B$2:$B$1002, $A12, Продажи!$E$2:$E$1002, "<=" & D$2, Продажи!$F$2:$F$1002, ">" & D$2) -> 1 | E12: =COUNTIFS(Продажи!$B$2:$B$1002, $A12, Продажи!$E$2:$E$1002, "<=" & E$2, Продажи!$F$2:$F$1002, ">" & E$2) -> 1 | F12: =COUNTIFS(Продажи!$B$2:$B$1002, $A12, Продажи!$E$2:$E$1002, "<=" & F$2, Продажи!$F$2:$F$1002, ">" & F$2) -> 1 | G12: =COUNTIFS(Продажи!$B$2:$B$1002, $A12, Продажи!$E$2:$E$1002, "<=" & G$2, Продажи!$F$2:$F$1002, ">" & G$2) -> 1 | H12: =COUNTIFS(Продажи!$B$2:$B$1002, $A12, Продажи!$E$2:$E$1002, "<=" & H$2, Продажи!$F$2:$F$1002, ">" & H$2) -> 1 | I12: =COUNTIFS(Продажи!$B$2:$B$1002, $A12, Продажи!$E$2:$E$1002, "<=" & I$2, Продажи!$F$2:$F$1002, ">" & I$2) -> 1 | ... AD12: =COUNTIFS(Продажи!$B$2:$B$1002, $A12, Продажи!$E$2:$E$1002, "<=" & AD$2, Продажи!$F$2:$F$1002, ">" & AD$2) -> 1 | AE12: =SUM(B12:AD12) -> 29 | AF12: =IF(SUM(OFFSET($B12, 0, VLOOKUP("Станция отправления",Продажи!$R$2:$T$31,3,0)-1, 1, VLOOKUP("Станция прибытия",Продажи!$R$2:$T$31,3,0)-VLOOKUP("Станция отправления",Продажи!$R$2:$T$31,3,0)))=0, "Свободно", "Мест нет") -> Мест нет | AG12: =VLOOKUP(A12,ID_купе[],2,0) -> 3 | AH12: =IF(AF12="Мест нет", "Занято", IF(COUNTIFS($AG$3:$AG$56, AG12, $AF$3:$AF$56, "Свободно") = COUNTIF($AG$3:$AG$56, AG12), "Целое купе/отсек", "Частично")) -> Занято
A13: 11 | B13: =COUNTIFS(Продажи!$B$2:$B$1002, $A13, Продажи!$E$2:$E$1002, "<=" & B$2, Продажи!$F$2:$F$1002, ">" & B$2) -> 1 | C13: =COUNTIFS(Продажи!$B$2:$B$1002, $A13, Продажи!$E$2:$E$1002, "<=" & C$2, Продажи!$F$2:$F$1002, ">" & C$2) -> 1 | D13: =COUNTIFS(Продажи!$B$2:$B$1002, $A13, Продажи!$E$2:$E$1002, "<=" & D$2, Продажи!$F$2:$F$1002, ">" & D$2) -> 1 | E13: =COUNTIFS(Продажи!$B$2:$B$1002, $A13, Продажи!$E$2:$E$1002, "<=" & E$2, Продажи!$F$2:$F$1002, ">" & E$2) -> 1 | F13: =COUNTIFS(Продажи!$B$2:$B$1002, $A13, Продажи!$E$2:$E$1002, "<=" & F$2, Продажи!$F$2:$F$1002, ">" & F$2) -> 1 | G13: =COUNTIFS(Продажи!$B$2:$B$1002, $A13, Продажи!$E$2:$E$1002, "<=" & G$2, Продажи!$F$2:$F$1002, ">" & G$2) -> 1 | H13: =COUNTIFS(Продажи!$B$2:$B$1002, $A13, Продажи!$E$2:$E$1002, "<=" & H$2, Продажи!$F$2:$F$1002, ">" & H$2) -> 1 | I13: =COUNTIFS(Продажи!$B$2:$B$1002, $A13, Продажи!$E$2:$E$1002, "<=" & I$2, Продажи!$F$2:$F$1002, ">" & I$2) -> 1 | ... AD13: =COUNTIFS(Продажи!$B$2:$B$1002, $A13, Продажи!$E$2:$E$1002, "<=" & AD$2, Продажи!$F$2:$F$1002, ">" & AD$2) -> 1 | AE13: =SUM(B13:AD13) -> 29 | AF13: =IF(SUM(OFFSET($B13, 0, VLOOKUP("Станция отправления",Продажи!$R$2:$T$31,3,0)-1, 1, VLOOKUP("Станция прибытия",Продажи!$R$2:$T$31,3,0)-VLOOKUP("Станция отправления",Продажи!$R$2:$T$31,3,0)))=0, "Свободно", "Мест нет") -> Мест нет | AG13: =VLOOKUP(A13,ID_купе[],2,0) -> 3 | AH13: =IF(AF13="Мест нет", "Занято", IF(COUNTIFS($AG$3:$AG$56, AG13, $AF$3:$AF$56, "Свободно") = COUNTIF($AG$3:$AG$56, AG13), "Целое купе/отсек", "Частично")) -> Занято
A14: 12 | B14: =COUNTIFS(Продажи!$B$2:$B$1002, $A14, Продажи!$E$2:$E$1002, "<=" & B$2, Продажи!$F$2:$F$1002, ">" & B$2) -> 1 | C14: =COUNTIFS(Продажи!$B$2:$B$1002, $A14, Продажи!$E$2:$E$1002, "<=" & C$2, Продажи!$F$2:$F$1002, ">" & C$2) -> 1 | D14: =COUNTIFS(Продажи!$B$2:$B$1002, $A14, Продажи!$E$2:$E$1002, "<=" & D$2, Продажи!$F$2:$F$1002, ">" & D$2) -> 1 | E14: =COUNTIFS(Продажи!$B$2:$B$1002, $A14, Продажи!$E$2:$E$1002, "<=" & E$2, Продажи!$F$2:$F$1002, ">" & E$2) -> 1 | F14: =COUNTIFS(Продажи!$B$2:$B$1002, $A14, Продажи!$E$2:$E$1002, "<=" & F$2, Продажи!$F$2:$F$1002, ">" & F$2) -> 1 | G14: =COUNTIFS(Продажи!$B$2:$B$1002, $A14, Продажи!$E$2:$E$1002, "<=" & G$2, Продажи!$F$2:$F$1002, ">" & G$2) -> 1 | H14: =COUNTIFS(Продажи!$B$2:$B$1002, $A14, Продажи!$E$2:$E$1002, "<=" & H$2, Продажи!$F$2:$F$1002, ">" & H$2) -> 1 | I14: =COUNTIFS(Продажи!$B$2:$B$1002, $A14, Продажи!$E$2:$E$1002, "<=" & I$2, Продажи!$F$2:$F$1002, ">" & I$2) -> 1 | ... AD14: =COUNTIFS(Продажи!$B$2:$B$1002, $A14, Продажи!$E$2:$E$1002, "<=" & AD$2, Продажи!$F$2:$F$1002, ">" & AD$2) -> 1 | AE14: =SUM(B14:AD14) -> 29 | AF14: =IF(SUM(OFFSET($B14, 0, VLOOKUP("Станция отправления",Продажи!$R$2:$T$31,3,0)-1, 1, VLOOKUP("Станция прибытия",Продажи!$R$2:$T$31,3,0)-VLOOKUP("Станция отправления",Продажи!$R$2:$T$31,3,0)))=0, "Свободно", "Мест нет") -> Мест нет | AG14: =VLOOKUP(A14,ID_купе[],2,0) -> 3 | AH14: =IF(AF14="Мест нет", "Занято", IF(COUNTIFS($AG$3:$AG$56, AG14, $AF$3:$AF$56, "Свободно") = COUNTIF($AG$3:$AG$56, AG14), "Целое купе/отсек", "Частично")) -> Занято
... A56: 54 | B56: =COUNTIFS(Продажи!$B$2:$B$1002, $A56, Продажи!$E$2:$E$1002, "<=" & B$2, Продажи!$F$2:$F$1002, ">" & B$2) -> 0 | C56: =COUNTIFS(Продажи!$B$2:$B$1002, $A56, Продажи!$E$2:$E$1002, "<=" & C$2, Продажи!$F$2:$F$1002, ">" & C$2) -> 0 | D56: =COUNTIFS(Продажи!$B$2:$B$1002, $A56, Продажи!$E$2:$E$1002, "<=" & D$2, Продажи!$F$2:$F$1002, ">" & D$2) -> 0 | E56: =COUNTIFS(Продажи!$B$2:$B$1002, $A56, Продажи!$E$2:$E$1002, "<=" & E$2, Продажи!$F$2:$F$1002, ">" & E$2) -> 0 | F56: =COUNTIFS(Продажи!$B$2:$B$1002, $A56, Продажи!$E$2:$E$1002, "<=" & F$2, Продажи!$F$2:$F$1002, ">" & F$2) -> 0 | G56: =COUNTIFS(Продажи!$B$2:$B$1002, $A56, Продажи!$E$2:$E$1002, "<=" & G$2, Продажи!$F$2:$F$1002, ">" & G$2) -> 0 | H56: =COUNTIFS(Продажи!$B$2:$B$1002, $A56, Продажи!$E$2:$E$1002, "<=" & H$2, Продажи!$F$2:$F$1002, ">" & H$2) -> 0 | I56: =COUNTIFS(Продажи!$B$2:$B$1002, $A56, Продажи!$E$2:$E$1002, "<=" & I$2, Продажи!$F$2:$F$1002, ">" & I$2) -> 0 | ... AD56: =COUNTIFS(Продажи!$B$2:$B$1002, $A56, Продажи!$E$2:$E$1002, "<=" & AD$2, Продажи!$F$2:$F$1002, ">" & AD$2) -> 0 | AE56: =SUM(B56:AD56) -> 0 | AF56: =IF(SUM(OFFSET($B56, 0, VLOOKUP("Станция отправления",Продажи!$R$2:$T$31,3,0)-1, 1, VLOOKUP("Станция прибытия",Продажи!$R$2:$T$31,3,0)-VLOOKUP("Станция отправления",Продажи!$R$2:$T$31,3,0)))=0, "Свободно", "Мест нет") -> Свободно | AG56: =VLOOKUP(A56,ID_купе[],2,0) -> 1 | AH56: =IF(AF56="Мест нет", "Занято", IF(COUNTIFS($AG$3:$AG$56, AG56, $AF$3:$AF$56, "Свободно") = COUNTIF($AG$3:$AG$56, AG56), "Целое купе/отсек", "Частично")) -> Частично
B57: =SUM(B3:B56) -> 12 | C57: =SUM(C3:C56) -> 13 | D57: =SUM(D3:D56) -> 13 | E57: =SUM(E3:E56) -> 15 | F57: =SUM(F3:F56) -> 15 | G57: =SUM(G3:G56) -> 15 | H57: =SUM(H3:H56) -> 14 | I57: =SUM(I3:I56) -> 14 | ... AD57: =SUM(AD3:AD56) -> 10

Sheet Справочник
A1: ID | B1: Станция (остановка) | C1: Расстояние от Мск (км) | D1: Длина перегона (км) | E1: Сбор: Вода (₽) | F1: Сбор: Септик (₽) | G1: Примечание | I1: № места | J1: № купе | L1: Статья затрат | M1: Стоимость | P1: Наименование | Q1: Цена | R1: Описание
A2: 1 | B2: Москва (Казанский) | C2: 0 | D2: 0 | E2: 0 | F2: 0 | G2: Старт | I2: 1 | J2: 1 | L2: Комплект белья (расход на 1 билет).: | M2: 250 | P2: Базовая ставка: | Q2: 800
A3: 2 | B3: Рязань 2 | C3: 198 | D3: =Справочник_станций_и_сборов[[#This Row],[Расстояние от Мск (км)]]-C2 -> 198 | E3: 0 | F3: 0 | I3: 2 | J3: 1 | L3: ФОТ (2 проводника, за рейс): | M3: 30000 | P3: Стоимость км: | Q3: 3.5
A4: 3 | B4: Ряжск 1 | C4: 314 | D4: =Справочник_станций_и_сборов[[#This Row],[Расстояние от Мск (км)]]-C3 -> 116 | E4: 0 | F4: 0 | I4: 3 | J4: 1 | L4: ТО вагона: | M4: 4000 | P4: Сервисный сбор: | Q4: 250
A5: 4 | B5: Мичуринск-Вор. | C5: 410 | D5: =Справочник_станций_и_сборов[[#This Row],[Расстояние от Мск (км)]]-C4 -> 96 | E5: 1500 | F5: 0 | G5: Заправка водой | I5: 4 | J5: 1 | L5: Амортизация: | M5: 2000 | P5: Вагонный буфет проводника | Q5: 150
A6: 5 | B6: Грязи-Воронежские | C6: 471 | D6: =Справочник_станций_и_сборов[[#This Row],[Расстояние от Мск (км)]]-C5 -> 61 | E6: 0 | F6: 0 | I6: 5 | J6: 2 | L6: Энергия (тяга)(за 1 км пути вагона.): | M6: 15
A7: 6 | B7: Воронеж 1 | C7: 589 | D7: =Справочник_станций_и_сборов[[#This Row],[Расстояние от Мск (км)]]-C6 -> 118 | E7: 1200 | F7: 1000 | G7: Тех. обслуживание | I7: 6 | J7: 2 | P7: Наименование | Q7: Цена | R7: Описание
A8: 7 | B8: Лиски | C8: 687 | D8: =Справочник_станций_и_сборов[[#This Row],[Расстояние от Мск (км)]]-C7 -> 98 | E8: 0 | F8: 0 | I8: 7 | J8: 2 | L8: Станция отправления | P8: Полный | Q8: 0
A9: 8 | B9: Пухово | C9: 715 | D9: =Справочник_станций_и_сборов[[#This Row],[Расстояние от Мск (км)]]-C8 -> 28 | E9: 0 | F9: 0 | I9: 8 | J9: 2 | L9: Станция прибытия | P9: Дети (до 10 лет): | Q9: 0.35 | R9: Скидка 65% от тарифа.
A10: 9 | B10: Евдаково | C10: 745 | D10: =Справочник_станций_и_сборов[[#This Row],[Расстояние от Мск (км)]]-C9 -> 30 | E10: 0 | F10: 0 | I10: 9 | J10: 3 | P10: Младенцы (до 5 лет): | Q10: 1 | R10: Бесплатно (без занятия места), но в системе они отражаются с ценой 0.
A11: 10 | B11: Сагуны | C11: 772 | D11: =Справочник_станций_и_сборов[[#This Row],[Расстояние от Мск (км)]]-C10 -> 27 | E11: 0 | F11: 0 | I11: 10 | J11: 3 | P11: Школьники/Студенты: | Q11: 0.5 | R11: Скидка 50% (обычно действует в учебный период, с сентября по май).
A12: 11 | B12: Подгорное | C12: 794 | D12: =Справочник_станций_и_сборов[[#This Row],[Расстояние от Мск (км)]]-C11 -> 22 | E12: 0 | F12: 0 | I12: 11 | J12: 3 | P12: Пенсионеры / Инвалиды: | Q12: 0.25 | R12: Идут по спецтарифам или талонам соцстрахования.
A13: 12 | B13: Россошь | C13: 823 | D13: =Справочник_станций_и_сборов[[#This Row],[Расстояние от Мск (км)]]-C12 -> 29 | E13: 1200 | F13: 0 | G13: Заправка водой | I13: 12 | J13: 3
A14: 13 | B14: Райновская | C14: 850 | D14: =Справочник_станций_и_сборов[[#This Row],[Расстояние от Мск (км)]]-C13 -> 27 | E14: 0 | F14: 0 | I14: 13 | J14: 4
A15: 14 | B15: Кантемировка | C15: 888 | D15: =Справочник_станций_и_сборов[[#This Row],[Расстояние от Мск (км)]]-C14 -> 38 | E15: 0 | F15: 0 | I15: 14 | J15: 4 | P15: Тип полки | Q15: Коэф-нт цены | R15: Примечание
A16: 15 | B16: Чертково | C16: 930 | D16: =Справочник_станций_и_сборов[[#This Row],[Расстояние от Мск (км)]]-C15 -> 42 | E16: 0 | F16: 0 | I16: 15 | J16: 4 | P16: Нижнее место | Q16: 0 | R16: Базовая цена
A17: 16 | B17: Миллерово | C17: 996 | D17: =Справочник_станций_и_сборов[[#This Row],[Расстояние от Мск (км)]]-C16 -> 66 | E17: 0 | F17: 0 | I17: 16 | J17: 4 | P17: Верхнее место | Q17: 0.1 | R17: Скидка 10%
A18: 17 | B18: Тарасовка | C18: 1018 | D18: =Справочник_станций_и_сборов[[#This Row],[Расстояние от Мск (км)]]-C17 -> 22 | E18: 0 | F18: 0 | I18: 17 | J18: 5 | P18: Нижнее боковое место | Q18: 0.15 | R18: Скидка 15%
A19: 18 | B19: Глубокая | C19: 1042 | D19: =Справочник_станций_и_сборов[[#This Row],[Расстояние от Мск (км)]]-C18 -> 24 | E19: 0 | F19: 0 | I19: 18 | J19: 5 | P19: Верхнее боковое место | Q19: 0.2 | R19: Скидка 20%
A20: 19 | B20: Каменская | C20: 1065 | D20: =Справочник_станций_и_сборов[[#This Row],[Расстояние от Мск (км)]]-C19 -> 23 | E20: 0 | F20: 800 | G20: Откачка баков | I20: 19 | J20: 5
A21: 20 | B21: Лихая | C21: 1089 | D21: =Справочник_станций_и_сборов[[#This Row],[Расстояние от Мск (км)]]-C20 -> 24 | E21: 0 | F21: 0 | I21: 20 | J21: 5
A22: 21 | B22: Замчалово | C22: 1101 | D22: =Справочник_станций_и_сборов[[#This Row],[Расстояние от Мск (км)]]-C21 -> 12 | E22: 0 | F22: 0 | I22: 21 | J22: 6
A23: 22 | B23: Зверево | C23: 1109 | D23: =Справочник_станций_и_сборов[[#This Row],[Расстояние от Мск (км)]]-C22 -> 8 | E23: 0 | F23: 0 | I23: 22 | J23: 6
A24: 23 | B24: Сулин | C24: 1128 | D24: =Справочник_станций_и_сборов[[#This Row],[Расстояние от Мск (км)]]-C23 -> 19 | E24: 0 | F24: 0 | I24: 23 | J24: 6
A25: 24 | B25: Шахтная | C25: 1157 | D25: =Справочник_станций_и_сборов[[#This Row],[Расстояние от Мск (км)]]-C24 -> 29 | E25: 0 | F25: 0 | I25: 24 | J25: 6
A26: 25 | B26: Каменоломни | C26: 1165 | D26: =Справочник_станций_и_сборов[[#This Row],[Расстояние от Мск (км)]]-C25 -> 8 | E26: 0 | F26: 0 | I26: 25 | J26: 7
A27: 26 | B27: Персиановка | C27: 1182 | D27: =Справочник_станций_и_сборов[[#This Row],[Расстояние от Мск (км)]]-C26 -> 17 | E27: 0 | F27: 0 | I27: 26 | J27: 7
A28: 27 | B28: Хотунок | C28: 1190 | D28: =Справочник_станций_и_сборов[[#This Row],[Расстояние от Мск (км)]]-C27 -> 8 | E28: 0 | F28: 0 | I28: 27 | J28: 7
A29: 28 | B29: Новочеркасск | C29: 1195 | D29: =Справочник_станций_и_сборов[[#This Row],[Расстояние от Мск (км)]]-C28 -> 5 | E29: 0 | F29: 0 | I29: 28 | J29: 7
A30: 29 | B30: Александровка | C30: 1218 | D30: =Справочник_станций_и_сборов[[#This Row],[Расстояние от Мск (км)]]-C29 -> 23 | E30: 0 | F30: 0 | I30: 29 | J30: 8
A31: 30 | B31: Ростов-Главный | C31: 1230 | D31: =Справочник_станций_и_сборов[[#This Row],[Расстояние от Мск (км)]]-C30 -> 12 | E31: 0 | F31: 0 | G31: Финиш | I31: 30 | J31: 8
A32: Итог | C32: =SUBTOTAL(109,Справочник_станций_и_сборов[Расстояние от Мск (км)]) -> 26071 | D32: =SUBTOTAL(109,Справочник_станций_и_сборов[Длина перегона (км)]) -> 1230 | E32: =SUBTOTAL(109,Справочник_станций_и_сборов[Сбор: Вода (₽)]) -> 3900 | F32: =SUBTOTAL(109,Справочник_станций_и_сборов[Сбор: Септик (₽)]) -> 1800 | G32: =SUBTOTAL(103,Справочник_станций_и_сборов[Примечание]) -> 6 | I32: 31 | J32: 8
I33: 32 | J33: 8
I34: 33 | J34: 9
I35: 34 | J35: 9
I36: 35 | J36: 9
I37: 36 | J37: 9
I38: 37 | J38: 9
I39: 38 | J39: 9
I40: 39 | J40: 8
I41: 40 | J41: 8
I42: 41 | J42: 7
I43: 42 | J43: 7
I44: 43 | J44: 6
... I55: 54 | J55: 1

Sheet P&L Отчет
B2: 1. Доходы (Revenue)
B3: Статья | C3: Сумма, руб | D3: Описание
B4: Выручка от билетов | C4: =Sales[[#Totals],[Цена, ₽]] -> 68437.75 | D4: Сумма всех проданных билетов
B5: Продажа чая/сувениров | C5: =Sales[[#Totals],[Место]]*Справочник!$Q$5 -> 4050 | D5: Условно 150₽ прибыли с каждого пассажира
B6: ИТОГО ДОХОД | C6: =SUM(C4:C5) -> 72487.75 | D6: Брутто выручка
B8: 2. Расходы (Expenses)
B9: Статья | C9: Сумма, руб | D9: Описание
B10: ФОТ (2 проводника) | C10: =Справочник!$M$3 -> 30000 | D10: Фикс за рейс (2 проводника)
B11: Стирка белья | C11: =Sales[[#Totals],[Место]]*250 -> 6750 | D11: Стирка комплекта на каждого севшего
B12: Станционные сборы | C12: =Справочник_станций_и_сборов[[#Totals],[Сбор: Вода (₽)]]+Справочник_станций_и_сборов[[#Totals],[Сбор: Септик (₽)]] -> 5700 | D12: Из твоей первой таблицы
B13: Энергия / Тяга | C13: =Справочник_станций_и_сборов[[#Totals],[Длина перегона (км)]]*Справочник!$M$6 -> 18450 | D13: Расход на движение вагона (15₽ за 1 км)
B14: ТО и Амортизация | C14: =Справочник!$M$4+Справочник!$M$5 -> 6000 | D14: Износ вагона за рейс
B15: ИТОГО РАСХОД | C15: =SUM(C10:C14) -> 66900 | D15: Себестоимость рейса
B17: 3. Главные показатели (KPI)
B18: Метрики | C18: Показатели | D18: Описание
B19: Чистая прибыль: | C19: =C6-C15 -> 5587.75 | D19: ИТОГО ДОХОД - ИТОГО РАСХОД.
B20: Средний чек: | C20: =Sales[[#Totals],[Цена, ₽]]/Sales[[#Totals],[Место]] -> 2534.7315 | D20: Выручка общая / Количество билетов.
B21: Доход на 1 км: | C21: =C6/Справочник_станций_и_сборов[[#Totals],[Длина перегона (км)]] -> 58.93313 | D21: Выручка / Общий пробег.
B22: Рентабельность: | C22: =(C19/C6)*100% -> 0.077085439 | D22: Чистая прибыль / ИТОГО ДОХОД) * 100%. (Хороший показатель для вагона — 15–25%).
B23: Коэффициент загрузки (Load Factor): | C23: =SUM(Аналитика!B3:AD56) / (54 * 29) -> 0.23371648 | D23: На сколько процентов в среднем был заполнен вагон за весь путь
B24: Точка безубыточности (чел): | C24: =C15/(C4/Sales[[#Totals],[Место]]) -> 26.393328 | D24: Сколько билетов нужно продать, чтобы выйти в 0.

Sheet Сводная по местам
A3: Число элементов в столбце Цена, ₽ | B3: Названия столбцов
A4: Названия строк | B4: (пусто) | C4: 0 | D4: 1 | E4: 2 | F4: 3 | G4: 4 | H4: 5 | I4: 6 | J4: 7 | K4: 8 | L4: 9 | M4: 10 | N4: 11 | O4: 12 | P4: 13 | Q4: 14 | R4: 18 | S4: 25 | T4: 33 | U4: 39 | V4: Общий итог
A5: (пусто)
A6: (пусто) | B6: 29 | V6: 29
A7: Воронеж 1
A8: Глубокая | I8: 1 | V8: 1
A9: Ростов-Главный | E9: 1 | R9: 1 | V9: 2
A10: Грязи-Воронежские
A11: Новочеркасск | P11: 1 | V11: 1
A12: Каменская
A13: Ростов-Главный | G13: 1 | V13: 1
A14: Лиски
A15: Россошь | F15: 1 | V15: 1
A16: Миллерово
A17: Шахтная | Q17: 1 | V17: 1
A18: Мичуринск-Вор.
A19: Лиски | F19: 1 | V19: 1
A20: Сулин | U20: 1 | V20: 1
A21: Чертково | H21: 1 | V21: 1
A22: Москва (Казанский)
A23: Воронеж 1 | E23: 1 | I23: 1 | L23: 1 | V23: 3
A24: Грязи-Воронежские | T24: 1 | V24: 1
A25: Лиски | K25: 1 | V25: 1
A26: Миллерово | J26: 1 | V26: 1
A27: Мичуринск-Вор. | F27: 1 | V27: 1
A28: Ростов-Главный | C28: 1 | D28: 1 | M28: 1 | N28: 1 | O28: 1 | V28: 5
A29: Чертково | Q29: 1 | V29: 1
A30: Россошь
A31: Ростов-Главный | F31: 1 | V31: 1
A32: Рязань 2
A33: Каменская | G33: 1 | V33: 1
A34: Хотунок
A35: Ростов-Главный | S35: 1 | V35: 1
A36: Чертково
A37: Ростов-Главный | H37: 1 | V37: 1
A38: Общий итог | B38: 29 | C38: 1 | D38: 1 | E38: 2 | F38: 4 | G38: 2 | H38: 2 | I38: 2 | J38: 1 | K38: 1 | L38: 1 | M38: 1 | N38: 1 | O38: 1 | P38: 1 | Q38: 2 | R38: 1 | S38: 1 | T38: 1 | U38: 1 | V38: 56
